Workbook
Name _Hlk138419189: 'Mail Dashboard'!$A$53
Name Check10: 'Mail Dashboard'!$A$69
Name Check13: 'Mail Dashboard'!$A$73
Name Check16: 'Mail Dashboard'!$C$76
Name Check17: 'Mail Dashboard'!$B$75
Name Check18: 'Mail Dashboard'!$B$79
Name Check19: 'Mail Dashboard'!$A$81
Name Check20: 'Mail Dashboard'!$D$82
Name Check21: 'Mail Dashboard'!$I$82
Name Check22: 'Mail Dashboard'!$F$83
Name Check23: 'Mail Dashboard'!$H$83
Name Check24: 'Mail Dashboard'!$E$84
Name Check25: 'Mail Dashboard'!$G$84
Name Check26: 'Mail Dashboard'!$A$93
Name Check27: 'Mail Dashboard'!$A$94
Name Check28: 'Mail Dashboard'!$A$95
Name Check29: 'Mail Dashboard'!$A$96
Name Check30: 'Mail Dashboard'!$A$99
Name Check31: 'Mail Dashboard'!$B$99
Name Text10: 'Mail Dashboard'!$B$65
Name Text11: 'Mail Dashboard'!$B$73
Name Text12: 'Mail Dashboard'!$B$81
Name Text18: 'Mail Dashboard'!$B$55
Name Text2: 'Mail Dashboard'!$C$55
Name Text20: 'Mail Dashboard'!$C$93
Name Text21: 'Mail Dashboard'!$E$93
Name Text22: 'Mail Dashboard'!$C$95
Name Text23: 'Mail Dashboard'!$E$96
Name Text24: 'Mail Dashboard'!$C$99

Sheet Pension Calculator
A1: California Ironworkers Field Pension Trust Pension Calculation
A2: Member Name: | C2: Rigoberto Pimentel | H2: Member ID: | I2: 320395X00
A3: Member Date of Birth: | C3: 23105
A4: Member Age at Retirement: | C4: =DATEDIF(C3,C5,"y")&"/"&(DATEDIF(C3,C5, "m") - (DATEDIF(C3,C5, "y") * 12)) -> 62/3
A5: Member Retirement Date: | C5: 45870
A6: Spouse Name: | C6: Perla S. Pimentel | G6: =IF(C7=0,"","Spouse Age Difference from Member:") -> Spouse Age Difference from Member: | J6: =IF(C7=0,"",IF(AND(C3-C7<0,(DATEDIF(C3,C5,"m")-(DATEDIF(C3,C5,"y")*12))-(DATEDIF(C7,C5,"m")-(DATEDIF(C7,C5,"y")*12))=0),DATEDIF(C3,C5,"y")-DATEDIF(C7,C5,"y"),IF(AND(C3-C7>0,(DATEDIF(C7,C5,"m")-(DATEDIF(C7,C5,"y")*12))-(DATEDIF(C3,C5,"m")-(DATEDIF(C3,C5,"y")*12))=0),DATEDIF(C7,C5,"y")-DATEDIF(C3,C5,"y"),IF(C3-C7<0,ROUNDDOWN(YEARFRAC(C3,C7),0),IF(C3-C7>0,ROUNDDOWN(YEARFRAC(C7,C3),0),0))))) -> 8 | K6: =IF(C7=0,"",IF(J6=0,"No Difference.",IF(C3-C7<0,"Year(s) Younger.", IF(C3-C7>0, "Year(s) Older.","No Difference.")))) -> Year(s) Younger.
A7: Spouse Date of Birth: | C7: 26366
A8: =IF(COUNTIF(C7,""),"","Spouse Age at Retirement:") -> Spouse Age at Retirement: | C8: =IF(COUNTIF(C7,""),"",DATEDIF(C7,C5,"y")&"/"&(DATEDIF(C7,C5,"m")-(DATEDIF(C7,C5,"y")*12))) -> 53/4 | D8: 8. Service Pension Pre-Age 55 & Disability Pension
A9: Credits Earned Prior to 09/01/2011 | D9: Benefit Calculation | I9: =IF(COUNTIF(C7,""),"",IF(COUNTIF(D8,"1.*"),"Early Retirement H&W Pension Options",IF(COUNTIF(D8,"2.*"),"Regular at 62 H&W Pension Options",IF(COUNTIF(D8,"3.*"),"Regular at 62 & Early H&W Pension Options",IF(COUNTIF(D8,"4.*"),"Regular at 62 H&W Pension Options",IF(COUNTIF(D8,"5.*"),"Regular at 65 H&W Pension Options",IF(COUNTIF(D8,"6.*"),"Disability H&W Pension Options",IF(COUNTIF(D8,"7.*"),"Service Pre-Age 55 H&W Pension Options",IF(COUNTIF(D8,"8.*"),"Service Pre-Age 55 H&W Pension Options",IF(COUNTIF(D8,"9.*"),"Service H&W Pension Options","Additional H&W Options")))))))))) -> Service Pre-Age 55 H&W Pension Options
A10: CA Credits | B10: Rate | C10: Value | D10: Total Pension Credits | H10: =SUM(A11:A17,A20:A21,A24:A29) -> 7.33 | I10: =IF(COUNTIF(C7,""),"","Option") -> Option | J10: =IF(COUNTIF(C7,""),"","Factor") -> Factor | K10: =IF(COUNTIF(C7,""),"","Member Benefit") -> Member Benefit | L10: =IF(COUNTIF(C7,""),"","Spouse Benefit") -> Spouse Benefit
C11: =A11*B11 -> 0 | D11: Member Benefit Prior to 09/01/2011 | G11: =SUM(A11:A17) -> 7.33 | H11: =C18 -> 876 | I11: =IF(COUNTIF(C7,""),"","50%") -> 50% | J11: =IF(COUNTIF(C7,""),"",IF(COUNTIF(D8,"4.*"),IF(COUNTIF(K6,"*Younger*"),100%-8%-(J6*0.4%),IF(100%-8%+(J6*0.4%)>100%,100%,100%-8%+(J6*0.4%)))*100&"% / "&IF(COUNTIF(K6,"*Younger*"),100%-18%-(J6*0.4%),IF(100%-18%+(J6*0.4%)>100%,100%,100%-18%+(J6*0.4%)))*100&"%",IF(COUNTIF(D8,"6.*"),IF(COUNTIF(K6,"*Younger*"),100%-18%-(J6*0.4%),IF(100%-18%+(J6*0.4%)>100%,100%,100%-18%+(J6*0.4%))),IF(COUNTIF(D8,"8.*"),IF(COUNTIF(K6,"*Younger*"),100%-8%-(J6*0.4%),IF(100%-8%+(J6*0.4%)>100%,100%,100%-8%+(J6*0.4%)))*100&"% / "&IF(COUNTIF(K6,"*Younger*"),100%-18%-(J6*0.4%),IF(100%-18%+(J6*0.4%)>100%,100%,100%-18%+(J6*0.4%)))*100&"%",IF(COUNTIF(K6,"*Younger*"),100%-8%-(J6*0.4%),IF(100%-8%+(J6*0.4%)>100%,100%,100%-8%+(J6*0.4%))))))) -> 88.8% / 78.8% | K11: =IF(COUNTIF(C7,""),"",IF(COUNTIF(D8,"1.*"),(H13+H16+H19)*J11,IF(COUNTIF(D8,"2.*"),(H11)*J11,IF(COUNTIF(D8,"3.*"),(H11+H16+H19)*J11,IF(COUNTIF(D8,"5.*"),(H11+H14+H17)*J11,IF(COUNTIF(D8,"6.*"),(H11+H14+H17)*J11,IF(COUNTIF(D8,"7.*"),(H11+H14)*J11,IF(COUNTIF(D8,"8.*"),(H11+H14)*IF(COUNTIF(K6,"*Younger*"),100%-8%-(J6*0.4%),IF(100%-8%+(J6*0.4%)>100%,100%,100%-8%+(J6*0.4%)))+(H17*IF(COUNTIF(K6,"*Younger*"),100%-18%-(J6*0.4%),IF(100%-18%+(J6*0.4%)>100%,100%,100%-18%+(J6*0.4%)))),IF(COUNTIF(D8,"4.*"),H11*IF(COUNTIF(K6,"*Younger*"),100%-8%-(J6*0.4%),IF(100%-8%+(J6*0.4%)>100%,100%,100%-8%+(J6*0.4%)))+(H14+H17)*IF(COUNTIF(K6,"*Younger*"),100%-18%-(J6*0.4%),IF(100%-18%+(J6*0.4%)>100%,100%,100%-18%+(J6*0.4%))),IF(COUNTIF(D8,"9.*"),(H11+H14+H17)*J11,"")))))))))) -> 777.888 | L11: =IF(COUNTIF(C7,""),"",K11*I11) -> 388.944
C12: =A12*B12 -> 0 | D12: =IF(COUNTIF(D8,"1.*"),"ER Factor","") | H12: =IF(COUNTIF(D8,"1.*"),IF(DATEDIF(C3,C5,"m")<=600,(DATEDIF(C3,C5,"m")-540)*0.1%+40%,IF(DATEDIF(C3,C5,"m")<=660,(DATEDIF(C3,C5,"m")-600)*0.2%+46%,IF((DATEDIF(C3,C5,"m")-660)*0.5%+58%>=100%,100%,(DATEDIF(C3,C5,"m")-660)*0.5%+58%))),"") | I12: =IF(COUNTIF(C7,""),"","13th Check") -> 13th Check | J12: =IF(COUNTIF(C7,""),"",IF(COUNTIF(D8,"4.*"),IF(COUNTIF(K6,"*Younger*"),100%-8%-(J6*0.4%),IF(100%-8%+(J6*0.4%)>100%,100%,100%-8%+(J6*0.4%)))*100&"% / "&IF(COUNTIF(K6,"*Younger*"),100%-18%-(J6*0.4%),IF(100%-18%+(J6*0.4%)>100%,100%,100%-18%+(J6*0.4%)))*100&"%",IF(COUNTIF(D8,"6.*"),IF(COUNTIF(K6,"*Younger*"),100%-18%-(J6*0.4%),IF(100%-18%+(J6*0.4%)>100%,100%,100%-18%+(J6*0.4%))),IF(COUNTIF(D8,"8.*"),IF(COUNTIF(K6,"*Younger*"),100%-8%-(J6*0.4%),IF(100%-8%+(J6*0.4%)>100%,100%,100%-8%+(J6*0.4%)))*100&"% / "&IF(COUNTIF(K6,"*Younger*"),100%-18%-(J6*0.4%),IF(100%-18%+(J6*0.4%)>100%,100%,100%-18%+(J6*0.4%)))*100&"%",IF(COUNTIF(K6,"*Younger*"),100%-8%-(J6*0.4%),IF(100%-8%+(J6*0.4%)>100%,100%,100%-8%+(J6*0.4%))))))) -> 88.8% / 78.8% | K12: =IF(COUNTIF(C7,""),"",IF(COUNTIF(D8,"1.*"),(H13+H16+H19)*J12,IF(COUNTIF(D8,"2.*"),(H11)*J12,IF(COUNTIF(D8,"3.*"),(H11+H16+H19)*J12,IF(COUNTIF(D8,"5.*"),(H11+H14+H17)*J12,IF(COUNTIF(D8,"6.*"),(H11+H14+H17)*J12,IF(COUNTIF(D8,"7.*"),(H11+H14)*J12,IF(COUNTIF(D8,"8.*"),(H11+H14)*IF(COUNTIF(K6,"*Younger*"),100%-8%-(J6*0.4%),IF(100%-8%+(J6*0.4%)>100%,100%,100%-8%+(J6*0.4%)))+(H17*IF(COUNTIF(K6,"*Younger*"),100%-18%-(J6*0.4%),IF(100%-18%+(J6*0.4%)>100%,100%,100%-18%+(J6*0.4%)))),IF(COUNTIF(D8,"4.*"),H11*IF(COUNTIF(K6,"*Younger*"),100%-8%-(J6*0.4%),IF(100%-8%+(J6*0.4%)>100%,100%,100%-8%+(J6*0.4%)))+(H14+H17)*IF(COUNTIF(K6,"*Younger*"),100%-18%-(J6*0.4%),IF(100%-18%+(J6*0.4%)>100%,100%,100%-18%+(J6*0.4%))),IF(COUNTIF(D8,"9.*"),(H11+H14+H17)*J12,"")))))))))) -> 777.888 | L12: =IF(COUNTIF(C7,""),"",K12*I11) -> 388.944
C13: =A13*B13 -> 0 | D13: =IF(COUNTIF(D8,"1.*"),"ER Benefit Prior to 09/01/2011","") | H13: =IF(COUNTIF(D8,"1.*"),(H11*H12),"") | I13: =IF(COUNTIF(C7,""),"","75%") -> 75% | J13: =IF(COUNTIF(C7,""),"",IF(COUNTIF(D8,"4.*"),IF(COUNTIF(K6,"*Younger*"),100%-12%-(J6*0.4%),IF(100%-12%+(J6*0.4%)>100%,100%,100%-12%+(J6*0.4%)))*100&"% / "&IF(COUNTIF(K6,"*Younger*"),100%-24%-(J6*0.4%),IF(100%-24%+(J6*0.4%)>100%,100%,100%-24%+(J6*0.4%)))*100&"%",IF(COUNTIF(D8,"6.*"),IF(COUNTIF(K6,"*Younger*"),100%-24%-(J6*0.4%),IF(100%-24%+(J6*0.4%)>100%,100%,100%-24%+(J6*0.4%))),IF(COUNTIF(D8,"8.*"),IF(COUNTIF(K6,"*Younger*"),100%-12%-(J6*0.4%),IF(100%-12%+(J6*0.4%)>100%,100%,100%-12%+(J6*0.4%)))*100&"% / "&IF(COUNTIF(K6,"*Younger*"),100%-24%-(J6*0.4%),IF(100%-24%+(J6*0.4%)>100%,100%,100%-24%+(J6*0.4%)))*100&"%",IF(COUNTIF(K6,"*Younger*"),100%-12%-(J6*0.4%),IF(100%-12%+(J6*0.4%)>100%,100%,100%-12%+(J6*0.4%))))))) -> 84.8% / 72.8% | K13: =IF(COUNTIF(C7,""),"",IF(COUNTIF(D8,"1.*"),(H13+H16+H19)*J13,IF(COUNTIF(D8,"2.*"),(H11)*J13,IF(COUNTIF(D8,"3.*"),(H11+H16+H19)*J13,IF(COUNTIF(D8,"5.*"),(H11+H14+H17)*J13,IF(COUNTIF(D8,"6.*"),(H11+H14+H17)*J13,IF(COUNTIF(D8,"7.*"),(H11+H14)*J13,IF(COUNTIF(D8,"8.*"),(H11+H14)*IF(COUNTIF(K6,"*Younger*"),100%-12%-(J6*0.4%),IF(100%-12%+(J6*0.4%)>100%,100%,100%-12%+(J6*0.4%)))+(H17*IF(COUNTIF(K6,"*Younger*"),100%-24%-(J6*0.4%),IF(100%-24%+(J6*0.4%)>100%,100%,100%-24%+(J6*0.4%)))),IF(COUNTIF(D8,"4.*"),H11*IF(COUNTIF(K6,"*Younger*"),100%-12%-(J6*0.4%),IF(100%-12%+(J6*0.4%)>100%,100%,100%-12%+(J6*0.4%)))+(H14+H17)*IF(COUNTIF(K6,"*Younger*"),100%-24%-(J6*0.4%),IF(100%-24%+(J6*0.4%)>100%,100%,100%-24%+(J6*0.4%))),IF(COUNTIF(D8,"9.*"),(H11+H14+H17)*J13,"")))))))))) -> 742.848 | L13: =IF(COUNTIF(C7,""),"",K13*I13) -> 557.136
B14: 50 | C14: =A14*B14 -> 0 | D14: ="Member Benefit from 09/01/2011 to 09/30/2014" -> Member Benefit from 09/01/2011 to 09/30/2014 | G14: =SUM(A20:A21) -> 0 | H14: =C22 -> 0 | I14: =IF(COUNTIF(C7,""),"","13th Check") -> 13th Check | J14: =IF(COUNTIF(C7,""),"",IF(COUNTIF(D8,"4.*"),IF(COUNTIF(K6,"*Younger*"),100%-12%-(J6*0.4%),IF(100%-12%+(J6*0.4%)>100%,100%,100%-12%+(J6*0.4%)))*100&"% / "&IF(COUNTIF(K6,"*Younger*"),100%-24%-(J6*0.4%),IF(100%-24%+(J6*0.4%)>100%,100%,100%-24%+(J6*0.4%)))*100&"%",IF(COUNTIF(D8,"6.*"),IF(COUNTIF(K6,"*Younger*"),100%-24%-(J6*0.4%),IF(100%-24%+(J6*0.4%)>100%,100%,100%-24%+(J6*0.4%))),IF(COUNTIF(D8,"8.*"),IF(COUNTIF(K6,"*Younger*"),100%-12%-(J6*0.4%),IF(100%-12%+(J6*0.4%)>100%,100%,100%-12%+(J6*0.4%)))*100&"% / "&IF(COUNTIF(K6,"*Younger*"),100%-24%-(J6*0.4%),IF(100%-24%+(J6*0.4%)>100%,100%,100%-24%+(J6*0.4%)))*100&"%",IF(COUNTIF(K6,"*Younger*"),100%-12%-(J6*0.4%),IF(100%-12%+(J6*0.4%)>100%,100%,100%-12%+(J6*0.4%))))))) -> 84.8% / 72.8% | K14: =IF(COUNTIF(C7,""),"",IF(COUNTIF(D8,"1.*"),(H13+H16+H19)*J14,IF(COUNTIF(D8,"2.*"),(H11)*J14,IF(COUNTIF(D8,"3.*"),(H11+H16+H19)*J14,IF(COUNTIF(D8,"5.*"),(H11+H14+H17)*J14,IF(COUNTIF(D8,"6.*"),(H11+H14+H17)*J14,IF(COUNTIF(D8,"7.*"),(H11+H14)*J14,IF(COUNTIF(D8,"8.*"),(H11+H14)*IF(COUNTIF(K6,"*Younger*"),100%-12%-(J6*0.4%),IF(100%-12%+(J6*0.4%)>100%,100%,100%-12%+(J6*0.4%)))+(H17*IF(COUNTIF(K6,"*Younger*"),100%-24%-(J6*0.4%),IF(100%-24%+(J6*0.4%)>100%,100%,100%-24%+(J6*0.4%)))),IF(COUNTIF(D8,"4.*"),H11*IF(COUNTIF(K6,"*Younger*"),100%-12%-(J6*0.4%),IF(100%-12%+(J6*0.4%)>100%,100%,100%-12%+(J6*0.4%)))+(H14+H17)*IF(COUNTIF(K6,"*Younger*"),100%-24%-(J6*0.4%),IF(100%-24%+(J6*0.4%)>100%,100%,100%-24%+(J6*0.4%))),IF(COUNTIF(D8,"9.*"),(H11+H14+H17)*J14,"")))))))))) -> 742.848 | L14: =IF(COUNTIF(C7,""),"",K14*I13) -> 557.136
A15: 5.75 | B15: 118 | C15: =A15*B15 -> 678.5 | D15: =IF(OR(COUNTIF(D8,"1.*"),COUNTIF(D8,"2.*"),COUNTIF(D8,"3.*")),"ER Factor","") | H15: =IF(OR(COUNTIF(D8,"1.*"),COUNTIF(D8,"2.*"),COUNTIF(D8,"3.*")),IF(DATEDIF(C3,C5,"m")<=600,(DATEDIF(C3,C5,"m")-540)*0.1%+22%,IF(DATEDIF(C3,C5,"m")<=660,(DATEDIF(C3,C5,"m")-600)*0.2%+28%,IF((DATEDIF(C3,C5,"m")-660)*0.5%+40%>=100%,100%,(DATEDIF(C3,C5,"m")-660)*0.5%+40%))),"") | I15: =IF(COUNTIF(C7,""),"","100%") -> 100% | J15: =IF(COUNTIF(C7,""),"",IF(COUNTIF(D8,"4.*"),IF(COUNTIF(K6,"*Younger*"),100%-15%-(J6*0.5%),IF(100%-15%+(J6*0.5%)>100%,100%,100%-15%+(J6*0.5%)))*100&"% / "&IF(COUNTIF(K6,"*Younger*"),100%-30%-(J6*0.5%),IF(100%-30%+(J6*0.5%)>100%,100%,100%-30%+(J6*0.5%)))*100&"%",IF(COUNTIF(D8,"6.*"),IF(COUNTIF(K6,"*Younger*"),100%-30%-(J6*0.5%),IF(100%-30%+(J6*0.5%)>100%,100%,100%-30%+(J6*0.5%))),IF(COUNTIF(D8,"8.*"),IF(COUNTIF(K6,"*Younger*"),100%-15%-(J6*0.5%),IF(100%-15%+(J6*0.5%)>100%,100%,100%-15%+(J6*0.5%)))*100&"% / "&IF(COUNTIF(K6,"*Younger*"),100%-30%-(J6*0.5%),IF(100%-30%+(J6*0.5%)>100%,100%,100%-30%+(J6*0.5%)))*100&"%",IF(COUNTIF(K6,"*Younger*"),100%-15%-(J6*0.5%),IF(100%-15%+(J6*0.5%)>100%,100%,100%-15%+(J6*0.5%))))))) -> 81% / 66% | K15: =IF(COUNTIF(C7,""),"",IF(COUNTIF(D8,"1.*"),(H13+H16+H19)*J15,IF(COUNTIF(D8,"2.*"),(H11)*J15,IF(COUNTIF(D8,"3.*"),(H11+H16+H19)*J15,IF(COUNTIF(D8,"5.*"),(H11+H14+H17)*J15,IF(COUNTIF(D8,"6.*"),(H11+H14+H17)*J15,IF(COUNTIF(D8,"7.*"),(H11+H14)*J15,IF(COUNTIF(D8,"8.*"),(H11+H14)*IF(COUNTIF(K6,"*Younger*"),100%-15%-(J6*0.5%),IF(100%-15%+(J6*0.5%)>100%,100%,100%-15%+(J6*0.5%)))+(H17*IF(COUNTIF(K6,"*Younger*"),100%-30%-(J6*0.5%),IF(100%-30%+(J6*0.5%)>100%,100%,100%-30%+(J6*0.5%)))),IF(COUNTIF(D8,"4.*"),H11*IF(COUNTIF(K6,"*Younger*"),100%-15%-(J6*0.5%),IF(100%-15%+(J6*0.5%)>100%,100%,100%-15%+(J6*0.5%)))+(H14+H17)*IF(COUNTIF(K6,"*Younger*"),100%-30%-(J6*0.5%),IF(100%-30%+(J6*0.5%)>100%,100%,100%-30%+(J6*0.5%))),IF(COUNTIF(D8,"9.*"),(H11+H14+H17)*J15,"")))))))))) -> 709.56 | L15: =IF(COUNTIF(C7,""),"",K15*I15) -> 709.56
B16: 105 | C16: =A16*B16 -> 0 | D16: =IF(OR(COUNTIF(D8,"1.*"),COUNTIF(D8,"2.*"),COUNTIF(D8,"3.*")),"ER Benefit from 09/01/2011 to 09/30/2014","") | H16: =IF(OR(COUNTIF(D8,"1.*"),COUNTIF(D8,"2.*"),COUNTIF(D8,"3.*")),H14*H15,"") | I16: =IF(COUNTIF(C7,""),"","13th Check") -> 13th Check | J16: =IF(COUNTIF(C7,""),"",IF(COUNTIF(D8,"4.*"),IF(COUNTIF(K6,"*Younger*"),100%-15%-(J6*0.5%),IF(100%-15%+(J6*0.5%)>100%,100%,100%-15%+(J6*0.5%)))*100&"% / "&IF(COUNTIF(K6,"*Younger*"),100%-30%-(J6*0.5%),IF(100%-30%+(J6*0.5%)>100%,100%,100%-30%+(J6*0.5%)))*100&"%",IF(COUNTIF(D8,"6.*"),IF(COUNTIF(K6,"*Younger*"),100%-30%-(J6*0.5%),IF(100%-30%+(J6*0.5%)>100%,100%,100%-30%+(J6*0.5%))),IF(COUNTIF(D8,"8.*"),IF(COUNTIF(K6,"*Younger*"),100%-15%-(J6*0.5%),IF(100%-15%+(J6*0.5%)>100%,100%,100%-15%+(J6*0.5%)))*100&"% / "&IF(COUNTIF(K6,"*Younger*"),100%-30%-(J6*0.5%),IF(100%-30%+(J6*0.5%)>100%,100%,100%-30%+(J6*0.5%)))*100&"%",IF(COUNTIF(K6,"*Younger*"),100%-15%-(J6*0.5%),IF(100%-15%+(J6*0.5%)>100%,100%,100%-15%+(J6*0.5%))))))) -> 81% / 66% | K16: =IF(COUNTIF(C7,""),"",IF(COUNTIF(D8,"1.*"),(H13+H16+H19)*J16,IF(COUNTIF(D8,"2.*"),(H11)*J16,IF(COUNTIF(D8,"3.*"),(H11+H16+H19)*J16,IF(COUNTIF(D8,"5.*"),(H11+H14+H17)*J16,IF(COUNTIF(D8,"6.*"),(H11+H14+H17)*J16,IF(COUNTIF(D8,"7.*"),(H11+H14)*J16,IF(COUNTIF(D8,"8.*"),(H11+H14)*IF(COUNTIF(K6,"*Younger*"),100%-15%-(J6*0.5%),IF(100%-15%+(J6*0.5%)>100%,100%,100%-15%+(J6*0.5%)))+(H17*IF(COUNTIF(K6,"*Younger*"),100%-30%-(J6*0.5%),IF(100%-30%+(J6*0.5%)>100%,100%,100%-30%+(J6*0.5%)))),IF(COUNTIF(D8,"4.*"),H11*IF(COUNTIF(K6,"*Younger*"),100%-15%-(J6*0.5%),IF(100%-15%+(J6*0.5%)>100%,100%,100%-15%+(J6*0.5%)))+(H14+H17)*IF(COUNTIF(K6,"*Younger*"),100%-30%-(J6*0.5%),IF(100%-30%+(J6*0.5%)>100%,100%,100%-30%+(J6*0.5%))),IF(COUNTIF(D8,"9.*"),(H11+H14+H17)*J16,"")))))))))) -> 709.56 | L16: =IF(COUNTIF(C7,""),"",K16*I15) -> 709.56
A17: 1.58 | B17: 125 | C17: =A17*B17 -> 197.5 | D17: ="Member Benefit on and After 10/01/2014" -> Member Benefit on and After 10/01/2014 | G17: =SUM(A24:A29) -> 0 | H17: =C30 -> 0
A18: =SUM(A11:A17) -> 7.33 | B18: Subtotal | C18: =SUM(C11:C17) -> 876 | D18: =IF(OR(COUNTIF(D8,"1.*"),COUNTIF(D8,"2.*"),COUNTIF(D8,"3.*"),COUNTIF(D8,"7.*")),"ER Factor","") | H18: =IF(OR(COUNTIF(D8,"1.*"),COUNTIF(D8,"2.*"),COUNTIF(D8,"3.*"),COUNTIF(D8,"7.*")),IF(DATEDIF(C3,C5,"m")<=600,(DATEDIF(C3,C5,"m")-540)*0.1%+22%,IF(DATEDIF(C3,C5,"m")<=660,(DATEDIF(C3,C5,"m")-600)*0.2%+28%,IF((DATEDIF(C3,C5,"m")-660)*0.5%+40%>=100%,100%,(DATEDIF(C3,C5,"m")-660)*0.5%+40%))),"") | I18: =IF(COUNTIF(C7,""),"",IF(COUNTIF(D8,"1.*"),"Pension Benefit Deferred at Age 65 H&W Options",IF(COUNTIF(D8,"2.*"),"Regular at 62 & Early H&W Options",IF(OR(COUNTIF(D8,"3.*"),COUNTIF(D8,"7.*")),"Pension Benefit Regular at 62 with Early H&W Options",IF(COUNTIF(D8,"4.*"),"Disability after 09/01/2011 H&W Options",IF(COUNTIF(D8,"8.*"),"Disability after 10/01/2014 H&W Options","")))))) -> Disability after 10/01/2014 H&W Options
A19: Credits Earned On or After 09/01/2011 | D19: =IF(OR(COUNTIF(D8,"1.*"),COUNTIF(D8,"2.*"),COUNTIF(D8,"3.*"),COUNTIF(D8,"7.*")),"ER Benefit on or After 10/01/2014","") | H19: =IF(OR(COUNTIF(D8,"1.*"),COUNTIF(D8,"2.*"),COUNTIF(D8,"3.*"),COUNTIF(D8,"7.*")),H17*H18,"") | I19: =IF(COUNTIF(C7,""),"",IF(OR(COUNTIF(D8,"1.*"),COUNTIF(D8,"2.*"),COUNTIF(D8,"3.*"),COUNTIF(D8,"7.*"),COUNTIF(D8,"8.*")),"Option","")) -> Option | J19: =IF(COUNTIF(C7,""),"",IF(OR(COUNTIF(D8,"1.*"),COUNTIF(D8,"2.*"),COUNTIF(D8,"3.*"),COUNTIF(D8,"7.*"),COUNTIF(D8,"8.*")),"Factor","")) -> Factor | K19: =IF(COUNTIF(C7,""),"",IF(OR(COUNTIF(D8,"1.*"),COUNTIF(D8,"2.*"),COUNTIF(D8,"3.*"),COUNTIF(D8,"7.*"),COUNTIF(D8,"8.*")),"Member Benefit","")) -> Member Benefit | L19: =IF(COUNTIF(C7,""),"",IF(OR(COUNTIF(D8,"1.*"),COUNTIF(D8,"2.*"),COUNTIF(D8,"3.*"),COUNTIF(D8,"7.*"),COUNTIF(D8,"8.*")),"Spouse Benefit","")) -> Spouse Benefit
B20: 90 | C20: =A20*B20 -> 0 | I20: =IF(COUNTIF(C7,""),"",IF(OR(COUNTIF(D8,"1.*"),COUNTIF(D8,"2.*"),COUNTIF(D8,"3.*"),COUNTIF(D8,"7.*"),COUNTIF(D8,"8.*")),"50%","")) -> 50% | J20: =IF(COUNTIF(C7,""),"",IF(OR(COUNTIF(D8,"1.*"),COUNTIF(D8,"2.*"),COUNTIF(D8,"3.*"),COUNTIF(D8,"7.*")),IF(COUNTIF(K6,"*Younger*"),100%-8%-(J6*0.4%),IF(100%-8%+(J6*0.4%)>100%,100%,100%-8%+(J6*0.4%))),IF(OR(COUNTIF(D8,"4.*"),COUNTIF(D8,"8.*")),IF(COUNTIF(K6,"*Younger*"),100%-18%-(J6*0.4%),IF(100%-18%+(J6*0.4%)>100%,100%,100%-18%+(J6*0.4%))),""))) -> 0.788 | K20: =IF(COUNTIF(C7,""),"",IF(COUNTIF(D8,"1.*"),(H27*J20),IF(COUNTIF(D8,"2.*"),(H11+H16+H19)*J20,IF(COUNTIF(D8,"3.*"),(H11+H14+H17)*J20,IF(COUNTIF(D8,"7.*"),(H11+H14+H19)*J20,""))))) | L20: =IF(COUNTIF(C7,""),"",IF(OR(COUNTIF(D8,"1.*"),COUNTIF(D8,"2.*"),COUNTIF(D8,"3.*"),COUNTIF(D8,"7.*")),K20*I20,""))
B21: 125 | C21: =A21*B21 -> 0 | D21: =IF(COUNTIF(D8,"1.*"),"Member Early Retirement Pension Amount",IF(COUNTIF(D8,"2.*"),"Member Regular Retirement Pension at 62 Amount",IF(COUNTIF(D8,"3.*"),"Member Regular at 62 & Early Retirement Pension Amount",IF(COUNTIF(D8,"4.*"),"Member Regular Retirement at 62 & Disability Pension Amount",IF(COUNTIF(D8,"5.*"),"Member Regular Retirement Pension at 65 Amount",IF(COUNTIF(D8,"6.*"),"Member Disability Pension Amount",IF(COUNTIF(D8,"7.*"),"Member Pre-Age 55 Service",IF(COUNTIF(D8,"8.*"),"Member Pre-Age 55 Service & Disability Pension Amount",IF(COUNTIF(D8,"9.*"),"Member Service Pension Amount",""))))))))) -> Member Pre-Age 55 Service & Disability Pension Amount | H21: =IF(COUNTIF(D8,"1.*"),SUM(H13,H16,H19),IF(COUNTIF(D8,"2.*"),H11,IF(COUNTIF(D8,"3.*"),SUM(H11,H16,H19),IF(COUNTIF(D8,"4.*"),SUM(H11,H14,H17),IF(COUNTIF(D8,"5.*"),SUM(H11,H14,H17),IF(COUNTIF(D8,"6.*"),SUM(H11,H14,H17),IF(COUNTIF(D8,"7.*"),SUM(H11,H14),IF(COUNTIF(D8,"8.*"),SUM(H11,H14,H17),IF(COUNTIF(D8,"9.*"),SUM(H11,H14,H17),""))))))))) -> 876 | I21: =IF(COUNTIF(C7,""),"",IF(OR(COUNTIF(D8,"1.*"),COUNTIF(D8,"2.*"),COUNTIF(D8,"3.*"),COUNTIF(D8,"7.*"),COUNTIF(D8,"8.*")),"13th Check","")) -> 13th Check | J21: =IF(COUNTIF(C7,""),"",IF(OR(COUNTIF(D8,"1.*"),COUNTIF(D8,"2.*"),COUNTIF(D8,"3.*"),COUNTIF(D8,"7.*")),IF(COUNTIF(K6,"*Younger*"),100%-8%-(J6*0.4%),IF(100%-8%+(J6*0.4%)>100%,100%,100%-8%+(J6*0.4%))),IF(OR(COUNTIF(D8,"4.*"),COUNTIF(D8,"8.*")),IF(COUNTIF(K6,"*Younger*"),100%-18%-(J6*0.4%),IF(100%-18%+(J6*0.4%)>100%,100%,100%-18%+(J6*0.4%))),""))) -> 0.788 | K21: =IF(COUNTIF(C7,""),"",IF(COUNTIF(D8,"1.*"),(H27*J21),IF(COUNTIF(D8,"2.*"),(H11+H16+H19)*J21,IF(COUNTIF(D8,"3.*"),(H11+H14+H17)*J21,IF(COUNTIF(D8,"7.*"),(H11+H14+H19)*J21,""))))) | L21: =IF(COUNTIF(C7,""),"",IF(OR(COUNTIF(D8,"1.*"),COUNTIF(D8,"2.*"),COUNTIF(D8,"3.*"),COUNTIF(D8,"7.*")),K21*I20,""))
A22: =SUM(A20:A21) -> 0 | B22: Subtotal | C22: =SUM(C20:C21) -> 0 | D22: Member 13th Check | H22: =IF(COUNTIF(D8,"1.*"),SUM(H13,H16,H19),IF(COUNTIF(D8,"2.*"),H11,IF(COUNTIF(D8,"3.*"),SUM(H11,H16,H19),IF(COUNTIF(D8,"4.*"),SUM(H11,H14,H17),IF(COUNTIF(D8,"5.*"),SUM(H11,H14,H17),IF(COUNTIF(D8,"6.*"),SUM(H11,H14,H17),IF(COUNTIF(D8,"7.*"),SUM(H11,H14),IF(COUNTIF(D8,"8.*"),SUM(H11,H14,H17),IF(COUNTIF(D8,"9.*"),SUM(H11,H14,H17),""))))))))) -> 876 | I22: =IF(COUNTIF(C7,""),"",IF(OR(COUNTIF(D8,"1.*"),COUNTIF(D8,"2.*"),COUNTIF(D8,"3.*"),COUNTIF(D8,"7.*"),COUNTIF(D8,"8.*")),"75%","")) -> 75% | J22: =IF(COUNTIF(C7,""),"",IF(OR(COUNTIF(D8,"1.*"),COUNTIF(D8,"2.*"),COUNTIF(D8,"3.*"),COUNTIF(D8,"7.*")),IF(COUNTIF(K6,"*Younger*"),100%-12%-(J6*0.4%),IF(100%-12%+(J6*0.4%)>100%,100%,100%-12%+(J6*0.4%))),IF(OR(COUNTIF(D8,"4.*"),COUNTIF(D8,"8.*")),IF(COUNTIF(K6,"*Younger*"),100%-24%-(J6*0.4%),IF(100%-24%+(J6*0.4%)>100%,100%,100%-24%+(J6*0.4%))),""))) -> 0.728 | K22: =IF(COUNTIF(C7,""),"",IF(COUNTIF(D8,"1.*"),(H27*J22),IF(COUNTIF(D8,"2.*"),(H11+H16+H19)*J22,IF(COUNTIF(D8,"3.*"),(H11+H14+H17)*J22,IF(COUNTIF(D8,"7.*"),(H11+H14+H19)*J22,""))))) | L22: =IF(COUNTIF(C7,""),"",IF(OR(COUNTIF(D8,"1.*"),COUNTIF(D8,"2.*"),COUNTIF(D8,"3.*"),COUNTIF(D8,"7.*")),K22*I22,""))
A23: Credits Earned On or After 10/01/2014 | I23: =IF(COUNTIF(C7,""),"",IF(OR(COUNTIF(D8,"1.*"),COUNTIF(D8,"2.*"),COUNTIF(D8,"3.*"),COUNTIF(D8,"7.*"),COUNTIF(D8,"8.*")),"13th Check","")) -> 13th Check | J23: =IF(COUNTIF(C7,""),"",IF(OR(COUNTIF(D8,"1.*"),COUNTIF(D8,"2.*"),COUNTIF(D8,"3.*"),COUNTIF(D8,"7.*")),IF(COUNTIF(K6,"*Younger*"),100%-12%-(J6*0.4%),IF(100%-12%+(J6*0.4%)>100%,100%,100%-12%+(J6*0.4%))),IF(OR(COUNTIF(D8,"4.*"),COUNTIF(D8,"8.*")),IF(COUNTIF(K6,"*Younger*"),100%-24%-(J6*0.4%),IF(100%-24%+(J6*0.4%)>100%,100%,100%-24%+(J6*0.4%))),""))) -> 0.728 | K23: =IF(COUNTIF(C7,""),"",IF(COUNTIF(D8,"1.*"),(H27*J23),IF(COUNTIF(D8,"2.*"),(H11+H16+H19)*J23,IF(COUNTIF(D8,"3.*"),(H11+H14+H17)*J23,IF(COUNTIF(D8,"7.*"),(H11+H14+H19)*J23,""))))) | L23: =IF(COUNTIF(C7,""),"",IF(OR(COUNTIF(D8,"1.*"),COUNTIF(D8,"2.*"),COUNTIF(D8,"3.*"),COUNTIF(D8,"7.*")),K23*I22,""))
B24: 105 | C24: =A24*B24 -> 0 | D24: =IF(COUNTIF(D8,"2.*"),"Member Regular Retirement Pension at 62 with Early",IF(COUNTIF(D8,"7.*"),"Member Service Pension Pre-Age 55 with Early","")) | H24: =IF(COUNTIF(D8,"2.*"),H11+H16+H19,IF(COUNTIF(D8,"7.*"),H11+H14+H19,"")) | I24: =IF(COUNTIF(C7,""),"",IF(OR(COUNTIF(D8,"1.*"),COUNTIF(D8,"2.*"),COUNTIF(D8,"3.*"),COUNTIF(D8,"7.*"),COUNTIF(D8,"8.*")),"100%","")) -> 100% | J24: =IF(COUNTIF(C7,""),"",IF(OR(COUNTIF(D8,"1.*"),COUNTIF(D8,"2.*"),COUNTIF(D8,"3.*"),COUNTIF(D8,"7.*")),IF(COUNTIF(K6,"*Younger*"),100%-15%-(J6*0.5%),IF(100%-15%+(J6*0.5%)>100%,100%,100%-15%+(J6*0.5%))),IF(OR(COUNTIF(D8,"4.*"),COUNTIF(D8,"8.*")),IF(COUNTIF(K6,"*Younger*"),100%-30%-(J6*0.5%),IF(100%-30%+(J6*0.5%)>100%,100%,100%-30%+(J6*0.5%))),""))) -> 0.66 | K24: =IF(COUNTIF(C7,""),"",IF(COUNTIF(D8,"1.*"),(H27*J24),IF(COUNTIF(D8,"2.*"),(H11+H16+H19)*J24,IF(COUNTIF(D8,"3.*"),(H11+H14+H17)*J24,IF(COUNTIF(D8,"7.*"),(H11+H14+H19)*J24,""))))) | L24: =IF(COUNTIF(C7,""),"",IF(OR(COUNTIF(D8,"1.*"),COUNTIF(D8,"2.*"),COUNTIF(D8,"3.*"),COUNTIF(D8,"7.*")),K24*I24,""))
B25: 125 | C25: =A25*B25 -> 0 | D25: =IF(OR(COUNTIF(D8,"2.*"),COUNTIF(D8,"7.*")),"Member 13th Check","") | H25: =IF(COUNTIF(D8,"2.*"),H11+H16+H19,IF(COUNTIF(D8,"7.*"),H11+H14+H19,"")) | I25: =IF(COUNTIF(C7,""),"",IF(OR(COUNTIF(D8,"1.*"),COUNTIF(D8,"2.*"),COUNTIF(D8,"3.*"),COUNTIF(D8,"7.*"),COUNTIF(D8,"8.*")),"13th Check","")) -> 13th Check | J25: =IF(COUNTIF(C7,""),"",IF(OR(COUNTIF(D8,"1.*"),COUNTIF(D8,"2.*"),COUNTIF(D8,"3.*"),COUNTIF(D8,"7.*")),IF(COUNTIF(K6,"*Younger*"),100%-15%-(J6*0.5%),IF(100%-15%+(J6*0.5%)>100%,100%,100%-15%+(J6*0.5%))),IF(OR(COUNTIF(D8,"4.*"),COUNTIF(D8,"8.*")),IF(COUNTIF(K6,"*Younger*"),100%-30%-(J6*0.5%),IF(100%-30%+(J6*0.5%)>100%,100%,100%-30%+(J6*0.5%))),""))) -> 0.66 | K25: =IF(COUNTIF(C7,""),"",IF(COUNTIF(D8,"1.*"),(H27*J25),IF(COUNTIF(D8,"2.*"),(H11+H16+H19)*J25,IF(COUNTIF(D8,"3.*"),(H11+H14+H17)*J25,IF(COUNTIF(D8,"7.*"),(H11+H14+H19)*J25,""))))) | L25: =IF(COUNTIF(C7,""),"",IF(OR(COUNTIF(D8,"1.*"),COUNTIF(D8,"2.*"),COUNTIF(D8,"3.*"),COUNTIF(D8,"7.*")),K25*I24,""))
B26: 135 | C26: =A26*B26 -> 0
C27: =A27*B27 -> 0 | D27: =IF(OR(COUNTIF(D8,"1.*"),COUNTIF(D8,"2.*"),COUNTIF(D8,"3.*"),COUNTIF(D8,"7.*")),"Member Benefit Deferred at Age 65","") | H27: =IF(OR(COUNTIF(D8,"1.*"),COUNTIF(D8,"2.*"),COUNTIF(D8,"3.*"),COUNTIF(D8,"7.*")),SUM(H11,H14,H17),"") | I27: =IF(COUNTIF(C7,""),"",IF(OR(COUNTIF(D8,"2.*"),COUNTIF(D8,"7.*")),"Pension Benefit Deferred at Age 65 H&W Options",IF(COUNTIF(D8,"4.*"),"Regular at 62 & Disability H&W Combined Pension Options",IF(COUNTIF(D8,"8.*"),"Service Pre-Age 55 & Disability H&W Combined Pension Options","")))) -> Service Pre-Age 55 & Disability H&W Combined Pension Options
C28: =A28*B28 -> 0 | D28: =IF(OR(COUNTIF(D8,"1.*"),COUNTIF(D8,"2.*"),COUNTIF(D8,"3.*"),COUNTIF(D8,"7.*")),"Member 13th Check","") | H28: =IF(OR(COUNTIF(D8,"1.*"),COUNTIF(D8,"2.*"),COUNTIF(D8,"3.*"),COUNTIF(D8,"7.*")),SUM(H11,H14,H17),"") | I28: =IF(COUNTIF(C7,""),"",IF(OR(COUNTIF(D8,"2.*"),COUNTIF(D8,"7.*"),COUNTIF(D8,"8.*")),"Option","")) -> Option | J28: =IF(COUNTIF(C7,""),"",IF(OR(COUNTIF(D8,"2.*"),COUNTIF(D8,"7.*"),COUNTIF(D8,"8.*")),"Factor","")) -> Factor | K28: =IF(COUNTIF(C7,""),"",IF(OR(COUNTIF(D8,"2.*"),COUNTIF(D8,"7.*"),COUNTIF(D8,"8.*")),"Member Benefit","")) -> Member Benefit | L28: =IF(COUNTIF(C7,""),"",IF(OR(COUNTIF(D8,"2.*"),COUNTIF(D8,"7.*"),COUNTIF(D8,"8.*")),"Spouse Benefit","")) -> Spouse Benefit
C29: =A29*B29 -> 0 | I29: =IF(COUNTIF(C7,""),"",IF(OR(COUNTIF(D8,"2.*"),COUNTIF(D8,"7.*"),COUNTIF(D8,"8.*")),"50%","")) -> 50% | J29: =IF(COUNTIF(C7,""),"",IF(OR(COUNTIF(D8,"2.*"),COUNTIF(D8,"7.*")),IF(COUNTIF(K6,"*Younger*"),100%-8%-(J6*0.4%),IF(100%-8%+(J6*0.4%)>100%,100%,100%-8%+(J6*0.4%))),"")) | K29: =IF(COUNTIF(C7,""),"",IF(OR(COUNTIF(D8,"2.*"),COUNTIF(D8,"7.*")),((H11+H14+H17)*J29),"")) | L29: =IF(COUNTIF(C7,""),"",IF(OR(COUNTIF(D8,"2.*"),COUNTIF(D8,"7.*")),K29*I29,""))
A30: =SUM(A24:A29) -> 0 | B30: Subtotal | C30: =SUM(C24:C29) -> 0 | I30: =IF(COUNTIF(C7,""),"",IF(OR(COUNTIF(D8,"2.*"),COUNTIF(D8,"7.*"),COUNTIF(D8,"8.*")),"13th Check","")) -> 13th Check | J30: =IF(COUNTIF(C7,""),"",IF(OR(COUNTIF(D8,"2.*"),COUNTIF(D8,"7.*")),IF(COUNTIF(K6,"*Younger*"),100%-8%-(J6*0.4%),IF(100%-8%+(J6*0.4%)>100%,100%,100%-8%+(J6*0.4%))),"")) | K30: =IF(COUNTIF(C7,""),"",IF(OR(COUNTIF(D8,"2.*"),COUNTIF(D8,"7.*")),((H11+H14+H17)*J30),"")) | L30: =IF(COUNTIF(C7,""),"",IF(OR(COUNTIF(D8,"2.*"),COUNTIF(D8,"7.*")),K30*I29,""))
A31: =SUM(A18,A22,A30) -> 7.33 | B31: Total | C31: =SUM(C18,C22,C30) -> 876 | I31: =IF(COUNTIF(C7,""),"",IF(OR(COUNTIF(D8,"2.*"),COUNTIF(D8,"7.*"),COUNTIF(D8,"8.*")),"75%","")) -> 75% | J31: =IF(COUNTIF(C7,""),"",IF(OR(COUNTIF(D8,"2.*"),COUNTIF(D8,"7.*")),IF(COUNTIF(K6,"*Younger*"),100%-12%-(J6*0.4%),IF(100%-12%+(J6*0.4%)>100%,100%,100%-12%+(J6*0.4%))),"")) | K31: =IF(COUNTIF(C7,""),"",IF(OR(COUNTIF(D8,"2.*"),COUNTIF(D8,"7.*")),((H11+H14+H17)*J31),"")) | L31: =IF(COUNTIF(C7,""),"",IF(OR(COUNTIF(D8,"2.*"),COUNTIF(D8,"7.*")),K31*I31,""))
I32: =IF(COUNTIF(C7,""),"",IF(OR(COUNTIF(D8,"2.*"),COUNTIF(D8,"7.*"),COUNTIF(D8,"8.*")),"13th Check","")) -> 13th Check | J32: =IF(COUNTIF(C7,""),"",IF(OR(COUNTIF(D8,"2.*"),COUNTIF(D8,"7.*")),IF(COUNTIF(K6,"*Younger*"),100%-12%-(J6*0.4%),IF(100%-12%+(J6*0.4%)>100%,100%,100%-12%+(J6*0.4%))),"")) | K32: =IF(COUNTIF(C7,""),"",IF(OR(COUNTIF(D8,"2.*"),COUNTIF(D8,"7.*")),((H11+H14+H17)*J32),"")) | L32: =IF(COUNTIF(C7,""),"",IF(OR(COUNTIF(D8,"2.*"),COUNTIF(D8,"7.*")),K32*I31,""))
I33: =IF(COUNTIF(C7,""),"",IF(OR(COUNTIF(D8,"2.*"),COUNTIF(D8,"7.*"),COUNTIF(D8,"8.*")),"100%","")) -> 100% | J33: =IF(COUNTIF(C7,""),"",IF(OR(COUNTIF(D8,"2.*"),COUNTIF(D8,"7.*")),IF(COUNTIF(K6,"*Younger*"),100%-15%-(J6*0.5%),IF(100%-15%+(J6*0.5%)>100%,100%,100%-15%+(J6*0.5%))),"")) | K33: =IF(COUNTIF(C7,""),"",IF(OR(COUNTIF(D8,"2.*"),COUNTIF(D8,"7.*")),((H11+H14+H17)*J33),"")) | L33: =IF(COUNTIF(C7,""),"",IF(OR(COUNTIF(D8,"2.*"),COUNTIF(D8,"7.*")),K33*I33,""))
A34: Processed By: | B34: Alex Miles | E34: Checked By: | F34: Alex Miles | I34: =IF(COUNTIF(C7,""),"",IF(OR(COUNTIF(D8,"2.*"),COUNTIF(D8,"7.*"),COUNTIF(D8,"8.*")),"13th Check","")) -> 13th Check | J34: =IF(COUNTIF(C7,""),"",IF(OR(COUNTIF(D8,"2.*"),COUNTIF(D8,"7.*")),IF(COUNTIF(K6,"*Younger*"),100%-15%-(J6*0.5%),IF(100%-15%+(J6*0.5%)>100%,100%,100%-15%+(J6*0.5%))),"")) | K34: =IF(COUNTIF(C7,""),"",IF(OR(COUNTIF(D8,"2.*"),COUNTIF(D8,"7.*")),((H11+H14+H17)*J34),"")) | L34: =IF(COUNTIF(C7,""),"",IF(OR(COUNTIF(D8,"2.*"),COUNTIF(D8,"7.*")),K34*I33,""))
A36: Date: | B36: =TODAY() -> 46164 | E36: Date: | F36: =TODAY() -> 46164

Sheet Delayed
A1: California Ironworkers Field Pension Trust Pension Calculation | M1: Delayed Retirement Age 65 Pension Credit Separater
A2: Member Name: | C2: Richard E Hoitinga | H2: Member ID: | I2: 451973X00
A3: Member Date of Birth: | C3: 32593
A4: Member Age at Retirement: | C4: =DATEDIF(C3,C5,"y")&"/"&(DATEDIF(C3,C5, "m") - (DATEDIF(C3,C5, "y") * 12)) -> 65/0
A5: Member Retirement Date: | C5: 56340
A6: Spouse Name: | C6: Brooklyn A Hoitinga | G6: =IF(COUNTIF(C7,""),"","Spouse Age Difference from Member:") -> Spouse Age Difference from Member: | J6: =IF(C7=0,"",IF(AND(C3-C7<0,(DATEDIF(C3,C5,"m")-(DATEDIF(C3,C5,"y")*12))-(DATEDIF(C7,C5,"m")-(DATEDIF(C7,C5,"y")*12))=0),DATEDIF(C3,C5,"y")-DATEDIF(C7,C5,"y"),IF(AND(C3-C7>0,(DATEDIF(C7,C5,"m")-(DATEDIF(C7,C5,"y")*12))-(DATEDIF(C3,C5,"m")-(DATEDIF(C3,C5,"y")*12))=0),DATEDIF(C7,C5,"y")-DATEDIF(C3,C5,"y"),IF(C3-C7<0,ROUNDDOWN(YEARFRAC(C3,C7),0),IF(C3-C7>0,ROUNDDOWN(YEARFRAC(C7,C3),0),0))))) -> 2 | K6: =IF(C7=0,"",IF(J6=0,"No Difference.",IF(C3-C7<0,"Year(s) Younger.", IF(C3-C7>0, "Year(s) Older.","No Difference.")))) -> Year(s) Younger.
A7: Spouse Date of Birth: | C7: 33410
A8: =IF(COUNTIF(C7,""),"","Spouse Age at Retirement:") -> Spouse Age at Retirement: | C8: =IF(COUNTIF(C7,""),"",DATEDIF(C7,C5,"y")&"/"&(DATEDIF(C7,C5,"m")-(DATEDIF(C7,C5,"y")*12))) -> 62/9
A9: Credits Earned Prior to 09/01/2011 | D9: Delayed Pension Benefit Calculation | I9: =IF(COUNTIF(C7,""),"","Delayed 1 H&W Pension Options") -> Delayed 1 H&W Pension Options | M9: Plan Year | N9: =IF(MONTH(H18)>5,YEAR(H18)+1,YEAR(H18)) -> 2054
A10: CA Credits | B10: Rate | C10: Value | D10: Total Pension Credits | H10: =SUM(A11:A17,A20:A21,A24:A29,A33:A38) -> 44.38 | I10: =IF(COUNTIF(C7,""),"","Option") -> Option | J10: =IF(COUNTIF(C7,""),"","Factor") -> Factor | K10: =IF(COUNTIF(C7,""),"","Member Benefit") -> Member Benefit | L10: =IF(COUNTIF(C7,""),"","Spouse Benefit") -> Spouse Benefit | M10: Month | N10: Hours | O10: Pension Credits
C11: =A11*B11 -> 0 | D11: Member Benefit Prior to 09/01/2011 | G11: =SUM(A11:A17) -> 26.96 | H11: =SUM(C11:C17) -> 3208.79 | I11: =IF(COUNTIF(C7,""),"","50%") -> 50% | J11: =IF(COUNTIF(C7,""),"",IF(COUNTIF(K6,"*Younger*"),100%-8%-(J6*0.4%),IF(100%-8%+(J6*0.4%)>100%,100%,100%-8%+(J6*0.4%)))) -> 0.912 | K11: =IF(COUNTIF(C7,""),"",(C18+C22+C30+C39)*J11) -> 5031.6773 | L11: =IF(COUNTIF(C7,""),"",K11*I11) -> 2515.8386 | M11: =IF(AND(MONTH(H18)=5,DAY(H18)>1),"Member turned 65 in May",IF(AND(MONTH(H18)=5,DAY(H18)=1),"Member turned 65 at the start of May","May")) -> May | N11: 125 | O11: =IF(N9=2015,ROUND(ROUNDDOWN((SUM(N11))/117,0)/12,2),"")
C12: =A12*B12 -> 0 | I12: =IF(COUNTIF(C7,""),"","13th Check") -> 13th Check | J12: =IF(COUNTIF(C7,""),"",IF(COUNTIF(K6,"*Younger*"),100%-8%-(J6*0.4%),IF(100%-8%+(J6*0.4%)>100%,100%,100%-8%+(J6*0.4%)))) -> 0.912 | K12: =IF(COUNTIF(C7,""),"",(C18+C22+C30+C39)*J12) -> 5031.6773 | L12: =IF(COUNTIF(C7,""),"",K12*I11) -> 2515.8386 | M12: =IF(AND(MONTH(H18)=4,DAY(H18)>1),"Member turned 65 in April",IF(AND(MONTH(H18)=4,DAY(H18)=1),"Member turned 65 at the start April","April")) -> April | N12: 125 | O12: =IF(N9=2015,ROUND(ROUNDDOWN((SUM(N11:N12))/117,0)/12,2),"")
C13: =A13*B13 -> 0 | D13: Member Benefit from 09/01/2011 to 09/30/2014 | G13: =SUM(A20:A21) -> 4.33 | H13: =SUM(C20:C21) -> 541.25 | I13: =IF(COUNTIF(C7,""),"","75%") -> 75% | J13: =IF(COUNTIF(C7,""),"",IF(COUNTIF(K6,"*Younger*"),100%-12%-(J6*0.4%),IF(100%-12%+(J6*0.4%)>100%,100%,100%-12%+(J6*0.4%)))) -> 0.872 | K13: =IF(COUNTIF(C7,""),"",(C18+C22+C30+C39)*J13) -> 4810.9897 | L13: =IF(COUNTIF(C7,""),"",K13*I13) -> 3608.2423 | M13: =IF(AND(MONTH(H18)=3,DAY(H18)>1),"Member turned 65 in March",IF(AND(MONTH(H18)=3,DAY(H18)=1),"Member turned 65 at the start of March","March")) -> Member turned 65 in March | N13: 125 | O13: =IF(N9=2015,ROUND(ROUNDDOWN((SUM(N11:N13))/117,0)/12,2),"")
B14: 50 | C14: =A14*B14 -> 0 | I14: =IF(COUNTIF(C7,""),"","13th Check") -> 13th Check | J14: =IF(COUNTIF(C7,""),"",IF(COUNTIF(K6,"*Younger*"),100%-12%-(J6*0.4%),IF(100%-12%+(J6*0.4%)>100%,100%,100%-12%+(J6*0.4%)))) -> 0.872 | K14: =IF(COUNTIF(C7,""),"",(C18+C22+C30+C39)*J14) -> 4810.9897 | L14: =IF(COUNTIF(C7,""),"",K14*I13) -> 3608.2423 | M14: =IF(AND(MONTH(H18)=2,DAY(H18)>1),"Member turned 65 in February",IF(AND(MONTH(H18)=2,DAY(H18)=1),"Member turned 65 at the start February","February")) -> February | N14: 125 | O14: =IF(N9=2015,ROUND(ROUNDDOWN((SUM(N11:N14))/117,0)/12,2),"")
A15: 23.03 | B15: 118 | C15: =A15*B15 -> 2717.54 | D15: Member Benefit on or After 10/01/2014 | G15: =SUM(A24:A29,A33:A38) -> 13.09 | H15: =SUM(C24:C29,C33:C38) -> 1767.15 | I15: =IF(COUNTIF(C7,""),"","100%") -> 100% | J15: =IF(COUNTIF(C7,""),"",IF(COUNTIF(K6,"*Younger*"),100%-15%-(J6*0.5%),IF(100%-15%+(J6*0.5%)>100%,100%,100%-15%+(J6*0.5%)))) -> 0.84 | K15: =IF(COUNTIF(C7,""),"",(C18+C22+C30+C39)*J15) -> 4634.4396 | L15: =IF(COUNTIF(C7,""),"",K15*I15) -> 4634.4396 | M15: =IF(AND(MONTH(H18)=1,DAY(H18)>1),"Member turned 65 in January",IF(AND(MONTH(H18)=1,DAY(H18)=1),"Member turned 65 at the start of January","January")) -> January | N15: 125 | O15: =IF(N9=2015,(ROUND(ROUNDDOWN(SUM(N15)/125,0)/12,2)+(ROUND(ROUNDDOWN(SUM(N11:N14)/117,0)/12,2))),"")
B16: 105 | C16: =A16*B16 -> 0 | D16: Member Delayed Calculation 1 Monthly Amount | H16: =SUM(C11:C17,C20:C21,C24:C29,C33:C38) -> 5517.19 | I16: =IF(COUNTIF(C7,""),"","13th Check") -> 13th Check | J16: =IF(COUNTIF(C7,""),"",IF(COUNTIF(K6,"*Younger*"),100%-15%-(J6*0.5%),IF(100%-15%+(J6*0.5%)>100%,100%,100%-15%+(J6*0.5%)))) -> 0.84 | K16: =IF(COUNTIF(C7,""),"",(C18+C22+C30+C39)*J16) -> 4634.4396 | L16: =IF(COUNTIF(C7,""),"",K16*I15) -> 4634.4396 | M16: =IF(AND(MONTH(H18)=12,DAY(H18)>1),"Member turned 65 in December",IF(AND(MONTH(H18)=12,DAY(H18)=1),"Member turned 65 at the start of December","December")) -> December | N16: 125 | O16: =IF(N9=2015,(ROUND(ROUNDDOWN(SUM(N15:N16)/125,0)/12,2)+(ROUND(ROUNDDOWN(SUM(N11:N14)/117,0)/12,2))),"")
A17: 3.93 | B17: 125 | C17: =A17*B17 -> 491.25 | D17: Member Calculation 1 13th Check Amount | H17: =SUM(C11:C17,C20:C21,C24:C29,C33:C38) -> 5517.19 | M17: =IF(AND(MONTH(H18)=11,DAY(H18)>1),"Member turned 65 in November",IF(AND(MONTH(H18)=11,DAY(H18)=1),"Member turned 65 at the start of November","November")) -> November | N17: 125 | O17: =IF(N9=2015,(ROUND(ROUNDDOWN(SUM(N15:N17)/125,0)/12,2)+(ROUND(ROUNDDOWN(SUM(N11:N14)/117,0)/12,2))),"")
A18: =SUM(A11:A17) -> 26.96 | B18: Subtotal | C18: =SUM(C11:C17) -> 3208.79 | D18: Date member turned 65 | G18: =SUM(A11:A17,A20:A21,A24:A29) -> 43.05 | H18: =EDATE(C3, 65 * 12) -> 56334 | I18: =IF(COUNTIF(C7,""),"","Delayed 2 H&W Pension Options") -> Delayed 2 H&W Pension Options | M18: =IF(AND(MONTH(H18)=10,DAY(H18)>1),"Member turned 65 in October",IF(AND(MONTH(H18)=10,DAY(H18)=1),"Member turned 65 at the start of October","October")) -> October | N18: 125 | O18: =IF(N9=2015,(ROUND(ROUNDDOWN(SUM(N15:N18)/125,0)/12,2)+(ROUND(ROUNDDOWN(SUM(N11:N14)/117,0)/12,2))),"")
A19: Credits Earned On or After 09/01/2011 | D19: =IF(DATEDIF(C3,C5,"m")>=846,"Date member turned 70 1/2","") | H19: =IF(DATEDIF(C3,C5,"m")>=846,EDATE(C3,70*12+6),"") | I19: =IF(COUNTIF(C7,""),"","Option") -> Option | J19: =IF(COUNTIF(C7,""),"","Factor") -> Factor | K19: =IF(COUNTIF(C7,""),"","Member Benefit") -> Member Benefit | L19: =IF(COUNTIF(C7,""),"","Spouse Benefit") -> Spouse Benefit | M19: =IF(AND(MONTH(H18)=9,DAY(H18)>1),"Member turned 65 in September",IF(AND(MONTH(H18)=9,DAY(H18)=1),"Member turned 65 at the start of September","September")) -> September | N19: 125 | O19: =IF(N9=2015,(ROUND(ROUNDDOWN(SUM(N15:N19)/125,0)/12,2)+(ROUND(ROUNDDOWN(SUM(N11:N14)/117,0)/12,2))),"")
B20: 90 | C20: =A20*B20 -> 0 | D20: Pre-65 Monthly Pension Amount | H20: =SUM(C11:C17,C20:C21,C24:C29) -> 5337.64 | I20: =IF(COUNTIF(C7,""),"",50%) -> 0.5 | J20: =IF(COUNTIF(C7,""),"",IF(COUNTIF(K6,"*Younger*"),100%-8%-(J6*0.4%),IF(100%-8%+(J6*0.4%)>100%,100%,100%-8%+(J6*0.4%)))) -> 0.912 | K20: =IF(COUNTIF(C7,""),"",(((C18+C22+C30)*((H22*1%)+(H23*1.5%)))+(C18+C22+C30))*J20) -> 6717.7402 | L20: =IF(COUNTIF(C7,""),"",K20*I20) -> 3358.8701 | M20: =IF(AND(MONTH(H18)=8,DAY(H18)>1),"Member turned 65 in August",IF(AND(MONTH(H18)=8,DAY(H18)=1),"Member turned 65 at the start of August","August")) -> August | N20: 125 | O20: =IF(N9=2015,(ROUND(ROUNDDOWN(SUM(N15:N20)/125,0)/12,2)+(ROUND(ROUNDDOWN(SUM(N11:N14)/117,0)/12,2))),"")
A21: 4.33 | B21: 125 | C21: =A21*B21 -> 541.25 | D21: Pre-65 13th Check Amount | H21: =SUM(C11:C17,C20:C21,C24:C29) -> 5337.64 | I21: =IF(COUNTIF(C7,""),"","13th Check") -> 13th Check | J21: =IF(COUNTIF(C7,""),"",IF(COUNTIF(K6,"*Younger*"),100%-8%-(J6*0.4%),IF(100%-8%+(J6*0.4%)>100%,100%,100%-8%+(J6*0.4%)))) -> 0.912 | K21: =IF(COUNTIF(C7,""),"",(((C18+C22+C30)*((H22*1%)+(H23*1.5%)))+(C18+C22+C30))*J21) -> 6717.7402 | L21: =IF(COUNTIF(C7,""),"",K21*I20) -> 3358.8701 | M21: =IF(AND(MONTH(H18)=7,DAY(H18)>1),"Member turned 65 in July",IF(AND(MONTH(H18)=7,DAY(H18)=1),"Member turned 65 at the start of July","July")) -> July | N21: 125 | O21: =IF(N9=2015,(ROUND(ROUNDDOWN(SUM(N15:N21)/125,0)/12,2)+(ROUND(ROUNDDOWN(SUM(N11:N14)/117,0)/12,2))),"")
A22: =SUM(A20:A21) -> 4.33 | B22: Subtotal | C22: =SUM(C20:C21) -> 541.25 | D22: First 60 months with 40 hours or less (1.00%): | H22: 38 | I22: =IF(COUNTIF(C7,""),"","75%") -> 75% | J22: =IF(COUNTIF(C7,""),"",IF(COUNTIF(K6,"*Younger*"),100%-12%-(J6*0.4%),IF(100%-12%+(J6*0.4%)>100%,100%,100%-12%+(J6*0.4%)))) -> 0.872 | K22: =IF(COUNTIF(C7,""),"",(((C18+C22+C30)*((H22*1%)+(H23*1.5%)))+(C18+C22+C30))*J22) -> 6423.1025 | L22: =IF(COUNTIF(C7,""),"",K22*I22) -> 4817.3269 | M22: =IF(AND(MONTH(H18)=6,DAY(H18)>1),"Member turned 65 in June",IF(AND(MONTH(H18)=6,DAY(H18)=1),"Member turned 65 at the start of June","June")) -> June | N22: 125 | O22: =IF(N9=2015,(ROUND(ROUNDDOWN(SUM(N15:N22)/125,0)/12,2)+(ROUND(ROUNDDOWN(SUM(N11:N14)/117,0)/12,2))),"")
A23: Credits Earned On or After 10/01/2014 | D23: 61 + months with 40 hours or less (1.50%): | I23: =IF(COUNTIF(C7,""),"","13th Check") -> 13th Check | J23: =IF(COUNTIF(C7,""),"",IF(COUNTIF(K6,"*Younger*"),100%-12%-(J6*0.4%),IF(100%-12%+(J6*0.4%)>100%,100%,100%-12%+(J6*0.4%)))) -> 0.872 | K23: =IF(COUNTIF(C7,""),"",(((C18+C22+C30)*((H22*1%)+(H23*1.5%)))+(C18+C22+C30))*J23) -> 6423.1025 | L23: =IF(COUNTIF(C7,""),"",K23*I22) -> 4817.3269 | M23: ="Total hours and credits in PY "&IF(MONTH(H18)>5,YEAR(H18)+1,YEAR(H18)) -> Total hours and credits in PY 2054 | N23: =SUM(N11:N22) -> 1500 | O23: =IF(N9<2015,ROUND(ROUNDDOWN(N23/117,0)/12,2),IF(N9>2015,ROUND(ROUNDDOWN(N23/125,0)/12,2),(ROUNDDOWN(SUM(N11:N14/117,0)/12,2))+(ROUNDDOWN(SUM(N15:N22/125,0)/12,2)))) -> 1
B24: 105 | C24: =A24*B24 -> 0 | D24: Delayed Calc 2 Retirement Increase: | H24: =SUM(H22*1%)+(H23*1.5%) -> 0.38 | I24: =IF(COUNTIF(C7,""),"","100%") -> 100% | J24: =IF(COUNTIF(C7,""),"",IF(COUNTIF(K6,"*Younger*"),100%-15%-(J6*0.5%),IF(100%-15%+(J6*0.5%)>100%,100%,100%-15%+(J6*0.5%)))) -> 0.84 | K24: =IF(COUNTIF(C7,""),"",(((C18+C22+C30)*((H22*1%)+(H23*1.5%)))+(C18+C22+C30))*J24) -> 6187.3923 | L24: =IF(COUNTIF(C7,""),"",K24*I24) -> 6187.3923 | M24: Pre-65 hours total | N24: =IF(MONTH(H18)=6,IF(DAY(H18)=1,0,N22),IF(MONTH(H18)=7,IF(DAY(H18)=1,N22,SUM(N21:N22)),IF(MONTH(H18)=8,IF(DAY(H18)=1,SUM(N21:N22),SUM(N20:N22)),IF(MONTH(H18)=9,IF(DAY(H18)=1,SUM(N20:N22),SUM(N19:N22)),IF(MONTH(H18)=10,IF(DAY(H18)=1,SUM(N19:N22),SUM(N18:N22)),IF(MONTH(H18)=11,IF(DAY(H18)=1,SUM(N18:N22),SUM(N17:N22)),IF(MONTH(H18)=12,IF(DAY(H18)=1,SUM(N17:N22),SUM(N16:N22)),IF(MONTH(H18)=1,IF(DAY(H18)=1,SUM(N16:N22),SUM(N15:N22)),IF(MONTH(H18)=2,IF(DAY(H18)=1,SUM(N15:N22),SUM(N14:N22)),IF(MONTH(H18)=3,IF(DAY(H18)=1,SUM(N14:N22),SUM(N13:N22)),IF(MONTH(H18)=4,IF(DAY(H18)=1,SUM(N13:N22),SUM(N12:N22)),IF(MONTH(H18)=5,IF(DAY(H18)=1,SUM(N12:N22),SUM(N11:N22)))))))))))))) -> 1250 | O24: =IF(N9<2015,ROUND(ROUNDDOWN(N24/117,0)/12,2),IF(N9>2015,ROUND(ROUNDDOWN(N24/125,0)/12,2),ROUNDDOWN(SUM(N11:N14/117,0)/12,2)+ROUNDDOWN(SUM(N15:N22/125,0)/12,2))) -> 0.83
B25: 125 | C25: =A25*B25 -> 0 | D25: Delayed Benefit Increase | H25: =SUM(C18+C22+C30)*H24 -> 2028.3032 | I25: =IF(COUNTIF(C7,""),"","13th Check") -> 13th Check | J25: =IF(COUNTIF(C7,""),"",IF(COUNTIF(K6,"*Younger*"),100%-15%-(J6*0.5%),IF(100%-15%+(J6*0.5%)>100%,100%,100%-15%+(J6*0.5%)))) -> 0.84 | K25: =IF(COUNTIF(C7,""),"",(((C18+C22+C30)*((H22*1%)+(H23*1.5%)))+(C18+C22+C30))*J24) -> 6187.3923 | L25: =IF(COUNTIF(C7,""),"",K25*I24) -> 6187.3923 | M25: ="Credits earned Post-65 in PY "&IF(MONTH(H18)>5,YEAR(H18)+1,YEAR(H18)) -> Credits earned Post-65 in PY 2054 | O25: =O23-O24 -> 0.17
A26: 11.76 | B26: 135 | C26: =A26*B26 -> 1587.6 | D26: Delayed 13th Check Increase | H26: =SUM(C18+C22+C30)*H24 -> 2028.3032
C27: =A27*B27 -> 0 | D27: Delayed Calc 2 Member Benefit: | H27: =SUM(C18,C22,C30)*((H22*1%)+(H23*1.5%))+(C18+C22+C30) -> 7365.9432
C28: =A28*B28 -> 0 | D28: Delayed Calc 2 Member 13th Check: | H28: =SUM(C18,C22,C30)*((H22*1%)+(H23*1.5%))+(C18+C22+C30) -> 7365.9432
C29: =A29*B29 -> 0
A30: =SUM(A24:A29) -> 11.76 | B30: Subtotal | C30: =SUM(C24:C29) -> 1587.6 | D30: Delayed Calculation 1 Benefit Amount: | H30: =H16 -> 5517.19
A31: =SUM(A18,A22,A30) -> 43.05 | B31: Pre-65 Total | C31: =SUM(C18,C22,C30) -> 5337.64 | D31: Delayed Calculation 2 Benefit Amount: | H31: =H27 -> 7365.9432
A32: Credits Earned After Age 65 | D32: Greater of Calculation 1 and 2: | G32: =IF(H30=H31,"No Difference",IF(H30<H31,"Calculation 2","Calculation 1")) -> Calculation 2 | H32: =IF(H30=H31,H30,IF(H30<H31,H31,H30)) -> 7365.9432
B33: 105 | C33: =(A33*B33) -> 0
B34: 125 | C34: =(A34*B34) -> 0
A35: 1.33 | B35: 135 | C35: =(A35*B35) -> 179.55
C36: =(A36*B36) -> 0
C37: =(A37*B37) -> 0 | D37: Processed By: | E37: Alex Miles | H37: Checked By:
C38: =(A38*B38) -> 0
A39: =SUM(A33:A38) -> 1.33 | B39: Subtotal | C39: =SUM(C33:C38) -> 179.55 | D39: Date: | E39: =TODAY() -> 46164 | H39: Date:
A40: =SUM(A18,A22,A30,A39) -> 44.38 | B40: Total | C40: =SUM(C18,C22,C30,C39) -> 5517.19

Sheet Pro-Rata Worksheet
D1: PRO RATA CALCULATION WORKSHEET
A2: Participant Name: | C2: Julian A. Jove | H2: ID: | I2: 200180x00
I3: Combined PC | J3: Combined PC
A4: Plan Year | B4: CA | D4: 720 | I4: (1PC max / $) | J4: (combined/elig/%)
A5: Totals | B5: =SUM(B6:B69) -> 10.65 | C5: =SUM(C6:C69) -> 1 | D5: =SUM(D6:D69) -> 0 | E5: =SUM(E6:E69) -> 0 | F5: =SUM(F6:F69) -> 0 | G5: =SUM(G6:G69) -> 0 | H5: =SUM(H6:H69) -> 0 | I5: =SUM(I6:I69) -> 11.65 | J5: =SUM(J6:J69) -> 11.65
A6: 2035 | I6: =IF(AND(SUM(B6:H6)>=1,B6<=1),1,IF((B6>1),B6,SUM(B6:H6))) -> 0 | J6: =SUM(B6:H6) -> 0
A7: 2034 | I7: =IF(AND(SUM(B7:H7)>=1,B7<=1),1,IF((B7>1),B7,SUM(B7:H7))) -> 0 | J7: =SUM(B7:H7) -> 0
A8: 2033 | I8: =IF(AND(SUM(B8:H8)>=1,B8<=1),1,IF((B8>1),B8,SUM(B8:H8))) -> 0 | J8: =SUM(B8:H8) -> 0
A9: 2032 | I9: =IF(AND(SUM(B9:H9)>=1,B9<=1),1,IF((B9>1),B9,SUM(B9:H9))) -> 0 | J9: =SUM(B9:H9) -> 0
A10: 2031 | I10: =IF(AND(SUM(B10:H10)>=1,B10<=1),1,IF((B10>1),B10,SUM(B10:H10))) -> 0 | J10: =SUM(B10:H10) -> 0
A11: 2030 | I11: =IF(AND(SUM(B11:H11)>=1,B11<=1),1,IF((B11>1),B11,SUM(B11:H11))) -> 0 | J11: =SUM(B11:H11) -> 0
A12: 2029 | I12: =IF(AND(SUM(B12:H12)>=1,B12<=1),1,IF((B12>1),B12,SUM(B12:H12))) -> 0 | J12: =SUM(B12:H12) -> 0
A13: 2028 | I13: =IF(AND(SUM(B13:H13)>=1,B13<=1),1,IF((B13>1),B13,SUM(B13:H13))) -> 0 | J13: =SUM(B13:H13) -> 0
A14: 2027 | I14: =IF(AND(SUM(B14:H14)>=1,B14<=1),1,IF((B14>1),B14,SUM(B14:H14))) -> 0 | J14: =SUM(B14:H14) -> 0
A15: 2026 | I15: =IF(AND(SUM(B15:H15)>=1,B15<=1),1,IF((B15>1),B15,SUM(B15:H15))) -> 0 | J15: =SUM(B15:H15) -> 0
A16: 2025 | B16: 0.67 | I16: =IF(AND(SUM(B16:H16)>=1,B16<=1),1,IF((B16>1),B16,SUM(B16:H16))) -> 0.67 | J16: =SUM(B16:H16) -> 0.67
A17: 2024 | B17: 0.33 | I17: =IF(AND(SUM(B17:H17)>=1,B17<=1),1,IF((B17>1),B17,SUM(B17:H17))) -> 0.33 | J17: =SUM(B17:H17) -> 0.33
A18: 2023 | B18: 0.75 | I18: =IF(AND(SUM(B18:H18)>=1,B18<=1),1,IF((B18>1),B18,SUM(B18:H18))) -> 0.75 | J18: =SUM(B18:H18) -> 0.75
A19: 2022 | I19: =IF(AND(SUM(B19:H19)>=1,B19<=1),1,IF((B19>1),B19,SUM(B19:H19))) -> 0 | J19: =SUM(B19:H19) -> 0
A20: 2021 | I20: =IF(AND(SUM(B20:H20)>=1,B20<=1),1,IF((B20>1),B20,SUM(B20:H20))) -> 0 | J20: =SUM(B20:H20) -> 0
A21: 2020 | B21: 0.25 | I21: =IF(AND(SUM(B21:H21)>=1,B21<=1),1,IF((B21>1),B21,SUM(B21:H21))) -> 0.25 | J21: =SUM(B21:H21) -> 0.25
A22: 2019 | B22: 0.42 | I22: =IF(AND(SUM(B22:H22)>=1,B22<=1),1,IF((B22>1),B22,SUM(B22:H22))) -> 0.42 | J22: =SUM(B22:H22) -> 0.42
A23: 2018 | B23: 0.42 | I23: =IF(AND(SUM(B23:H23)>=1,B23<=1),1,IF((B23>1),B23,SUM(B23:H23))) -> 0.42 | J23: =SUM(B23:H23) -> 0.42
A24: 2017 | B24: 0.33 | I24: =IF(AND(SUM(B24:H24)>=1,B24<=1),1,IF((B24>1),B24,SUM(B24:H24))) -> 0.33 | J24: =SUM(B24:H24) -> 0.33
A25: 2016 | B25: 0.33 | I25: =IF(AND(SUM(B25:H25)>=1,B25<=1),1,IF((B25>1),B25,SUM(B25:H25))) -> 0.33 | J25: =SUM(B25:H25) -> 0.33
A26: 2015b | I26: {=IF(SUM(B26:B27)>=1,B26,IF(SUM(B26:H26+B27:H27)>=1,SUM(B26:H26/SUM(B26:H26+B27:H27)),SUM(B26:H26)))} -> 0 | J26: =SUM(B26:H26) -> 0
A27: 2015a | I27: {=IF(SUM(B26:B27)>=1,B27,IF(SUM(B26:H26+B27:H27)>=1,SUM(B27:H27/SUM(B26:H26+B27:H27)),SUM(B27:H27)))} -> 0 | J27: =SUM(B27:H27) -> 0
A28: 2014 | C28: 1 | I28: =IF(AND(SUM(B28:H28)>=1,B28<=1),1,IF((B28>1),B28,SUM(B28:H28))) -> 1 | J28: =SUM(B28:H28) -> 1
A29: 2013 | I29: =IF(AND(SUM(B29:H29)>=1,B29<=1),1,IF((B29>1),B29,SUM(B29:H29))) -> 0 | J29: =SUM(B29:H29) -> 0
A30: 2012b | B30: 0.08 | I30: {=IF(SUM(B30:B31)>=1,B30,IF(SUM(B30:H30+B31:H31)>=1,SUM(B30:H30/SUM(B30:H30+B31:H31)),SUM(B30:H30)))} -> 0.08 | J30: =SUM(B30:H30) -> 0.08
A31: 2012a | B31: 0.33 | I31: {=IF(SUM(B30:B31)>=1,B31,IF(SUM(B30:H30+B31:H31)>=1,SUM(B31:H31/SUM(B30:H30+B31:H31)),SUM(B31:H31)))} -> 0.33 | J31: =SUM(B31:H31) -> 0.33
A32: 2011 | B32: 0.58 | I32: =IF(AND(SUM(B32:H32)>=1,B32<=1),1,IF((B32>1),B32,SUM(B32:H32))) -> 0.58 | J32: =SUM(B32:H32) -> 0.58
A33: 2010 | B33: 0.83 | I33: =IF(AND(SUM(B33:H33)>=1,B33<=1),1,IF((B33>1),B33,SUM(B33:H33))) -> 0.83 | J33: =SUM(B33:H33) -> 0.83
A34: 2009 | I34: =IF(AND(SUM(B34:H34)>=1,B34<=1),1,IF((B34>1),B34,SUM(B34:H34))) -> 0 | J34: =SUM(B34:H34) -> 0
A35: 2008 | B35: 1.08 | I35: =IF(AND(SUM(B35:H35)>=1,B35<=1),1,IF((B35>1),B35,SUM(B35:H35))) -> 1.08 | J35: =SUM(B35:H35) -> 1.08
A36: 2007 | B36: 1 | I36: =IF(AND(SUM(B36:H36)>=1,B36<=1),1,IF((B36>1),B36,SUM(B36:H36))) -> 1 | J36: =SUM(B36:H36) -> 1
A37: 2006 | B37: 0.67 | I37: =IF(AND(SUM(B37:H37)>=1,B37<=1),1,IF((B37>1),B37,SUM(B37:H37))) -> 0.67 | J37: =SUM(B37:H37) -> 0.67
A38: 2005 | B38: 1 | I38: =IF(AND(SUM(B38:H38)>=1,B38<=1),1,IF((B38>1),B38,SUM(B38:H38))) -> 1 | J38: =SUM(B38:H38) -> 1
A39: 2004 | B39: 1.08 | I39: =IF(AND(SUM(B39:H39)>=1,B39<=1),1,IF((B39>1),B39,SUM(B39:H39))) -> 1.08 | J39: =SUM(B39:H39) -> 1.08
A40: 2003 | B40: 0.5 | I40: =IF(AND(SUM(B40:H40)>=1,B40<=1),1,IF((B40>1),B40,SUM(B40:H40))) -> 0.5 | J40: =SUM(B40:H40) -> 0.5
A41: 2002 | I41: =IF(AND(SUM(B41:H41)>=1,B41<=1),1,IF((B41>1),B41,SUM(B41:H41))) -> 0 | J41: =SUM(B41:H41) -> 0
A42: 2001 | I42: =IF(AND(SUM(B42:H42)>=1,B42<=1),1,IF((B42>1),B42,SUM(B42:H42))) -> 0 | J42: =SUM(B42:H42) -> 0
A43: 2000 | I43: =IF(AND(SUM(B43:H43)>=1,B43<=1),1,IF((B43>1),B43,SUM(B43:H43))) -> 0 | J43: =SUM(B43:H43) -> 0
A44: 1999 | I44: =IF(AND(SUM(B44:H44)>=1,B44<=1),1,IF((B44>1),B44,SUM(B44:H44))) -> 0 | J44: =SUM(B44:H44) -> 0
A45: 1998 | I45: =IF(AND(SUM(B45:H45)>=1,B45<=1),1,IF((B45>1),B45,SUM(B45:H45))) -> 0 | J45: =SUM(B45:H45) -> 0
A46: 1997 | I46: =IF(AND(SUM(B46:H46)>=1,B46<=1),1,IF((B46>1),B46,SUM(B46:H46))) -> 0 | J46: =SUM(B46:H46) -> 0
A47: 1996 | I47: =IF(AND(SUM(B47:H47)>=1,B47<=1),1,IF((B47>1),B47,SUM(B47:H47))) -> 0 | J47: =SUM(B47:H47) -> 0
A48: 1995 | I48: =IF(AND(SUM(B48:H48)>=1,B48<=1),1,IF((B48>1),B48,SUM(B48:H48))) -> 0 | J48: =SUM(B48:H48) -> 0
A49: 1994 | I49: =IF(AND(SUM(B49:H49)>=1,B49<=1),1,IF((B49>1),B49,SUM(B49:H49))) -> 0 | J49: =SUM(B49:H49) -> 0
A50: 1993 | I50: =IF(AND(SUM(B50:H50)>=1,B50<=1),1,IF((B50>1),B50,SUM(B50:H50))) -> 0 | J50: =SUM(B50:H50) -> 0
A51: 1992 | I51: =IF(AND(SUM(B51:H51)>=1,B51<=1),1,IF((B51>1),B51,SUM(B51:H51))) -> 0 | J51: =SUM(B51:H51) -> 0
A52: 1991 | I52: =IF(AND(SUM(B52:H52)>=1,B52<=1),1,IF((B52>1),B52,SUM(B52:H52))) -> 0 | J52: =SUM(B52:H52) -> 0
... A69: 1974 | I69: =IF(AND(SUM(B69:H69)>=1,B69<=1),1,IF((B69>1),B69,SUM(B69:H69))) -> 0 | J69: =SUM(B69:H69) -> 0

Sheet QDRO Pension Calculator
A1: California Ironworkers Field Pension Trust Pension Calculation | J1: California Ironworkers Field Pension Trust Pension Calculation
A2: Member Name: | C2: Martin E. Johnson | E2: Member ID: | F2: 336945X64 | K2: Processed By: | M2: Alex Miles
A3: Member Date of Birth: | C3: 23303
A4: Member Age at Retirement: | C4: =DATEDIF(C3,C5,"y")&"/"&(DATEDIF(C3,C5, "m") - (DATEDIF(C3,C5, "y") * 12)) -> 65/0 | K4: Date: | M4: =TODAY() -> 46164
A5: Member Retirement Date: | C5: 47058
A6: Spouse Name: | K6: Checked By:
A7: Spouse Date of Birth:
A8: Spouse Age at Retirement: | C8: =IF(COUNTIF(C7,""),"",DATEDIF(C7,C5,"y")&"/"&(DATEDIF(C7,C5,"m")-(DATEDIF(C7,C5,"y")*12))) | E8: =IF(C7=0,"","Spouse Age Difference from Member:") | H8: =IF(C7=0,"",IF(AND(C3-C7<0,(DATEDIF(C3,C5,"m")-(DATEDIF(C3,C5,"y")*12))-(DATEDIF(C7,C5,"m")-(DATEDIF(C7,C5,"y")*12))=0),DATEDIF(C3,C5,"y")-DATEDIF(C7,C5,"y"),IF(AND(C3-C7>0,(DATEDIF(C7,C5,"m")-(DATEDIF(C7,C5,"y")*12))-(DATEDIF(C3,C5,"m")-(DATEDIF(C3,C5,"y")*12))=0),DATEDIF(C7,C5,"y")-DATEDIF(C3,C5,"y"),IF(C3-C7<0,ROUNDDOWN(YEARFRAC(C3,C7),0),IF(C3-C7>0,ROUNDDOWN(YEARFRAC(C7,C3),0),0))))) | I8: =IF(C7=0,"",IF(H8=0,"No Difference.",IF(C3-C7<0,"Year(s) Younger.", IF(C3-C7>0, "Year(s) Older.","No Difference.")))) | K8: Date:
A9: Credits Earned Prior to 09/01/2011 | J9: 5. Regular at 65 | O9: =IF(COUNTIF(C7,""),"",IF(COUNTIF(J9,"1.*"),"Early Retirement H&W Pension Options",IF(COUNTIF(J9,"2.*"),"Regular at 62 H&W Pension Options",IF(COUNTIF(J9,"3.*"),"Regular at 62 & Early H&W Pension Options",IF(COUNTIF(J9,"4.*"),"Regular at 62 & Disability H&W Pension Options",IF(COUNTIF(J9,"5.*"),"Regular at 65 H&W Pension Options",IF(COUNTIF(J9,"6.*"),"Disability H&W Pension Options",IF(COUNTIF(J9,"7.*"),"Service Pre-Age 55 & Early H&W Pension Options",IF(COUNTIF(J9,"8.*"),"Service Pre-Age 55 & Disability H&W Pension Options",IF(COUNTIF(J9,"9.*"),"Service H&W Pension Options",L44&" Delayed H&W Options"))))))))))
A10: Member Credits | B10: =IF(COUNTIF(A34,"1.*"),"During AP 1 Marriage","") | C10: =IF(COUNTIF(A34,"1.*"),"AP 1 Credits","") | D10: =IF(COUNTIF(E34,"1.*"),"During AP 2 Marriage","") | E10: =IF(COUNTIF(E34,"1.*"),"AP 2 Credits","") | F10: Rate | G10: Member Value | H10: =IF(COUNTIF(A34,"1.*"),"AP 1 Value","") | I10: =IF(COUNTIF(E34,"1.*"),"AP 2 Value","") | J10: Benefit Calculation | O10: =IF(COUNTIF(C7,""),"","Option") | P10: =IF(COUNTIF(C7,""),"","Factor") | Q10: =IF(COUNTIF(C7,""),"","Member Benefit") | R10: =IF(COUNTIF(C7,""),"","Spouse Benefit")
C11: =IF(COUNTIF(A34,"1.*"),B11*D39,"") | E11: =IF(COUNTIF(E34,"1.*"),D11*H39,"") | G11: =IF(AND(COUNTIF(A34,"1.*"),COUNTIF(E34,"1.*")),SUM(A11*F11)-((C11*F11)+(E11*F11)),IF(COUNTIF(A34,"1.*"),SUM(A11*F11)-(C11*F11),IF(COUNTIF(E34,"1.*"),SUM(A11*F11)-(E11*F11),A11*F11))) -> 0 | H11: =IF(COUNTIF(A34,"1.*"),SUM(C11*F11),"") | I11: =IF(COUNTIF(E34,"1.*"),SUM(E11*F11),"") | J11: Full Benefit Prior to 09/01/2011: | M11: =SUM(A11:A16) -> 15.51 | N11: =SUM(A11*F11,A12*F12,A13*F13,A14*F14,A15*F15,A16*F16) -> 1848.87 | O11: =IF(COUNTIF(C7,""),"","50%") | P11: =IF(COUNTIF(C7,""),"",IF(COUNTIF(J9,"4.*"),IF(COUNTIF(I8,"*Younger*"),100%-8%-(H8*0.4%),IF(100%-8%+(H8*0.4%)>100%,100%,100%-8%+(H8*0.4%)))*100&"% / "&IF(COUNTIF(I8,"*Younger*"),100%-18%-(H8*0.4%),IF(100%-18%+(H8*0.4%)>100%,100%,100%-18%+(H8*0.4%)))*100&"%",IF(COUNTIF(J9,"6.*"),IF(COUNTIF(I8,"*Younger*"),100%-18%-(H8*0.4%),IF(100%-18%+(H8*0.4%)>100%,100%,100%-18%+(H8*0.4%))),IF(COUNTIF(J9,"8.*"),IF(COUNTIF(I8,"*Younger*"),100%-8%-(H8*0.4%),IF(100%-8%+(H8*0.4%)>100%,100%,100%-8%+(H8*0.4%)))*100&"% / "&IF(COUNTIF(I8,"*Younger*"),100%-18%-(H8*0.4%),IF(100%-18%+(H8*0.4%)>100%,100%,100%-18%+(H8*0.4%)))*100&"%",IF(COUNTIF(I8,"*Younger*"),100%-8%-(H8*0.4%),IF(100%-8%+(H8*0.4%)>100%,100%,100%-8%+(H8*0.4%))))))) | Q11: =IF(COUNTIF(C7,""),"",IF(COUNTIF(J9,"1.*"),(N40)*P11,IF(COUNTIF(J9,"2.*"),(N40)*P11,IF(COUNTIF(J9,"3.*"),(N40)*P11,IF(COUNTIF(J9,"5.*"),(N40)*P11,IF(COUNTIF(J9,"6.*"),(N40)*P11,IF(COUNTIF(J9,"7.*"),(N40)*P11,IF(COUNTIF(J9,"8.*"),(N11+N12)*IF(COUNTIF(I8,"*Younger*"),100%-8%-(H8*0.4%),IF(100%-8%+(H8*0.4%)>100%,100%,100%-8%+(H8*0.4%)))+(N13*IF(COUNTIF(I8,"*Younger*"),100%-18%-(H8*0.4%),IF(100%-18%+(H8*0.4%)>100%,100%,100%-18%+(H8*0.4%)))),IF(COUNTIF(J9,"4.*"),N11*IF(COUNTIF(I8,"*Younger*"),100%-8%-(H8*0.4%),IF(100%-8%+(H8*0.4%)>100%,100%,100%-8%+(H8*0.4%)))+(N12+N13)*IF(COUNTIF(I8,"*Younger*"),100%-18%-(H8*0.4%),IF(100%-18%+(H8*0.4%)>100%,100%,100%-18%+(H8*0.4%))),IF(COUNTIF(J9,"9.*"),(N40)*P11,IF(COUNTIF(J9,"10.*"),M44*P11,""))))))))))) | R11: =IF(COUNTIF(C7,""),"",Q11*O11)
C12: =IF(COUNTIF(A34,"1.*"),B12*D39,"") | E12: =IF(COUNTIF(E34,"1.*"),D12*H39,"") | G12: =IF(AND(COUNTIF(A34,"1.*"),COUNTIF(E34,"1.*")),SUM(A12*F12)-((C12*F12)+(E12*F12)),IF(COUNTIF(A34,"1.*"),SUM(A12*F12)-(C12*F12),IF(COUNTIF(E34,"1.*"),SUM(A12*F12)-(E12*F12),A12*F12))) -> 0 | H12: =IF(COUNTIF(A34,"1.*"),SUM(C12*F12),"") | I12: =IF(COUNTIF(E34,"1.*"),SUM(E12*F12),"") | J12: =IF(COUNTIF(J9,"2.*"),"","Full Benefit from 09/01/2011 to 09/30/2014:") -> Full Benefit from 09/01/2011 to 09/30/2014: | M12: =IF(COUNTIF(J9,"2.*"),"",SUM(A19:A20)) -> 3 | N12: =IF(COUNTIF(J9,"2.*"),"",SUM(A19*F19,A20*F20)) -> 375 | O12: =IF(COUNTIF(C7,""),"","13th Check") | P12: =IF(COUNTIF(C7,""),"",IF(COUNTIF(J9,"4.*"),IF(COUNTIF(I8,"*Younger*"),100%-8%-(H8*0.4%),IF(100%-8%+(H8*0.4%)>100%,100%,100%-8%+(H8*0.4%)))*100&"% / "&IF(COUNTIF(I8,"*Younger*"),100%-18%-(H8*0.4%),IF(100%-18%+(H8*0.4%)>100%,100%,100%-18%+(H8*0.4%)))*100&"%",IF(COUNTIF(J9,"6.*"),IF(COUNTIF(I8,"*Younger*"),100%-18%-(H8*0.4%),IF(100%-18%+(H8*0.4%)>100%,100%,100%-18%+(H8*0.4%))),IF(COUNTIF(J9,"8.*"),IF(COUNTIF(I8,"*Younger*"),100%-8%-(H8*0.4%),IF(100%-8%+(H8*0.4%)>100%,100%,100%-8%+(H8*0.4%)))*100&"% / "&IF(COUNTIF(I8,"*Younger*"),100%-18%-(H8*0.4%),IF(100%-18%+(H8*0.4%)>100%,100%,100%-18%+(H8*0.4%)))*100&"%",IF(COUNTIF(I8,"*Younger*"),100%-8%-(H8*0.4%),IF(100%-8%+(H8*0.4%)>100%,100%,100%-8%+(H8*0.4%))))))) | Q12: =IF(COUNTIF(C7,""),"",IF(COUNTIF(J9,"1.*"),(N41)*P12,IF(COUNTIF(J9,"2.*"),(N41)*P12,IF(COUNTIF(J9,"3.*"),(N41)*P12,IF(COUNTIF(J9,"5.*"),(N41)*P12,IF(COUNTIF(J9,"6.*"),(N41)*P12,IF(COUNTIF(J9,"7.*"),(N41)*P12,IF(COUNTIF(J9,"8.*"),(N11+N12)*IF(COUNTIF(I8,"*Younger*"),100%-8%-(H8*0.4%),IF(100%-8%+(H8*0.4%)>100%,100%,100%-8%+(H8*0.4%))),IF(COUNTIF(J9,"4.*"),N11*IF(COUNTIF(I8,"*Younger*"),100%-8%-(H8*0.4%),IF(100%-8%+(H8*0.4%)>100%,100%,100%-8%+(H8*0.4%)))+(N12)*IF(COUNTIF(I8,"*Younger*"),100%-18%-(H8*0.4%),IF(100%-18%+(H8*0.4%)>100%,100%,100%-18%+(H8*0.4%))),IF(COUNTIF(J9,"9.*"),(N41)*P12,IF(COUNTIF(J9,"10.*"),IF(COUNTIF(L44,"*1*"),M24*P12,M41*P12),""))))))))))) | R12: =IF(COUNTIF(C7,""),"",Q12*O11)
C13: =IF(COUNTIF(A34,"1.*"),B13*D39,"") | E13: =IF(COUNTIF(E34,"1.*"),D13*H39,"") | F13: 90 | G13: =IF(AND(COUNTIF(A34,"1.*"),COUNTIF(E34,"1.*")),SUM(A13*F13)-((C13*F13)+(E13*F13)),IF(COUNTIF(A34,"1.*"),SUM(A13*F13)-(C13*F13),IF(COUNTIF(E34,"1.*"),SUM(A13*F13)-(E13*F13),A13*F13))) -> 0 | H13: =IF(COUNTIF(A34,"1.*"),ROUND(C13*F13,2),"") | I13: =IF(COUNTIF(E34,"1.*"),SUM(E13*F13),"") | J13: =IF(COUNTIF(J9,"2.*"),"","Full Benefit on and After 10/01/2014:") -> Full Benefit on and After 10/01/2014: | M13: =IF(COUNTIF(J9,"2.*"),"",IF(COUNTIF(J9,"10.*"),SUM(A23:A25,A29:A31),SUM(A23:A25))) -> 12.5 | N13: =IF(COUNTIF(J9,"2.*"),"",IF(COUNTIF(J9,"10.*"),SUM(A23*F23,A24*F24,A25*F25,A29*F29,A30*F30,A31*F31),SUM(A23*F23,A24*F24,A25*F25))) -> 1687.5 | O13: =IF(COUNTIF(C7,""),"","75%") | P13: =IF(COUNTIF(C7,""),"",IF(COUNTIF(J9,"4.*"),IF(COUNTIF(I8,"*Younger*"),100%-12%-(H8*0.4%),IF(100%-12%+(H8*0.4%)>100%,100%,100%-12%+(H8*0.4%)))*100&"% / "&IF(COUNTIF(I8,"*Younger*"),100%-24%-(H8*0.4%),IF(100%-24%+(H8*0.4%)>100%,100%,100%-24%+(H8*0.4%)))*100&"%",IF(COUNTIF(J9,"6.*"),IF(COUNTIF(I8,"*Younger*"),100%-24%-(H8*0.4%),IF(100%-24%+(H8*0.4%)>100%,100%,100%-24%+(H8*0.4%))),IF(COUNTIF(J9,"8.*"),IF(COUNTIF(I8,"*Younger*"),100%-12%-(H8*0.4%),IF(100%-12%+(H8*0.4%)>100%,100%,100%-12%+(H8*0.4%)))*100&"% / "&IF(COUNTIF(I8,"*Younger*"),100%-24%-(H8*0.4%),IF(100%-24%+(H8*0.4%)>100%,100%,100%-24%+(H8*0.4%)))*100&"%",IF(COUNTIF(I8,"*Younger*"),100%-12%-(H8*0.4%),IF(100%-12%+(H8*0.4%)>100%,100%,100%-12%+(H8*0.4%))))))) | Q13: =IF(COUNTIF(C7,""),"",IF(COUNTIF(J9,"1.*"),(N40)*P13,IF(COUNTIF(J9,"2.*"),(N40)*P13,IF(COUNTIF(J9,"3.*"),(N40)*P13,IF(COUNTIF(J9,"5.*"),(N40)*P13,IF(COUNTIF(J9,"6.*"),(N40)*P13,IF(COUNTIF(J9,"7.*"),(N40)*P13,IF(COUNTIF(J9,"8.*"),(N11+N12)*IF(COUNTIF(I8,"*Younger*"),100%-12%-(H8*0.4%),IF(100%-12%+(H8*0.4%)>100%,100%,100%-12%+(H8*0.4%)))+(N13*IF(COUNTIF(I8,"*Younger*"),100%-24%-(H8*0.4%),IF(100%-24%+(H8*0.4%)>100%,100%,100%-24%+(H8*0.4%)))),IF(COUNTIF(J9,"4.*"),N11*IF(COUNTIF(I8,"*Younger*"),100%-12%-(H8*0.4%),IF(100%-12%+(H8*0.4%)>100%,100%,100%-12%+(H8*0.4%)))+(N12+N13)*IF(COUNTIF(I8,"*Younger*"),100%-24%-(H8*0.4%),IF(100%-24%+(H8*0.4%)>100%,100%,100%-24%+(H8*0.4%))),IF(COUNTIF(J9,"9.*"),(N40)*P13,IF(COUNTIF(J9,"10.*"),M44*P13,""))))))))))) | R13: =IF(COUNTIF(C7,""),"",Q13*O13)
A14: 12.84 | C14: =IF(COUNTIF(A34,"1.*"),B14*D39,"") | E14: =IF(COUNTIF(E34,"1.*"),D14*H39,"") | F14: 118 | G14: =IF(AND(COUNTIF(A34,"1.*"),COUNTIF(E34,"1.*")),ROUND(A14*F14,2)-(ROUND(C14*F14,2)+ROUND(E14*F14,2)),IF(COUNTIF(A34,"1.*"),ROUND(A14*F14,2)-ROUND(C14*F14,2),IF(COUNTIF(E34,"1.*"),ROUND(A14*F14,2)-ROUND(E14*F14,2),ROUND(A14*F14,2)))) -> 1515.12 | H14: =IF(COUNTIF(A34,"1.*"),ROUND(C14*F14,2),"") | I14: =IF(COUNTIF(E34,"1.*"),SUM(E14*F14),"") | J14: Total Pension Credits & Amount: | M14: =SUM(M11:M13) -> 31.01 | N14: =SUM(N11:N13) -> 3911.37 | O14: =IF(COUNTIF(C7,""),"","13th Check") | P14: =IF(COUNTIF(C7,""),"",IF(COUNTIF(J9,"4.*"),IF(COUNTIF(I8,"*Younger*"),100%-12%-(H8*0.4%),IF(100%-12%+(H8*0.4%)>100%,100%,100%-12%+(H8*0.4%)))*100&"% / "&IF(COUNTIF(I8,"*Younger*"),100%-24%-(H8*0.4%),IF(100%-24%+(H8*0.4%)>100%,100%,100%-24%+(H8*0.4%)))*100&"%",IF(COUNTIF(J9,"6.*"),IF(COUNTIF(I8,"*Younger*"),100%-24%-(H8*0.4%),IF(100%-24%+(H8*0.4%)>100%,100%,100%-24%+(H8*0.4%))),IF(COUNTIF(J9,"8.*"),IF(COUNTIF(I8,"*Younger*"),100%-12%-(H8*0.4%),IF(100%-12%+(H8*0.4%)>100%,100%,100%-12%+(H8*0.4%)))*100&"% / "&IF(COUNTIF(I8,"*Younger*"),100%-24%-(H8*0.4%),IF(100%-24%+(H8*0.4%)>100%,100%,100%-24%+(H8*0.4%)))*100&"%",IF(COUNTIF(I8,"*Younger*"),100%-12%-(H8*0.4%),IF(100%-12%+(H8*0.4%)>100%,100%,100%-12%+(H8*0.4%))))))) | Q14: =IF(COUNTIF(C7,""),"",IF(COUNTIF(J9,"1.*"),(N41)*P14,IF(COUNTIF(J9,"2.*"),(N41)*P14,IF(COUNTIF(J9,"3.*"),(N41)*P14,IF(COUNTIF(J9,"5.*"),(N41)*P14,IF(COUNTIF(J9,"6.*"),(N41)*P14,IF(COUNTIF(J9,"7.*"),(N41)*P14,IF(COUNTIF(J9,"8.*"),(N11+N12)*IF(COUNTIF(I8,"*Younger*"),100%-12%-(H8*0.4%),IF(100%-12%+(H8*0.4%)>100%,100%,100%-12%+(H8*0.4%))),IF(COUNTIF(J9,"4.*"),N11*IF(COUNTIF(I8,"*Younger*"),100%-12%-(H8*0.4%),IF(100%-12%+(H8*0.4%)>100%,100%,100%-12%+(H8*0.4%)))+(N12)*IF(COUNTIF(I8,"*Younger*"),100%-24%-(H8*0.4%),IF(100%-24%+(H8*0.4%)>100%,100%,100%-24%+(H8*0.4%))),IF(COUNTIF(J9,"9.*"),(N41)*P14,IF(COUNTIF(J9,"10.*"),IF(COUNTIF(L44,"*1*"),M24*P14,M41*P14),""))))))))))) | R14: =IF(COUNTIF(C7,""),"",Q14*O13)
C15: =IF(COUNTIF(A34,"1.*"),B15*D39,"") | E15: =IF(COUNTIF(E34,"1.*"),D15*H39,"") | F15: 105 | G15: =IF(AND(COUNTIF(A34,"1.*"),COUNTIF(E34,"1.*")),ROUND(A15*F15,2)-(ROUND(C15*F15,2)+ROUND(E15*F15,2)),IF(COUNTIF(A34,"1.*"),ROUND(A15*F15,2)-ROUND(C15*F15,2),IF(COUNTIF(E34,"1.*"),ROUND(A15*F15,2)-ROUND(E15*F15,2),ROUND(A15*F15,2)))) -> 0 | H15: =IF(COUNTIF(A34,"1.*"),ROUND(C15*F15,2),"") | I15: =IF(COUNTIF(E34,"1.*"),SUM(E15*F15),"") | J15: =IF(COUNTIF(J9,"10.*"),"Delayed Retirement Calculation 1","") | O15: =IF(COUNTIF(C7,""),"","100%") | P15: =IF(COUNTIF(C7,""),"",IF(COUNTIF(J9,"4.*"),IF(COUNTIF(I8,"*Younger*"),100%-15%-(H8*0.5%),IF(100%-15%+(H8*0.5%)>100%,100%,100%-15%+(H8*0.5%)))*100&"% / "&IF(COUNTIF(I8,"*Younger*"),100%-30%-(H8*0.5%),IF(100%-30%+(H8*0.5%)>100%,100%,100%-30%+(H8*0.5%)))*100&"%",IF(COUNTIF(J9,"6.*"),IF(COUNTIF(I8,"*Younger*"),100%-30%-(H8*0.5%),IF(100%-30%+(H8*0.5%)>100%,100%,100%-30%+(H8*0.5%))),IF(COUNTIF(J9,"8.*"),IF(COUNTIF(I8,"*Younger*"),100%-15%-(H8*0.5%),IF(100%-15%+(H8*0.5%)>100%,100%,100%-15%+(H8*0.5%)))*100&"% / "&IF(COUNTIF(I8,"*Younger*"),100%-30%-(H8*0.5%),IF(100%-30%+(H8*0.5%)>100%,100%,100%-30%+(H8*0.5%)))*100&"%",IF(COUNTIF(I8,"*Younger*"),100%-15%-(H8*0.5%),IF(100%-15%+(H8*0.5%)>100%,100%,100%-15%+(H8*0.5%))))))) | Q15: =IF(COUNTIF(C7,""),"",IF(COUNTIF(J9,"1.*"),(N40)*P15,IF(COUNTIF(J9,"2.*"),(N40)*P15,IF(COUNTIF(J9,"3.*"),(N40)*P15,IF(COUNTIF(J9,"5.*"),(N40)*P15,IF(COUNTIF(J9,"6.*"),(N40)*P15,IF(COUNTIF(J9,"7.*"),(N40)*P15,IF(COUNTIF(J9,"8.*"),(N11+N12)*IF(COUNTIF(I8,"*Younger*"),100%-15%-(H8*0.5%),IF(100%-15%+(H8*0.5%)>100%,100%,100%-15%+(H8*0.5%)))+(N13*IF(COUNTIF(I8,"*Younger*"),100%-30%-(H8*0.5%),IF(100%-30%+(H8*0.5%)>100%,100%,100%-30%+(H8*0.5%)))),IF(COUNTIF(J9,"4.*"),N11*IF(COUNTIF(I8,"*Younger*"),100%-15%-(H8*0.5%),IF(100%-15%+(H8*0.5%)>100%,100%,100%-15%+(H8*0.5%)))+(N12+N13)*IF(COUNTIF(I8,"*Younger*"),100%-30%-(H8*0.5%),IF(100%-30%+(H8*0.5%)>100%,100%,100%-30%+(H8*0.5%))),IF(COUNTIF(J9,"9.*"),(N40)*P15,IF(COUNTIF(J9,"10.*"),M44*P15,""))))))))))) | R15: =IF(COUNTIF(C7,""),"",Q15*O15)
A16: 2.67 | C16: =IF(COUNTIF(A34,"1.*"),B16*D39,"") | E16: =IF(COUNTIF(E34,"1.*"),D16*H39,"") | F16: 125 | G16: =IF(AND(COUNTIF(A34,"1.*"),COUNTIF(E34,"1.*")),SUM(A16*F16)-((C16*F16)+(E16*F16)),IF(COUNTIF(A34,"1.*"),SUM(A16*F16)-(C16*F16),IF(COUNTIF(E34,"1.*"),SUM(A16*F16)-(E16*F16),A16*F16))) -> 333.75 | H16: =IF(COUNTIF(A34,"1.*"),SUM(C16*F16),"") | I16: =IF(COUNTIF(E34,"1.*"),SUM(E16*F16),"") | J16: =IF(COUNTIF(A34,"_"),"","Alternate Payee 1 Award:") -> Alternate Payee 1 Award: | N16: =IF(COUNTIF(A34,"_"),"",IF(COUNTIF(A34,"1.*"),ROUND(H17+H21+H26,2),IF(COUNTIF(A34,"3.*"),D56,IF(OR(COUNTIF(A34,"2.*"),COUNTIF(A34,"4.*")),IF(COUNTIF(J9,"2.*"),D44,ROUND((D44+D47+D50),2)))))) -> 795.42 | O16: =IF(COUNTIF(C7,""),"","13th Check") | P16: =IF(COUNTIF(C7,""),"",IF(COUNTIF(J9,"4.*"),IF(COUNTIF(I8,"*Younger*"),100%-15%-(H8*0.5%),IF(100%-15%+(H8*0.5%)>100%,100%,100%-15%+(H8*0.5%)))*100&"% / "&IF(COUNTIF(I8,"*Younger*"),100%-30%-(H8*0.5%),IF(100%-30%+(H8*0.5%)>100%,100%,100%-30%+(H8*0.5%)))*100&"%",IF(COUNTIF(J9,"6.*"),IF(COUNTIF(I8,"*Younger*"),100%-30%-(H8*0.5%),IF(100%-30%+(H8*0.5%)>100%,100%,100%-30%+(H8*0.5%))),IF(COUNTIF(J9,"8.*"),IF(COUNTIF(I8,"*Younger*"),100%-15%-(H8*0.5%),IF(100%-15%+(H8*0.5%)>100%,100%,100%-15%+(H8*0.5%)))*100&"% / "&IF(COUNTIF(I8,"*Younger*"),100%-30%-(H8*0.5%),IF(100%-30%+(H8*0.5%)>100%,100%,100%-30%+(H8*0.5%)))*100&"%",IF(COUNTIF(I8,"*Younger*"),100%-15%-(H8*0.5%),IF(100%-15%+(H8*0.5%)>100%,100%,100%-15%+(H8*0.5%))))))) | Q16: =IF(COUNTIF(C7,""),"",IF(COUNTIF(J9,"1.*"),(N41)*P16,IF(COUNTIF(J9,"2.*"),(N41)*P16,IF(COUNTIF(J9,"3.*"),(N41)*P16,IF(COUNTIF(J9,"5.*"),(N41)*P16,IF(COUNTIF(J9,"6.*"),(N41)*P16,IF(COUNTIF(J9,"7.*"),(N41)*P16,IF(COUNTIF(J9,"8.*"),(N11+N12)*IF(COUNTIF(I8,"*Younger*"),100%-15%-(H8*0.5%),IF(100%-15%+(H8*0.5%)>100%,100%,100%-15%+(H8*0.5%))),IF(COUNTIF(J9,"4.*"),N11*IF(COUNTIF(I8,"*Younger*"),100%-15%-(H8*0.5%),IF(100%-15%+(H8*0.5%)>100%,100%,100%-15%+(H8*0.5%)))+(N12)*IF(COUNTIF(I8,"*Younger*"),100%-30%-(H8*0.5%),IF(100%-30%+(H8*0.5%)>100%,100%,100%-30%+(H8*0.5%))),IF(COUNTIF(J9,"9.*"),(N41)*P16,IF(COUNTIF(J9,"10.*"),IF(COUNTIF(L44,"*1*"),M24*P16,M41*P16),""))))))))))) | R16: =IF(COUNTIF(C7,""),"",Q16*O15)
A17: =SUM(A11:A16) -> 15.51 | B17: =IF(COUNTIF(A34,"1.*"),SUM(B11:B16),"") | C17: =IF(COUNTIF(A34,"1.*"),SUM(C11:C16),"") | D17: =IF(COUNTIF(E34,"1.*"),SUM(D11:D16),"") | E17: =IF(COUNTIF(E34,"1.*"),SUM(E11:E16),"") | F17: Subtotal | G17: =SUM(G11:G16) -> 1848.87 | H17: =IF(COUNTIF(A34,"1.*"),SUM(H11:H16),"") | I17: =IF(COUNTIF(E34,"1.*"),SUM(I11:I16),"") | J17: =IF(COUNTIF(A34,"_"),"","Alternate Payee 1 13th Check:") -> Alternate Payee 1 13th Check: | N17: =IF(COUNTIF(A34,"_"),"",IF(COUNTIF(A34,"1.*"),ROUND(H17+H21,2),IF(COUNTIF(A34,"3.*"),D57,IF(OR(COUNTIF(A34,"2.*"),COUNTIF(A34,"4.*")),IF(COUNTIF(J9,"2.*"),D44,ROUND((D44+D47+D50),2)))))) -> 795.42 | O17: =IF(COUNTIF(C7,""),"",IF(OR(COUNTIF(J9,"1.*"),COUNTIF(J9,"3.*"),COUNTIF(J9,"7.*")),"Pension Benefit Deferred at Age 65 H&W Options",""))
A18: Credits Earned On and Between 09/01/2011 to 09/30/2014 | J18: =IF(COUNTIF(E34,"Select*"),"","Alternate Payee 2 Award:") | N18: =IF(COUNTIF(E34,"Select*"),"",IF(COUNTIF(E34,"1.*"),ROUND(I17+I21+I26,2),IF(COUNTIF(E34,"3.*"),H40,IF(OR(COUNTIF(E34,"2.*"),COUNTIF(E34,"4.*")),IF(COUNTIF(J9,"2.*"),H44,ROUND((H44+H47+H50),2)))))) | O18: =IF(COUNTIF(C7,""),"",IF(OR(COUNTIF(J9,"1.*"),COUNTIF(J9,"3.*"),COUNTIF(J9,"7.*")),"Option","")) | P18: =IF(COUNTIF(C7,""),"",IF(OR(COUNTIF(J9,"1.*"),COUNTIF(J9,"3.*"),COUNTIF(J9,"7.*")),"Factor","")) | Q18: =IF(COUNTIF(C7,""),"",IF(OR(COUNTIF(J9,"1.*"),COUNTIF(J9,"3.*"),COUNTIF(J9,"7.*")),"Member Benefit","")) | R18: =IF(COUNTIF(C7,""),"",IF(OR(COUNTIF(J9,"1.*"),COUNTIF(J9,"3.*"),COUNTIF(J9,"7.*")),"Spouse Benefit",""))
C19: =IF(COUNTIF(A34,"1.*"),B19*D39,"") | E19: =IF(COUNTIF(E34,"1.*"),D19*H39,"") | F19: 90 | G19: =IF(AND(COUNTIF(A34,"1.*"),COUNTIF(E34,"1.*")),SUM(A19*F19)-((C19*F19)+(E19*F19)),IF(COUNTIF(A34,"1.*"),SUM(A19*F19)-(C19*F19),IF(COUNTIF(E34,"1.*"),SUM(A19*F19)-(E19*F19),A19*F19))) -> 0 | H19: =IF(COUNTIF(A34,"1.*"),SUM(C19*F19),"") | I19: =IF(COUNTIF(E34,"1.*"),SUM(E19*F19),"") | J19: =IF(COUNTIF(E34,"Select*"),"","Alternate Payee 2 13th Check:") | N19: =IF(COUNTIF(E34,"Select*"),"",IF(COUNTIF(E34,"1.*"),ROUND(I17+I21,2),IF(COUNTIF(E34,"3.*"),H41,IF(OR(COUNTIF(E34,"2.*"),COUNTIF(E34,"4.*")),ROUND((H44+H47),2))))) | O19: =IF(COUNTIF(C7,""),"",IF(OR(COUNTIF(J9,"1.*"),COUNTIF(J9,"3.*"),COUNTIF(J9,"7.*")),"50%","")) | P19: =IF(COUNTIF(C7,""),"",IF(OR(COUNTIF(J9,"1.*"),COUNTIF(J9,"3.*"),COUNTIF(J9,"7.*")),IF(COUNTIF(I8,"*Younger*"),100%-8%-(H8*0.4%),IF(100%-8%+(H8*0.4%)>100%,100%,100%-8%+(H8*0.4%))),"")) | Q19: =IF(COUNTIF(C7,""),"",IF(OR(COUNTIF(J9,"1.*"),COUNTIF(J9,"3.*"),COUNTIF(J9,"7.*")),(N43)*P19,"")) | R19: =IF(COUNTIF(C7,""),"",IF(OR(COUNTIF(J9,"1.*"),COUNTIF(J9,"3.*"),COUNTIF(J9,"7.*")),Q19*O19,""))
A20: 3 | C20: =IF(COUNTIF(A34,"1.*"),B20*D39,"") | E20: =IF(COUNTIF(E34,"1.*"),D20*H39,"") | F20: 125 | G20: =IF(AND(COUNTIF(A34,"1.*"),COUNTIF(E34,"1.*")),SUM(A20*F20)-((C20*F20)+(E20*F20)),IF(COUNTIF(A34,"1.*"),SUM(A20*F20)-(C20*F20),IF(COUNTIF(E34,"1.*"),SUM(A20*F20)-(E20*F20),A20*F20))) -> 375 | H20: =IF(COUNTIF(A34,"1.*"),SUM(C20*F20),"") | I20: =IF(COUNTIF(E34,"1.*"),SUM(E20*F20),"") | J20: Member Benefit Prior to 09/01/2011: | M20: =IF(OR(COUNTIF(J9,"1.*"),COUNTIF(J9,"2.*"),COUNTIF(J9,"3.*"),COUNTIF(J9,"4.*"),COUNTIF(J9,"5.*"),COUNTIF(J9,"6.*"),COUNTIF(J9,"7.*"),COUNTIF(J9,"8.*"),COUNTIF(J9,"9.*")),"",IF(COUNTIF(J9,"10*"),IF(AND(COUNTIF(A34,"1.*"),COUNTIF(E34,"1.*")),N11-(H17+I17),IF(AND(COUNTIF(A34,"1.*"),COUNTIF(E34,"2.*")),N11-(H17+(N11*H43)),IF(AND(COUNTIF(A34,"1.*"),COUNTIF(E34,"3.*")),N11-H17,IF(AND(COUNTIF(A34,"1.*"),COUNTIF(E34,"4.*")),N11-(H17+(N11*H43)),IF(AND(COUNTIF(A34,"2.*"),COUNTIF(E34,"1.*")),N11-((N11*D43)+I17),IF(AND(COUNTIF(A34,"2.*"),COUNTIF(E34,"2.*")),N11-((N11*D43)+(N11*H43)),IF(AND(COUNTIF(A34,"2.*"),COUNTIF(E34,"3.*")),N11-(N11*D43),IF(AND(COUNTIF(A34,"2.*"),COUNTIF(E34,"4.*")),N11-((N11*D43)+(N11*H43)),IF(AND(COUNTIF(A34,"3.*"),COUNTIF(E34,"1.*")),N11-I17,IF(AND(COUNTIF(A34,"3.*"),COUNTIF(E34,"2.*")),N11-(N11*H43),IF(AND(COUNTIF(A34,"3.*"),COUNTIF(E34,"3.*")),N11,IF(AND(COUNTIF(A34,"3.*"),COUNTIF(E34,"4.*")),N11-(N11*H43),IF(AND(COUNTIF(A34,"4.*"),COUNTIF(E34,"1.*")),N11-((N11*D43)+I17),IF(AND(COUNTIF(A34,"4.*"),COUNTIF(E34,"2.*")),N11-((N11*D43)+(N11*H43)),IF(AND(COUNTIF(A34,"4.*"),COUNTIF(E34,"3.*")),N11-(N11*D43),IF(AND(COUNTIF(A34,"4.*"),COUNTIF(E34,"4.*")),N11-((N11*D43)+(N11*H43)),IF(COUNTIF(A34,"1.*"),N11-H17,IF(COUNTIF(A34,"3.*"),N11-D40,IF(OR(COUNTIF(A34,"2.*"),COUNTIF(A34,"4.*")),N11-(N11*D43),IF(COUNTIF(E34,"1.*"),N11-I17,IF(OR(COUNTIF(E34,"2.*"),COUNTIF(E34,"4.*")),N11-(N11*H43),SUM(A11*F11,A12*F12,A13*F13,,A14*F14,A15*F15,A16*F16)))))))))))))))))))))))) | N20: =IF(COUNTIF(J9,"10.*"),"",IF(AND(COUNTIF(A34,"1.*"),COUNTIF(E34,"1.*")),N11-(H17+I17),IF(AND(COUNTIF(A34,"1.*"),COUNTIF(E34,"2.*")),N11-(H17+(N11*H43)),IF(AND(COUNTIF(A34,"1.*"),COUNTIF(E34,"3.*")),N11-H17,IF(AND(COUNTIF(A34,"1.*"),COUNTIF(E34,"4.*")),N11-(H17+(N11*H43)),IF(AND(COUNTIF(A34,"2.*"),COUNTIF(E34,"1.*")),N11-((N11*D43)+I17),IF(AND(COUNTIF(A34,"2.*"),COUNTIF(E34,"2.*")),N11-((N11*D43)+(N11*H43)),IF(AND(COUNTIF(A34,"2.*"),COUNTIF(E34,"3.*")),N11-(N11*D43),IF(AND(COUNTIF(A34,"2.*"),COUNTIF(E34,"4.*")),N11-((N11*D43)+(N11*H43)),IF(AND(COUNTIF(A34,"3.*"),COUNTIF(E34,"1.*")),N11-I17,IF(AND(COUNTIF(A34,"3.*"),COUNTIF(E34,"2.*")),N11-(N11*H43),IF(AND(COUNTIF(A34,"3.*"),COUNTIF(E34,"3.*")),N11,IF(AND(COUNTIF(A34,"3.*"),COUNTIF(E34,"4.*")),N11-(N11*H43),IF(AND(COUNTIF(A34,"4.*"),COUNTIF(E34,"1.*")),N11-((N11*D43)+I17),IF(AND(COUNTIF(A34,"4.*"),COUNTIF(E34,"2.*")),N11-((N11*D43)+(N11*H43)),IF(AND(COUNTIF(A34,"4.*"),COUNTIF(E34,"3.*")),N11-(N11*D43),IF(AND(COUNTIF(A34,"4.*"),COUNTIF(E34,"4.*")),N11-((N11*D43)+(N11*H43)),IF(COUNTIF(A34,"1.*"),N11-H17,IF(OR(COUNTIF(A34,"2.*"),COUNTIF(A34,"4.*")),N11-(N11*D43),IF(COUNTIF(A34,"3.*"),N11-D40,IF(COUNTIF(E34,"1.*"),N11-I17,IF(OR(COUNTIF(E34,"2.*"),COUNTIF(E34,"4.*")),N11-(N11*H43),SUM(A11*F11,A12*F12,A13*F13,,A14*F14,A15*F15,A16*F16))))))))))))))))))))))) -> 1053.45 | O20: =IF(COUNTIF(C7,""),"",IF(OR(COUNTIF(J9,"1.*"),COUNTIF(J9,"3.*"),COUNTIF(J9,"7.*")),"13th Check","")) | P20: =IF(COUNTIF(C7,""),"",IF(OR(COUNTIF(J9,"1.*"),COUNTIF(J9,"3.*"),COUNTIF(J9,"7.*")),IF(COUNTIF(I8,"*Younger*"),100%-8%-(H8*0.4%),IF(100%-8%+(H8*0.4%)>100%,100%,100%-8%+(H8*0.4%))),"")) | Q20: =IF(COUNTIF(C7,""),"",IF(OR(COUNTIF(J9,"1.*"),COUNTIF(J9,"3.*"),COUNTIF(J9,"7.*")),(N44)*P20,"")) | R20: =IF(COUNTIF(C7,""),"",IF(OR(COUNTIF(J9,"1.*"),COUNTIF(J9,"3.*"),COUNTIF(J9,"7.*")),Q20*O19,""))
A21: =SUM(A19:A20) -> 3 | B21: =IF(COUNTIF(A34,"1.*"),SUM(B19:B20),"") | C21: =IF(COUNTIF(A34,"1.*"),SUM(C19:C20),"") | D21: =IF(COUNTIF(E34,"1.*"),SUM(D19:D20),"") | E21: =IF(COUNTIF(E34,"1.*"),SUM(E19:E20),"") | F21: Subtotal | G21: =SUM(G19:G20) -> 375 | H21: =IF(COUNTIF(A34,"1.*"),SUM(H19:H20),"") | I21: =IF(COUNTIF(E34,"1.*"),SUM(I19:I20),"") | J21: =IF(COUNTIF(J9,"1.*"),"ER Factor",IF(COUNTIF(J9,"10.*"),"Member Benefit from 09/01/2011 to 09/30/2014:","")) | M21: =IF(OR(COUNTIF(J9,"1.*"),COUNTIF(J9,"2.*"),COUNTIF(J9,"3.*"),COUNTIF(J9,"4.*"),COUNTIF(J9,"5.*"),COUNTIF(J9,"6.*"),COUNTIF(J9,"7.*"),COUNTIF(J9,"8.*"),COUNTIF(J9,"9.*")),"",IF(COUNTIF(J9,"10.*"),IF(AND(COUNTIF(A34,"1.*"),COUNTIF(E34,"1.*")),N12-(H21+I21),IF(AND(COUNTIF(A34,"1.*"),COUNTIF(E34,"2.*")),N12-(H21+(N12*H43)),IF(AND(COUNTIF(A34,"1.*"),COUNTIF(E34,"3.*")),N12-H21,IF(AND(COUNTIF(A34,"1.*"),COUNTIF(E34,"4.*")),N12-(H21+(N12*H43)),IF(AND(COUNTIF(A34,"2.*"),COUNTIF(E34,"1.*")),N12-((N12*D43)+I21),IF(COUNTIF(A34,"3.*"),N12-D41,IF(AND(COUNTIF(A34,"2.*"),COUNTIF(E34,"2.*")),N12-((N12*D43)+(N12*H43)),IF(AND(COUNTIF(A34,"2.*"),COUNTIF(E34,"3.*")),N12-(N12*D43),IF(AND(COUNTIF(A34,"2.*"),COUNTIF(E34,"4.*")),N12-((N12*D43)+(N12*H43)),IF(AND(COUNTIF(A34,"3.*"),COUNTIF(E34,"1.*")),N12-I21,IF(AND(COUNTIF(A34,"3.*"),COUNTIF(E34,"2.*")),N12-(N12*H43),IF(AND(COUNTIF(A34,"3.*"),COUNTIF(E34,"3.*")),N12,IF(AND(COUNTIF(A34,"3.*"),COUNTIF(E34,"4.*")),N12-(N12*H43),IF(AND(COUNTIF(A34,"4.*"),COUNTIF(E34,"1.*")),N12-((N12*D43)+I21),IF(AND(COUNTIF(A34,"4.*"),COUNTIF(E34,"2.*")),N12-((N12*D43)+(N12*H43)),IF(AND(COUNTIF(A34,"4.*"),COUNTIF(E34,"3.*")),N12-(N12*D43),IF(AND(COUNTIF(A34,"4.*"),COUNTIF(E34,"4.*")),N12-((N12*D43)+(N12*H43)),IF(COUNTIF(A34,"1.*"),N12-H21,IF(COUNTIF(A34,"3.*"),N12,IF(OR(COUNTIF(A34,"2.*"),COUNTIF(A34,"4.*")),N12-(N12*D43),IF(COUNTIF(E34,"1.*"),N12-I21,IF(COUNTIF(E34,"3.*"),N12,IF(OR(COUNTIF(E34,"2.*"),COUNTIF(E34,"4.*")),N12-(N12*H43),SUM(A19*F19,A20*F20)))))))))))))))))))))))))) | N21: =IF(COUNTIF(J9,"1.*"),IF(DATEDIF(C3,C5,"m")<=600,((DATEDIF(C3,C5,"m")-540)*0.1%+40%),IF(DATEDIF(C3,C5,"m")<=660,((DATEDIF(C3,C5,"m")-600)*0.2%+46%),IF((DATEDIF(C3,C5,"m")-660)*0.5%+58%>=100%,100%,((DATEDIF(C3,C5,"m")-660)*0.5%+58%)))),"") | O21: =IF(COUNTIF(C7,""),"",IF(OR(COUNTIF(J9,"1.*"),COUNTIF(J9,"3.*"),COUNTIF(J9,"7.*")),"75%","")) | P21: =IF(COUNTIF(C7,""),"",IF(OR(COUNTIF(J9,"1.*"),COUNTIF(J9,"3.*"),COUNTIF(J9,"7.*")),IF(COUNTIF(I8,"*Younger*"),100%-12%-(H8*0.4%),IF(100%-12%+(H8*0.4%)>100%,100%,100%-12%+(H8*0.4%))),"")) | Q21: =IF(COUNTIF(C7,""),"",IF(OR(COUNTIF(J9,"1.*"),COUNTIF(J9,"3.*"),COUNTIF(J9,"7.*")),(N43)*P21,"")) | R21: =IF(COUNTIF(C7,""),"",IF(OR(COUNTIF(J9,"1.*"),COUNTIF(J9,"3.*"),COUNTIF(J9,"7.*")),Q21*O21,""))
A22: Credits Earned On and After 10/01/2014 | J22: =IF(COUNTIF(J9,"1.*"),"ER Benefit Prior to 09/01/2011",IF(COUNTIF(J9,"10.*"),"Member Benefit on and After 10/01/2014:","")) | M22: =IF(OR(COUNTIF(J9,"1.*"),COUNTIF(J9,"2.*"),COUNTIF(J9,"3.*"),COUNTIF(J9,"4.*"),COUNTIF(J9,"5.*"),COUNTIF(J9,"6.*"),COUNTIF(J9,"7.*"),COUNTIF(J9,"8.*"),COUNTIF(J9,"9.*")),"",IF(COUNTIF(J9,"10.*"),IF(AND(COUNTIF(A34,"1.*"),COUNTIF(E34,"1.*")),N13-(H26+I26),IF(AND(COUNTIF(A34,"1.*"),COUNTIF(E34,"2.*")),N13-(H26+(N13*H43)),IF(AND(COUNTIF(A34,"1.*"),COUNTIF(E34,"3.*")),N13-H26,IF(AND(COUNTIF(A34,"1.*"),COUNTIF(E34,"4.*")),N13-(H26+(N13*H43)),IF(AND(COUNTIF(A34,"2.*"),COUNTIF(E34,"1.*")),N13-((N13*D43)+I26),IF(COUNTIF(A34,"3.*"),N13-D42,IF(AND(COUNTIF(A34,"2.*"),COUNTIF(E34,"2.*")),N13-((N13*D43)+(N13*H43)),IF(AND(COUNTIF(A34,"2.*"),COUNTIF(E34,"3.*")),N13-(N13*D43),IF(AND(COUNTIF(A34,"2.*"),COUNTIF(E34,"4.*")),N13-((N13*D43)+(N13*H43)),IF(AND(COUNTIF(A34,"3.*"),COUNTIF(E34,"1.*")),N13-I26,IF(AND(COUNTIF(A34,"3.*"),COUNTIF(E34,"2.*")),N13-(N13*H43),IF(AND(COUNTIF(A34,"3.*"),COUNTIF(E34,"3.*")),N13,IF(AND(COUNTIF(A34,"3.*"),COUNTIF(E34,"4.*")),N13-(N13*H43),IF(AND(COUNTIF(A34,"4.*"),COUNTIF(E34,"1.*")),N13-((N13*D43)+I17),IF(AND(COUNTIF(A34,"4.*"),COUNTIF(E34,"2.*")),N13-((N13*D43)+(N13*H43)),IF(AND(COUNTIF(A34,"4.*"),COUNTIF(E34,"3.*")),N13-(N13*D43),IF(AND(COUNTIF(A34,"4.*"),COUNTIF(E34,"4.*")),N13-((N13*D43)+(N13*H43)),IF(COUNTIF(A34,"1.*"),N13-H26,IF(OR(COUNTIF(A34,"2.*"),COUNTIF(A34,"4.*")),N13-(N13*D43),IF(COUNTIF(E34,"1.*"),N13-I26,IF(OR(COUNTIF(E34,"2.*"),COUNTIF(E34,"4.*")),N13-(N13*H43),SUM(A23*F23,A24*F24,A25*F25,A25*F25,A29*F29,A30*F30,A31*F31)))))))))))))))))))))))) | N22: =IF(COUNTIF(J9,"1.*"),(N20*N21),IF(OR(COUNTIF(J9,"2.*"),COUNTIF(J9,"4.*"),COUNTIF(J9,"5.*"),COUNTIF(J9,"6.*"),COUNTIF(J9,"7.*"),COUNTIF(J9,"8.*"),COUNTIF(J9,"9.*"),COUNTIF(J9,"10.*")),"",IF(AND(COUNTIF(A34,"1.*"),COUNTIF(E34,"1.*")),N13-(H26+I26),IF(AND(COUNTIF(A34,"1.*"),COUNTIF(E34,"2.*")),N13-(H26+(N13*H43)),IF(AND(COUNTIF(A34,"1.*"),COUNTIF(E34,"3.*")),N13-H26,IF(AND(COUNTIF(A34,"1.*"),COUNTIF(E34,"4.*")),N13-(H26+(N13*H43)),IF(AND(COUNTIF(A34,"2.*"),COUNTIF(E34,"1.*")),N13-((N13*D43)+I26),IF(AND(COUNTIF(A34,"2.*"),COUNTIF(E34,"2.*")),N13-((N13*D43)+(N13*H43)),IF(AND(COUNTIF(A34,"2.*"),COUNTIF(E34,"3.*")),N13-(N13*D43),IF(AND(COUNTIF(A34,"2.*"),COUNTIF(E34,"4.*")),N13-((N13*D43)+(N13*H43)),IF(AND(COUNTIF(A34,"3.*"),COUNTIF(E34,"1.*")),N13-I26,IF(AND(COUNTIF(A34,"3.*"),COUNTIF(E34,"2.*")),N13-(N13*H43),IF(AND(COUNTIF(A34,"3.*"),COUNTIF(E34,"3.*")),N13,IF(AND(COUNTIF(A34,"3.*"),COUNTIF(E34,"4.*")),N13-(N13*H43),IF(AND(COUNTIF(A34,"4.*"),COUNTIF(E34,"1.*")),N13-((N13*D43)+I17),IF(AND(COUNTIF(A34,"4.*"),COUNTIF(E34,"2.*")),N13-((N13*D43)+(N13*H43)),IF(AND(COUNTIF(A34,"4.*"),COUNTIF(E34,"3.*")),N13-(N13*D43),IF(AND(COUNTIF(A34,"4.*"),COUNTIF(E34,"4.*")),N13-((N13*D43)+(N13*H43)),IF(COUNTIF(A34,"1.*"),N13-H26,IF(OR(COUNTIF(A34,"2.*"),COUNTIF(A34,"4.*")),N13-(N13*D43),IF(COUNTIF(E34,"1.*"),N13-I26,IF(OR(COUNTIF(E34,"2.*"),COUNTIF(E34,"4.*")),N13-(N13*H43),SUM(A23*F23,A24*F24,A25*F25,A25*F25))))))))))))))))))))))) | O22: =IF(COUNTIF(C7,""),"",IF(OR(COUNTIF(J9,"1.*"),COUNTIF(J9,"3.*"),COUNTIF(J9,"7.*")),"13th Check","")) | P22: =IF(COUNTIF(C7,""),"",IF(OR(COUNTIF(J9,"1.*"),COUNTIF(J9,"3.*"),COUNTIF(J9,"7.*")),IF(COUNTIF(I8,"*Younger*"),100%-12%-(H8*0.4%),IF(100%-12%+(H8*0.4%)>100%,100%,100%-12%+(H8*0.4%))),"")) | Q22: =IF(COUNTIF(C7,""),"",IF(OR(COUNTIF(J9,"1.*"),COUNTIF(J9,"3.*"),COUNTIF(J9,"7.*")),(N44)*P22,"")) | R22: =IF(COUNTIF(C7,""),"",IF(OR(COUNTIF(J9,"1.*"),COUNTIF(J9,"3.*"),COUNTIF(J9,"7.*")),Q22*O21,""))
C23: =IF(COUNTIF(A34,"1.*"),B23*D39,"") | E23: =IF(COUNTIF(E34,"1.*"),D23*H39,"") | F23: 105 | G23: =IF(AND(COUNTIF(A34,"1.*"),COUNTIF(E34,"1.*")),SUM(A23*F23)-((C23*F23))+(E23*F23),IF(COUNTIF(A34,"1.*"),SUM(A23*F23)-(C23*F23),IF(COUNTIF(E34,"1.*"),SUM(A23*F23)-(E23*F23),A23*F23))) -> 0 | H23: =IF(COUNTIF(A34,"1.*"),SUM(C23*F23),"") | I23: =IF(COUNTIF(E34,"1.*"),SUM(D23*F23),"") | J23: =IF(COUNTIF(J9,"10.*"),"Member Delayed Calculation 1 Monthly Amount",IF(COUNTIF(J9,"2.*"),"","Member Benefit from 09/01/2011 to 09/30/2014:")) -> Member Benefit from 09/01/2011 to 09/30/2014: | M23: =IF(AND(COUNTIF(A34,"3.*"),COUNTIF(E34,"3.*"),COUNTIF(J9,"10.*")),(M20+M21+M22)-(D40+H40),IF(AND(COUNTIF(A34,"3.*"),COUNTIF(J9,"10.*")),(M20+M21+M22),IF(AND(COUNTIF(E34,"3.*"),COUNTIF(J9,"10.*")),(M20+M21+M22)-H40,IF(COUNTIF(J9,"10.*"),M20+M21+M22,"")))) | N23: =IF(COUNTIF(J9,"10.*"),"",IF(COUNTIF(J9,"2.*"),"",IF(AND(COUNTIF(A34,"1.*"),COUNTIF(E34,"1.*")),N12-(H21+I21),IF(AND(COUNTIF(A34,"1.*"),COUNTIF(E34,"2.*")),N12-(H21+(N12*H43)),IF(AND(COUNTIF(A34,"1.*"),COUNTIF(E34,"3.*")),N12-H21,IF(AND(COUNTIF(A34,"1.*"),COUNTIF(E34,"4.*")),N12-(H21+(N12*H43)),IF(AND(COUNTIF(A34,"2.*"),COUNTIF(E34,"1.*")),N12-((N12*D43)+I21),IF(AND(COUNTIF(A34,"2.*"),COUNTIF(E34,"2.*")),N12-((N12*D43)+(N12*H43)),IF(AND(COUNTIF(A34,"2.*"),COUNTIF(E34,"3.*")),N12-(N12*D43),IF(AND(COUNTIF(A34,"2.*"),COUNTIF(E34,"4.*")),N12-((N12*D43)+(N12*H43)),IF(AND(COUNTIF(A34,"3.*"),COUNTIF(E34,"1.*")),N12-I21,IF(AND(COUNTIF(A34,"3.*"),COUNTIF(E34,"2.*")),N12-(N12*H43),IF(AND(COUNTIF(A34,"3.*"),COUNTIF(E34,"3.*")),N12,IF(AND(COUNTIF(A34,"3.*"),COUNTIF(E34,"4.*")),N12-(N12*H43),IF(AND(COUNTIF(A34,"4.*"),COUNTIF(E34,"1.*")),N12-((N12*D43)+I21),IF(AND(COUNTIF(A34,"4.*"),COUNTIF(E34,"2.*")),N12-((N12*D43)+(N12*H43)),IF(AND(COUNTIF(A34,"4.*"),COUNTIF(E34,"3.*")),N12-(N12*D43),IF(AND(COUNTIF(A34,"4.*"),COUNTIF(E34,"4.*")),N12-((N12*D43)+(N12*H43)),IF(COUNTIF(A34,"1.*"),N12-H21,IF(OR(COUNTIF(A34,"2.*"),COUNTIF(A34,"4.*")),N12-(N12*D43),IF(COUNTIF(A34,"3.*"),N12-D41,IF(COUNTIF(E34,"1.*"),N12-I21,IF(OR(COUNTIF(E34,"2.*"),COUNTIF(E34,"4.*")),N12-(N12*H43),SUM(A19*F19,A20*F20)))))))))))))))))))))))) -> 375 | O23: =IF(COUNTIF(C7,""),"",IF(OR(COUNTIF(J9,"1.*"),COUNTIF(J9,"3.*"),COUNTIF(J9,"7.*")),"100%","")) | P23: =IF(COUNTIF(C7,""),"",IF(OR(COUNTIF(J9,"1.*"),COUNTIF(J9,"3.*"),COUNTIF(J9,"7.*")),IF(COUNTIF(I8,"*Younger*"),100%-15%-(H8*0.5%),IF(100%-15%+(H8*0.5%)>100%,100%,100%-15%+(H8*0.5%))),"")) | Q23: =IF(COUNTIF(C7,""),"",IF(OR(COUNTIF(J9,"1.*"),COUNTIF(J9,"3.*"),COUNTIF(J9,"7.*")),(N43)*P23,"")) | R23: =IF(COUNTIF(C7,""),"",IF(OR(COUNTIF(J9,"1.*"),COUNTIF(J9,"3.*"),COUNTIF(J9,"7.*")),Q23*O23,""))
A24: 12.5 | C24: =IF(COUNTIF(A34,"1.*"),B24*D39,"") | E24: =IF(COUNTIF(E34,"1.*"),D24*H39,"") | F24: 135 | G24: =IF(AND(COUNTIF(A34,"1.*"),COUNTIF(E34,"1.*")),SUM(A24*F24)-((C24*F24)+(E24*F24)),IF(COUNTIF(A34,"1.*"),SUM(A24*F24)-(C24*F24),IF(COUNTIF(E34,"1.*"),SUM(A24*F24)-(E24*F24),A24*F24))) -> 1687.5 | H24: =IF(COUNTIF(A34,"1.*"),SUM(C24*F24),"") | I24: =IF(COUNTIF(E34,"1.*"),SUM(D24*F24),"") | J24: =IF(COUNTIF(J9,"10.*"),"Member Delayed Calculation 1 13th Check",IF(OR(COUNTIF(J9,"1.*"),COUNTIF(J9,"3.*")),"ER Factor","")) | M24: =IF(AND(COUNTIF(A34,"3.*"),COUNTIF(E34,"3.*"),COUNTIF(J9,"10.*")),(M20+M21)-(D41+H41),IF(AND(COUNTIF(A34,"3.*"),COUNTIF(J9,"10.*")),(M20+M21),IF(AND(COUNTIF(E34,"3.*"),COUNTIF(J9,"10.*")),(M20+M21)-H41,IF(COUNTIF(J9,"10.*"),M20+M21,"")))) | N24: =IF(COUNTIF(J9,"10.*"),"",IF(OR(COUNTIF(J9,"1.*"),COUNTIF(J9,"3.*")),IF(DATEDIF(C3,C5,"m")<=600,((DATEDIF(C3,C5,"m")-540)*0.1%+22%),IF(DATEDIF(C3,C5,"m")<=660,((DATEDIF(C3,C5,"m")-600)*0.2%+28%),IF((DATEDIF(C3,C5,"m")-660)*0.5%+40%>=100%,100%,((DATEDIF(C3,C5,"m")-660)*0.5%+40%)))),"")) | O24: =IF(COUNTIF(C7,""),"",IF(OR(COUNTIF(J9,"1.*"),COUNTIF(J9,"3.*"),COUNTIF(J9,"7.*")),"13th Check","")) | P24: =IF(COUNTIF(C7,""),"",IF(OR(COUNTIF(J9,"1.*"),COUNTIF(J9,"3.*"),COUNTIF(J9,"7.*")),IF(COUNTIF(I8,"*Younger*"),100%-15%-(H8*0.5%),IF(100%-15%+(H8*0.5%)>100%,100%,100%-15%+(H8*0.5%))),"")) | Q24: =IF(COUNTIF(C7,""),"",IF(OR(COUNTIF(J9,"1.*"),COUNTIF(J9,"3.*"),COUNTIF(J9,"7.*")),(N44)*P24,"")) | R24: =IF(COUNTIF(C7,""),"",IF(OR(COUNTIF(J9,"1.*"),COUNTIF(J9,"3.*"),COUNTIF(J9,"7.*")),Q24*O23,""))
C25: =IF(COUNTIF(A34,"1.*"),B25*D39,"") | E25: =IF(COUNTIF(E34,"1.*"),D25*H39,"") | F25: 70 | G25: =IF(AND(COUNTIF(A34,"1.*"),COUNTIF(E34,"1.*")),SUM(A25*F25)-((C25*F25)+(E25*F25)),IF(COUNTIF(A34,"1.*"),SUM(A25*F25)-(C25*F25),IF(COUNTIF(E34,"1.*"),SUM(A25*F25)-(E25*F25),A25*F25))) -> 0 | H25: =IF(COUNTIF(A34,"1.*"),SUM(C25*F25),"") | I25: =IF(COUNTIF(E34,"1.*"),SUM(D25*F25),"") | J25: =IF(COUNTIF(J9,"10.*"),"Delayed Retirement Calculation 2","")
A26: =SUM(A23:A25) -> 12.5 | B26: =IF(COUNTIF(A34,"1.*"),SUM(B23:B25),"") | C26: =IF(COUNTIF(A34,"1.*"),SUM(C23:C25),"") | D26: =IF(COUNTIF(E34,"1.*"),SUM(D23:D25),"") | E26: =IF(COUNTIF(E34,"1.*"),SUM(E23:E25),"") | F26: Subtotal | G26: =SUM(G23:G25) -> 1687.5 | H26: =IF(COUNTIF(A34,"1.*"),SUM(H23:H25),"") | I26: =IF(COUNTIF(E34,"1.*"),SUM(I23:I25),"") | J26: =IF(OR(COUNTIF(J9,"1.*"),COUNTIF(J9,"3.*")),"ER Benefit from 09/01/2011 to 09/30/2014",IF(DATEDIF(C3,C5,"m")>=780,"Date member turned 65","")) -> Date member turned 65 | M26: =IF(COUNTIF(J9,"10.*"),IF(DATEDIF(C3,C5,"m")>=780,EDATE(C3,65*12),""),"") | N26: =IF(OR(COUNTIF(J9,"1.*"),COUNTIF(J9,"3.*")),N23*N24,"")
A27: =SUM(A17,A21,A26) -> 31.01 | B27: =IF(COUNTIF(A34,"1.*"),SUM(B17,B21,B26),"") | C27: =IF(COUNTIF(A34,"1.*"),SUM(C17,C21,C26),"") | D27: =IF(COUNTIF(E34,"1.*"),SUM(D17,D21,D26),"") | E27: =IF(COUNTIF(E34,"1.*"),SUM(E17,E21,E26),"") | F27: =IF(COUNTIF(J9,"10.*"),"Pre-Age 65 Total","Total") -> Total | G27: =SUM(G17,G21,G26) -> 3911.37 | H27: =IF(COUNTIF(A34,"1.*"),SUM(H17,H21,H26),"") | I27: =IF(COUNTIF(E34,"1.*"),SUM(I17,I21,I26),"") | J27: =IF(COUNTIF(J9,"2.*"),"",IF(COUNTIF(J9,"10.*"),IF(DATEDIF(C3,C5,"m")>=846,"Date member turned 70 1/2",""),"Member Benefit on and After 10/01/2014:")) -> Member Benefit on and After 10/01/2014: | M27: =IF(COUNTIF(J9,"10.*"),IF(DATEDIF(C3,C5,"m")>=846,EDATE(C3,70*12+6),""),"") | N27: =IF(OR(COUNTIF(J9,"2.*"),COUNTIF(J9,"10.*")),"",IF(AND(COUNTIF(A34,"1.*"),COUNTIF(E34,"1.*")),N13-(H26+I26),IF(AND(COUNTIF(A34,"1.*"),COUNTIF(E34,"2.*")),N13-(H26+(N13*H43)),IF(AND(COUNTIF(A34,"1.*"),COUNTIF(E34,"3.*")),N13-H26,IF(AND(COUNTIF(A34,"1.*"),COUNTIF(E34,"4.*")),N13-(H26+(N13*H43)),IF(AND(COUNTIF(A34,"2.*"),COUNTIF(E34,"1.*")),N13-((N13*D43)+I26),IF(AND(COUNTIF(A34,"2.*"),COUNTIF(E34,"2.*")),N13-((N13*D43)+(N13*H43)),IF(AND(COUNTIF(A34,"2.*"),COUNTIF(E34,"3.*")),N13-(N13*D43),IF(AND(COUNTIF(A34,"2.*"),COUNTIF(E34,"4.*")),N13-((N13*D43)+(N13*H43)),IF(AND(COUNTIF(A34,"3.*"),COUNTIF(E34,"1.*")),N13-I26,IF(AND(COUNTIF(A34,"3.*"),COUNTIF(E34,"2.*")),N13-(N13*H43),IF(AND(COUNTIF(A34,"3.*"),COUNTIF(E34,"3.*")),N13,IF(AND(COUNTIF(A34,"3.*"),COUNTIF(E34,"4.*")),N13-(N13*H43),IF(AND(COUNTIF(A34,"4.*"),COUNTIF(E34,"1.*")),N13-((N13*D43)+I17),IF(AND(COUNTIF(A34,"4.*"),COUNTIF(E34,"2.*")),N13-((N13*D43)+(N13*H43)),IF(AND(COUNTIF(A34,"4.*"),COUNTIF(E34,"3.*")),N13-(N13*D43),IF(AND(COUNTIF(A34,"4.*"),COUNTIF(E34,"4.*")),N13-((N13*D43)+(N13*H43)),IF(COUNTIF(A34,"1.*"),N13-H26,IF(OR(COUNTIF(A34,"2.*"),COUNTIF(A34,"4.*")),N13-(N13*D43),IF(COUNTIF(A34,"3.*"),N13-D42,IF(COUNTIF(E34,"1.*"),N13-I26,IF(OR(COUNTIF(E34,"2.*"),COUNTIF(E34,"4.*")),N13-(N13*H43),SUM(A23*F23,A24*F24,A25*F25,A25*F25))))))))))))))))))))))) -> 1687.5
A28: =IF(COUNTIF(J9,"10.*"),"Credits Earned After Age 65","") | J28: =IF(OR(COUNTIF(J9,"1.*"),COUNTIF(J9,"3.*"),COUNTIF(J9,"7.*")),"ER Factor",IF(COUNTIF(J9,"10.*"),"Member Benefit Prior to 09/01/2011:","")) | M28: =IF(OR(COUNTIF(J9,"1.*"),COUNTIF(J9,"2.*"),COUNTIF(J9,"3.*"),COUNTIF(J9,"4.*"),COUNTIF(J9,"5.*"),COUNTIF(J9,"6.*"),COUNTIF(J9,"7.*"),COUNTIF(J9,"8.*"),COUNTIF(J9,"9.*")),"",IF(COUNTIF(J9,"10*"),SUM(G17:I17),"")) | N28: =IF(OR(COUNTIF(J9,"1.*"),COUNTIF(J9,"3.*"),COUNTIF(J9,"7.*")),IF(DATEDIF(C3,C5,"m")<=600,(DATEDIF(C3,C5,"m")-540)*0.1%+22%,IF(DATEDIF(C3,C5,"m")<=660,(DATEDIF(C3,C5,"m")-600)*0.2%+28%,IF((DATEDIF(C3,C5,"m")-660)*0.5%+40%>=100%,100%,(DATEDIF(C3,C5,"m")-660)*0.5%+40%))),"")
F29: =IF(COUNTIF(J9,"10.*"),105,"") | G29: =IF(COUNTIF(J9,"10.*"),IF(AND(COUNTIF(A34,"1.*"),COUNTIF(E34,"1.*")),SUM(A29*F29)-((C29*F29)+(E29*F29)),IF(COUNTIF(A34,"1.*"),SUM(A29*F29)-(C29*F29),IF(COUNTIF(E34,"1.*"),SUM(A29*F29)-(E29*F29),IF(COUNTIF(J9,"10.*"),A29*F29,"")))),"") | H29: =IF(AND(COUNTIF(J9,"10.*"),COUNTIF(A34,"1.*")),SUM(C29*F29),"") | I29: =IF(COUNTIF(E34,"1.*"),SUM(D29*F29),"") | J29: =IF(OR(COUNTIF(J9,"1.*"),COUNTIF(J9,"3.*"),COUNTIF(J9,"7.*")),"ER Benefit on or After 10/01/2014",IF(COUNTIF(J9,"10.*"),"Member Benefit from 09/01/2011 to 09/30/2014","")) | M29: =IF(OR(COUNTIF(J9,"1.*"),COUNTIF(J9,"2.*"),COUNTIF(J9,"3.*"),COUNTIF(J9,"4.*"),COUNTIF(J9,"5.*"),COUNTIF(J9,"6.*"),COUNTIF(J9,"7.*"),COUNTIF(J9,"8.*"),COUNTIF(J9,"9.*")),"",IF(COUNTIF(J9,"10*"),SUM(G21:I21))) | N29: =IF(OR(COUNTIF(J9,"1.*"),COUNTIF(J9,"3.*"),COUNTIF(J9,"7.*")),ROUND(N27*N28,2),"")
F30: =IF(COUNTIF(J9,"10.*"),135,"") | G30: =IF(COUNTIF(J9,"10.*"),IF(AND(COUNTIF(A34,"1.*"),COUNTIF(E34,"1.*")),SUM(A30*F30)-((C30*F30)+(E30*F30)),IF(COUNTIF(A34,"1.*"),SUM(A30*F30)-(C30*F30),IF(COUNTIF(E34,"1.*"),SUM(A30*F30)-(E30*F30),IF(COUNTIF(J9,"10.*"),A30*F30,"")))),"") | H30: =IF(AND(COUNTIF(J9,"10.*"),COUNTIF(A34,"1.*")),SUM(C30*F30),"") | I30: =IF(COUNTIF(E34,"1.*"),SUM(D30*F30),"") | J30: =IF(COUNTIF(J9,"10.*"),"Member Benefit on and After 10/01/2014","") | M30: =IF(COUNTIF(J9,"10*"),SUM(G26:I26),"")
G31: =IF(COUNTIF(J9,"10.*"),IF(AND(COUNTIF(A34,"1.*"),COUNTIF(E34,"1.*")),SUM(A31*F31)-((C31*F31)+(E31*F31)),IF(COUNTIF(A34,"1.*"),SUM(A31*F31)-(C31*F31),IF(COUNTIF(E34,"1.*"),SUM(A31*F31)-(E31*F31),IF(COUNTIF(J9,"10.*"),A31*F31,"")))),"") | H31: =IF(AND(COUNTIF(J9,"10.*"),COUNTIF(A34,"1.*")),SUM(C31*F31),"") | I31: =IF(COUNTIF(E34,"1.*"),SUM(D30*F30),"") | J31: =IF(COUNTIF(J9,"10.*"),"First 60 Months With 40 Hours or Less (1%):","")
A32: =IF(COUNTIF(J9,"10.*"),SUM(A29:A31),"") | B32: =IF(AND(COUNTIF(J9,"10.*"),COUNTIF(A34,"1.*")),SUM(B29:B31),"") | C32: =IF(AND(COUNTIF(J9,"10.*"),COUNTIF(A34,"1.*")),SUM(C29:C31),"") | D32: =IF(AND(COUNTIF(J9,"10.*"),COUNTIF(E34,"1.*")),SUM(D29:D31),"") | E32: =IF(AND(COUNTIF(J9,"10.*"),COUNTIF(E34,"1.*")),SUM(E29:E31),"") | F32: =IF(COUNTIF(J9,"10.*"),"Subtotal","") | G32: =IF(COUNTIF(J9,"10.*"),SUM(G29:G31),"") | H32: =IF(AND(COUNTIF(J9,"10.*"),COUNTIF(A34,"1.*")),SUM(H29:H31),"") | I32: =IF(AND(COUNTIF(J9,"10.*"),COUNTIF(E34,"1.*")),SUM(I29:I31),"") | J32: =IF(COUNTIF(J9,"10.*"),"61 or More Months With 40 Hours or Less (1.5%):","")
A33: =IF(COUNTIF(J9,"10.*"),SUM(A17,A21,A26,A32),"") | B33: =IF(AND(COUNTIF(J9,"10.*"),COUNTIF(A34,"1.*")),SUM(B17,B21,B26,B32),"") | D33: =IF(AND(COUNTIF(J9,"10.*"),COUNTIF(E34,"1.*")),SUM(D17,D21,D26,D32),"") | F33: =IF(COUNTIF(J9,"10.*"),"Total","") | G33: =IF(COUNTIF(J9,"10.*"),SUM(G17,G21,G26,G32),"") | H33: =IF(AND(COUNTIF(J9,"10.*"),COUNTIF(A34,"1.*")),SUM(H17,H21,H26,H32),"") | I33: =IF(AND(COUNTIF(J9,"10.*"),COUNTIF(E34,"1.*")),SUM(I17,I21,I26,I32),"") | J33: =IF(COUNTIF(J9,"10.*"),"Delayed Calculation 2 Retirement Increase:","") | M33: =IF(COUNTIF(J9,"10.*"),SUM(M31*1%,M32*1.5%),"")
A34: 3. AP in Pay Status | E34: Select AP 2 Award Type | J34: =IF(COUNTIF(J9,"10.*"),"Delayed Monthly Benefit Increase:","") | M34: =IF(COUNTIF(J9,"10.*"),(M28+M29+M30)*M33,"")
A35: =IF(COUNTIF(A34,"_"),"","AP 1 QDRO Calculation") -> AP 1 QDRO Calculation | E35: =IF(COUNTIF(E34,"_"),"","AP 2 QDRO Calculation") -> AP 2 QDRO Calculation | J35: =IF(COUNTIF(J9,"10.*"),"Delayed 13th Check Increase:","") | M35: =IF(COUNTIF(J9,"10.*"),(M28+M29)*M33,"")
A36: =IF(COUNTIF(A34,"Select*"),"","AP 1 Name:") -> AP 1 Name: | B36: Andrea Johnson | C36: =IF(COUNTIF(A34,"Select*"),"","AP 1 DOB:") -> AP 1 DOB: | D36: 27365 | E36: =IF(COUNTIF(E34,"Select*"),"","AP 2 Name:") | G36: =IF(COUNTIF(E34,"Select*"),"","AP 2 DOB:") | J36: =IF(COUNTIF(A34,"_"),"",IF(COUNTIF(J9,"10.*"),"Alternate Payee 1 Award:","")) | M36: =IF(COUNTIF(A34,"_"),"",IF(COUNTIF(J9,"10.*"),D56,""))
A37: =IF(COUNTIF(A34,"Select*"),"","DOM:") -> DOM: | B37: 35539 | C37: =IF(COUNTIF(A34,"Select*"),"","DOS:") -> DOS: | D37: 40522 | E37: =IF(COUNTIF(E34,"Select*"),"","DOM:") | G37: =IF(COUNTIF(E34,"Select*"),"","DOS:") | J37: =IF(COUNTIF(A34,"_"),"",IF(COUNTIF(J9,"10.*"),"Alternate Payee 1 13th Check:","")) | M37: =IF(COUNTIF(A34,"_"),"",IF(COUNTIF(J9,"10.*"),D57,""))
A38: =IF(COUNTIF(A34,"_"),"",IF(COUNTIF(A34,"2.*"),"Total Service Credits:",IF(COUNTIF(A34,"4.*"),"Total Months Worked",""))) | B38: =IF(COUNTIF(A34,"_"),"",IF(COUNTIF(A34,"2.*"),SUM(A11:A16,A19:A20,A23:A25,A29:A31),IF(COUNTIF(A34,"4.*"),SUM('QDRO Month Calc'!B4:B69),""))) | C38: =IF(COUNTIF(A34,"_"),"",IF(COUNTIF(A34,"2.*"),"Total Credits EDM:",IF(COUNTIF(A34,"3.*"),"",IF(COUNTIF(A34,"4.*"),"Total Months Worked During Marriage","")))) | E38: =IF(COUNTIF(E34,"Select*"),"",IF(COUNTIF(E34,"2.*"),"Total Service Credits:",IF(COUNTIF(E34,"4.*"),"Total Months Worked",""))) | F38: =IF(COUNTIF(E34,"_"),"",IF(COUNTIF(E34,"2.*"),SUM(A11:A16,A19:A20,A23:A25),IF(COUNTIF(E34,"4.*"),SUM('QDRO Month Calc'!H4:H69),""))) | G38: =IF(COUNTIF(E34,"_"),"",IF(COUNTIF(E34,"2.*"),"Total Credits EDM:",IF(COUNTIF(E34,"3.*"),"",IF(COUNTIF(E34,"4.*"),"Total Months Worked During Marriage",""))))
A39: =IF(COUNTIF(A34,"_"),"",IF(OR(COUNTIF(A34,"2.*"),COUNTIF(A34,"4.*")),"Community Property Percentage:","")) | B39: =IF(COUNTIF(A34,"_"),"",IF(OR(COUNTIF(A34,"2.*"),COUNTIF(A34,"4.*")),ROUNDDOWN(SUM(D38/B38),4),"")) | C39: =IF(COUNTIF(A34,"_"),"",IF(OR(COUNTIF(A34,"1.*"),COUNTIF(A34,"2.*"),COUNTIF(A34,"4.*")),"Percentage Amount Awarded to AP 1:","")) | E39: =IF(COUNTIF(E34,"Select*"),"",IF(OR(COUNTIF(E34,"2.*"),COUNTIF(E34,"4.*")),"Community Property Percentage:","")) | F39: =IF(COUNTIF(E34,"_"),"",IF(OR(COUNTIF(E34,"2.*"),COUNTIF(E34,"4.*")),ROUNDDOWN(SUM(H38/F38),4),"")) | G39: =IF(COUNTIF(E34,"_"),"",IF(OR(COUNTIF(E34,"1.*"),COUNTIF(E34,"2.*"),COUNTIF(E34,"4.*")),"Percentage Amount Awarded to AP 2:",""))
A40: =IF(COUNTIF(A34,"_"),"",IF(COUNTIF(A34,"3.*"),"AP 1 Awarded Amount prior to 09/01/2011:","")) -> AP 1 Awarded Amount prior to 09/01/2011: | D40: 795.42 | E40: =IF(COUNTIF(E34,"Select*"),"",IF(COUNTIF(E34,"3.*"),"AP 2 Awarded Monthly Amount:","")) | J40: =IF(COUNTIF(J9,"10.*"),"Delayed Calculation 2 Member Monthly Benefit:","Member Monthly Benefit After AP Reductions:") -> Member Monthly Benefit After AP Reductions: | M40: =IF(COUNTIF(J9,"10.*"),(M28+M29+M30+((M28+M29+M30)*M33))-SUM(D56,H56),"") | N40: =IF(COUNTIF(J9,"10.*"),"",IF(COUNTIF(J9,"1.*"),SUM(N22,N26,N29),IF(COUNTIF(J9,"3.*"),SUM(N20,N26,N29),IF(COUNTIF(J9,"7.*"),SUM(N20,N23,N29),SUM(N20,N23,N27))))) -> 3115.95
A41: =IF(COUNTIF(A34,"_"),"",IF(COUNTIF(A34,"3.*"),"AP 1 Awarded Amount on and between 09/01/2011 to 09/30/2014:","")) -> AP 1 Awarded Amount on and between 09/01/2011 to 09/30/2014: | E41: =IF(COUNTIF(E34,"Select*"),"",IF(COUNTIF(E34,"3.*"),"AP 2 Awarded 13th Check Amount:","")) | J41: =IF(COUNTIF(J9,"10.*"),"Delayed Calculation 2 Member 13th Check Benefit:","Member 13th Check After AP Reductions:") -> Member 13th Check After AP Reductions: | M41: =IF(COUNTIF(J9,"10.*"),(M28+M29+((M28+M29)*M33))-SUM(D57,H57),"") | N41: =IF(COUNTIF(J9,"10.*"),"",IF(COUNTIF(J9,"1.*"),SUM(N22,N26,N29),IF(COUNTIF(J9,"3.*"),SUM(N20,N26,N29),IF(COUNTIF(J9,"7.*"),SUM(N20,N23,N29),SUM(N20,N23,N27))))) -> 3115.95
A42: =IF(COUNTIF(A34,"_"),"",IF(COUNTIF(A34,"3.*"),"AP 1 Awarded Amount on and after 10/01/2014:","")) -> AP 1 Awarded Amount on and after 10/01/2014: | J42: =IF(COUNTIF(J9,"10.*"),"Delayed Calculation 1 Monthly Amount","") | M42: =IF(COUNTIF(J9,"10.*"),M23,"")
A43: =IF(COUNTIF(A34,"_"),"",IF(OR(COUNTIF(A34,"2.*"),COUNTIF(A34,"4.*")),"Final AP 1 Awarded Percentage:","")) | D43: =IF(COUNTIF(A34,"_"),"",IF(OR(COUNTIF(A34,"2.*"),COUNTIF(A34,"4.*")),ROUNDDOWN(SUM(B39*D39),4),"")) | E43: =IF(COUNTIF(E34,"Select*"),"",IF(OR(COUNTIF(E34,"2.*"),COUNTIF(E34,"4.*")),"Final AP 2 Awarded Percentage:","")) | H43: =IF(COUNTIF(E34,"Select*"),"",IF(OR(COUNTIF(E34,"2.*"),COUNTIF(E34,"4.*")),ROUNDDOWN(SUM(F39*H39),4),"")) | J43: =IF(COUNTIF(J9,"10.*"),"Delayed Calculation 2 Monthly Amount",IF(OR(COUNTIF(J9,"1.*"),COUNTIF(J9,"3.*"),COUNTIF(J9,"7.*")),"Member Benefit Deferred at Age 65 After AP Reductions:","")) | M43: =IF(COUNTIF(J9,"10.*"),M40,"") | N43: =IF(OR(COUNTIF(J9,"1.*"),COUNTIF(J9,"3.*"),COUNTIF(J9,"7.*")),SUM(N20,N23,N27),"")
A44: =IF(COUNTIF(A34,"_"),"",IF(OR(COUNTIF(A34,"1.*"),COUNTIF(A34,"2.*"),COUNTIF(A34,"4.*")),IF(COUNTIF(J9,"10*"),"AP 1 Delayed Calc 1 Benefit Prior to 09/01/2011:","AP 1 Full Benefit Prior to 09/01/2011:"),"")) | D44: =IF(COUNTIF(A34,"_"),"",IF(OR(COUNTIF(A34,"2.*"),COUNTIF(A34,"4.*")),ROUND(N11*D43,2),IF(COUNTIF(A34,"1.*"),H17,""))) | E44: =IF(COUNTIF(E34,"Select*"),"",IF(OR(COUNTIF(E34,"1.*"),COUNTIF(E34,"2.*"),COUNTIF(E34,"4.*")),"AP 2 Delayed Calc 1 Benefit Prior to 09/01/2011:","AP 2 Full Benefit Prior to 09/01/2011:")) | H44: =IF(COUNTIF(E34,"Select*"),"",IF(OR(COUNTIF(E34,"2.*"),COUNTIF(E34,"4.*")),N11*H43,IF(COUNTIF(E34,"1.*"),I17,""))) | J44: =IF(COUNTIF(J9,"10.*"),"Greater of Calculation 1 and 2",IF(OR(COUNTIF(J9,"1.*"),COUNTIF(J9,"3.*"),COUNTIF(J9,"7.*")),"Member 13th Check After AP Reductions:","")) | L44: =IF(COUNTIF(J9,"10.*"),IF(M42>=M43,"Calculation 1","Calculation 2"),"") | M44: =IF(COUNTIF(J9,"10.*"),IF(M42>=M43,M42,M43),"") | N44: =IF(OR(COUNTIF(J9,"1.*"),COUNTIF(J9,"3.*"),COUNTIF(J9,"7.*")),SUM(N20,N23),"")
A45: =IF(COUNTIF(A34,"_"),"",IF(OR(COUNTIF(A34,"1.*"),COUNTIF(A34,"2.*"),COUNTIF(A34,"4.*")),IF(OR(COUNTIF(J9,"1.*"),COUNTIF(J9,"6.*")),"AP 1 Early Retirement Factor:",""),"")) | D45: =IF(OR(COUNTIF(A34,"1.*"),COUNTIF(A34,"2.*"),COUNTIF(A34,"4.*")),IF(OR(COUNTIF(J9,"1.*"),COUNTIF(J9,"6.*")),IF(DATEDIF(C3,C5,"m")<=600,(DATEDIF(C3,C5,"m")-540)*0.1%+40%,IF(DATEDIF(C3,C5,"m")<=660,(DATEDIF(C3,C5,"m")-600)*0.2%+46%,IF((DATEDIF(C3,C5,"m")-660)*0.5%+58%>=100%,100%,(DATEDIF(C3,C5,"m")-660)*0.5%+58%))),""),"") | E45: =IF(COUNTIF(E34,"_"),"",IF(OR(COUNTIF(E34,"1.*"),COUNTIF(E34,"2.*"),COUNTIF(E34,"4.*")),IF(OR(COUNTIF(J9,"1.*"),COUNTIF(J9,"6.*")),"AP 2 Early Retirement Factor:",""),"")) | H45: =IF(OR(COUNTIF(E34,"1.*"),COUNTIF(E34,"2.*"),COUNTIF(E34,"4.*")),IF(OR(COUNTIF(J9,"1.*"),COUNTIF(J9,"6.*")),IF(DATEDIF(C3,C5,"m")<=600,(DATEDIF(C3,C5,"m")-540)*0.1%+40%,IF(DATEDIF(C3,C5,"m")<=660,(DATEDIF(C3,C5,"m")-600)*0.2%+46%,IF((DATEDIF(C3,C5,"m")-660)*0.5%+58%>=100%,100%,(DATEDIF(C3,C5,"m")-660)*0.5%+58%))),""),"")
A46: =IF(COUNTIF(A34,"_"),"",IF(OR(COUNTIF(A34,"1.*"),COUNTIF(A34,"2.*"),COUNTIF(A34,"4.*")),IF(OR(COUNTIF(J9,"1.*"),COUNTIF(J9,"6.*")),"AP 1 Early Benefit Prior to 09/01/2011:",""),"")) | D46: =IF(OR(COUNTIF(A34,"Select*"),COUNTIF(A34,"3.*")),"",IF(OR(COUNTIF(A34,"2.*"),COUNTIF(A34,"4.*")),IF(OR(COUNTIF(J9,"1.*"),COUNTIF(J9,"6.*")),D44*D45,""),IF(COUNTIF(A34,"1.*"),IF(OR(COUNTIF(J9,"1.*"),COUNTIF(J9,"6.*")),ROUND(D44*D45,2),"")))) | E46: =IF(COUNTIF(E34,"_"),"",IF(OR(COUNTIF(E34,"1.*"),COUNTIF(E34,"2.*"),COUNTIF(E34,"4.*")),IF(OR(COUNTIF(J9,"1.*"),COUNTIF(J9,"6.*")),"AP 2 Early Benefit Prior to 09/01/2011:",""),"")) | H46: =IF(OR(COUNTIF(E34,"Select*"),COUNTIF(E34,"3.*")),"",IF(OR(COUNTIF(E34,"2.*"),COUNTIF(E34,"4.*")),IF(OR(COUNTIF(J9,"1.*"),COUNTIF(J9,"6.*")),H44*H45,""),IF(COUNTIF(E34,"1.*"),IF(OR(COUNTIF(J9,"1.*"),COUNTIF(J9,"6.*")),H44*H45,""))))
A47: =IF(COUNTIF(A34,"_"),"",IF(OR(COUNTIF(A34,"1.*"),COUNTIF(A34,"2.*"),COUNTIF(A34,"4.*")),IF(COUNTIF(J9,"10*"),"AP 1 Delayed Calc 1 Benefit on 09/01/2011 to 09/30/2014:","AP 1 Full Benefit on 09/01/2011 to 09/30/2014:"),"")) | D47: =IF(OR(COUNTIF(A34,"Select*"),COUNTIF(A34,"3.*")),"",IF(COUNTIF(A34,"1.*"),H21,IF(OR(COUNTIF(A34,"2.*"),COUNTIF(A34,"4.*")),IF(COUNTIF(J9,"2.*"),"",ROUND(N12*D43,2))))) | E47: =IF(COUNTIF(E34,"Select*"),"",IF(OR(COUNTIF(E34,"1.*"),COUNTIF(E34,"2.*"),COUNTIF(E34,"4.*")),IF(COUNTIF(J9,"10*"),"AP 2 Delayed Calc 1 Benefit on 09/01/2011 to 09/30/2014:","AP 2 Full Benefit on 09/01/2011 to 09/30/2014:"))) | H47: =IF(COUNTIF(E34,"Select*"),"",IF(OR(COUNTIF(E34,"2.*"),COUNTIF(E34,"4.*")),N12*H43,IF(COUNTIF(E34,"1.*"),I21,"")))
A48: =IF(COUNTIF(A34,"_"),"",IF(OR(COUNTIF(A34,"1.*"),COUNTIF(A34,"2.*"),COUNTIF(A34,"4.*")),IF(OR(COUNTIF(J9,"1.*"),COUNTIF(J9,"3.*"),COUNTIF(J9,"4.*"),COUNTIF(J9,"6.*")),"AP 1 Early Retirement Factor:",""),"")) | D48: =IF(OR(COUNTIF(A34,"1.*"),COUNTIF(A34,"2.*"),COUNTIF(A34,"4.*")),IF(OR(COUNTIF(J9,"1.*"),COUNTIF(J9,"3.*"),COUNTIF(J9,"4.*"),COUNTIF(J9,"6.*")),IF(DATEDIF(C3,C5,"m")<=600,(DATEDIF(C3,C5,"m")-540)*0.1%+22%,IF(DATEDIF(C3,C5,"m")<=660,(DATEDIF(C3,C5,"m")-600)*0.2%+28%,IF((DATEDIF(C3,C5,"m")-660)*0.5%+40%>=100%,100%,(DATEDIF(C3,C5,"m")-660)*0.5%+40%))),""),"") | E48: =IF(COUNTIF(E34,"_"),"",IF(OR(COUNTIF(E34,"1.*"),COUNTIF(E34,"2.*"),COUNTIF(E34,"4.*")),IF(OR(COUNTIF(J9,"1.*"),COUNTIF(J9,"3.*"),COUNTIF(J9,"4.*"),COUNTIF(J9,"6.*")),"AP 2 Early Retirement Factor:",""),"")) | H48: =IF(OR(COUNTIF(E34,"1.*"),COUNTIF(E34,"2.*"),COUNTIF(E34,"4.*")),IF(OR(COUNTIF(J9,"1.*"),COUNTIF(J9,"3.*"),COUNTIF(J9,"4.*"),COUNTIF(J9,"6.*")),IF(DATEDIF(C3,C5,"m")<=600,(DATEDIF(C3,C5,"m")-540)*0.1%+22%,IF(DATEDIF(C3,C5,"m")<=660,(DATEDIF(C3,C5,"m")-600)*0.2%+28%,IF((DATEDIF(C3,C5,"m")-660)*0.5%+40%>=100%,100%,(DATEDIF(C3,C5,"m")-660)*0.5%+40%))),""),"")
A49: =IF(COUNTIF(A34,"_"),"",IF(OR(COUNTIF(A34,"1.*"),COUNTIF(A34,"2.*"),COUNTIF(A34,"4.*")),IF(OR(COUNTIF(J9,"1.*"),COUNTIF(J9,"3.*"),COUNTIF(J9,"4.*"),COUNTIF(J9,"6.*")),"AP 1 Early Benefit from 09/01/2011 to 09/30/2014:",""),"")) | D49: =IF(COUNTIF(A34,"_"),"",IF(OR(COUNTIF(A34,"1.*"),COUNTIF(A34,"2.*"),COUNTIF(A34,"4.*")),IF(OR(COUNTIF(J9,"1.*"),COUNTIF(J9,"3.*"),COUNTIF(J9,"4.*"),COUNTIF(J9,"6.*")),ROUND(D47*D48,2),""),"")) | E49: =IF(COUNTIF(E34,"_"),"",IF(OR(COUNTIF(E34,"1.*"),COUNTIF(E34,"2.*"),COUNTIF(E34,"4.*")),IF(OR(COUNTIF(J9,"1.*"),COUNTIF(J9,"3.*"),COUNTIF(J9,"4.*"),COUNTIF(J9,"6.*")),"AP 2 Early Benefit from 09/01/2011 to 09/30/2014:",""),"")) | H49: =IF(COUNTIF(E34,"_"),"",IF(OR(COUNTIF(E34,"1.*"),COUNTIF(E34,"2.*"),COUNTIF(E34,"4.*")),IF(OR(COUNTIF(J9,"1.*"),COUNTIF(J9,"3.*"),COUNTIF(J9,"4.*"),COUNTIF(J9,"6.*")),H47*H48,""),""))
A50: =IF(COUNTIF(A34,"_"),"",IF(OR(COUNTIF(A34,"1.*"),COUNTIF(A34,"2.*"),COUNTIF(A34,"4.*")),IF(COUNTIF(J9,"10*"),"AP 1 Delayed Calc 1 Benefit on and after 10/01/2014:","AP 1 Full Benefit After 10/01/2014:"),"")) | D50: =IF(OR(COUNTIF(A34,"Select*"),COUNTIF(A34,"3.*")),"",IF(AND(COUNTIF(A34,"1.*"),COUNTIF(J9,"10.*")),H26+H32,IF(COUNTIF(A34,"1.*"),H26,IF(OR(COUNTIF(A34,"2.*"),COUNTIF(A34,"4.*")),IF(COUNTIF(J9,"2.*"),"",ROUND(N13*D43,2)))))) | E50: =IF(COUNTIF(E34,"Select*"),"",IF(OR(COUNTIF(E34,"1.*"),COUNTIF(E34,"2.*"),COUNTIF(E34,"4.*")),IF(COUNTIF(J9,"10.*"),"AP 2 Delayed Calc 1 Benefit on and after 10/01/2014:","AP 2 Full Benefit After 10/01/2014:"))) | H50: =IF(COUNTIF(E34,"_"),"",IF(AND(COUNTIF(E34,"1.*"),COUNTIF(J9,"10.*")),I26+I32,IF(OR(COUNTIF(E34,"2.*"),COUNTIF(E34,"4.*")),N13*H43,IF(COUNTIF(E34,"1.*"),I26,""))))
A51: =IF(OR(COUNTIF(A34,"Select*"),COUNTIF(A34,"3.*")),"",IF(OR(COUNTIF(A34,"1.*"),COUNTIF(A34,"2.*"),COUNTIF(A34,"4.*")),IF(OR(COUNTIF(J9,"1.*"),COUNTIF(J9,"3.*"),COUNTIF(J9,"4.*"),COUNTIF(J9,"6.*"),COUNTIF(J9,"7.*"),COUNTIF(J9,"8.*")),"AP 1 Early Retirement Factor:",IF(COUNTIF(J9,"10.*"),"AP 1 Delayed Calc 1 Monthly Benefit:","")))) | C51: =IF(OR(COUNTIF(A34,"Select*"),COUNTIF(A34,"3.*")),"",IF(OR(COUNTIF(A34,"1.*"),COUNTIF(A34,"2.*"),COUNTIF(A34,"4.*")),IF(COUNTIF(J9,"10.*"),D44+D47+D50,""))) | D51: =IF(OR(COUNTIF(A34,"1.*"),COUNTIF(A34,"2.*"),COUNTIF(A34,"4.*")),IF(OR(COUNTIF(J9,"1.*"),COUNTIF(J9,"3.*"),COUNTIF(J9,"4.*"),COUNTIF(J9,"6.*"),COUNTIF(J9,"7.*"),COUNTIF(J9,"8.*")),IF(DATEDIF(C3,C5,"m")<=600,(DATEDIF(C3,C5,"m")-540)*0.1%+22%,IF(DATEDIF(C3,C5,"m")<=660,(DATEDIF(C3,C5,"m")-600)*0.2%+28%,IF((DATEDIF(C3,C5,"m")-660)*0.5%+40%>=100%,100%,(DATEDIF(C3,C5,"m")-660)*0.5%+40%))),""),"") | E51: =IF(COUNTIF(E34,"Select*"),"",IF(OR(COUNTIF(E34,"1.*"),COUNTIF(E34,"2.*"),COUNTIF(E34,"4.*")),IF(OR(COUNTIF(J9,"1.*"),COUNTIF(J9,"3.*"),COUNTIF(J9,"4.*"),COUNTIF(J9,"6.*"),COUNTIF(J9,"7.*"),COUNTIF(J9,"8.*")),"AP 2 Early Retirement Factor:",IF(COUNTIF(J9,"10.*"),"AP 1 Delayed Calc 1 Monthly Benefit:","")))) | H51: =IF(OR(COUNTIF(E34,"1.*"),COUNTIF(E34,"2.*"),COUNTIF(E34,"4.*")),IF(OR(COUNTIF(J9,"1.*"),COUNTIF(J9,"3.*"),COUNTIF(J9,"4.*"),COUNTIF(J9,"6.*"),COUNTIF(J9,"7.*"),COUNTIF(J9,"8.*")),IF(DATEDIF(C3,C5,"m")<=600,(DATEDIF(C3,C5,"m")-540)*0.1%+22%,IF(DATEDIF(C3,C5,"m")<=660,(DATEDIF(C3,C5,"m")-600)*0.2%+28%,IF((DATEDIF(C3,C5,"m")-660)*0.5%+40%>=100%,100%,(DATEDIF(C3,C5,"m")-660)*0.5%+40%))),""),"")
A52: =IF(OR(COUNTIF(A34,"Select*"),COUNTIF(A34,"3.*")),"",IF(OR(COUNTIF(A34,"1.*"),COUNTIF(A34,"2.*"),COUNTIF(A34,"4.*")),IF(OR(COUNTIF(J9,"1.*"),COUNTIF(J9,"3.*"),COUNTIF(J9,"4.*"),COUNTIF(J9,"6.*"),COUNTIF(J9,"7.*"),COUNTIF(J9,"8.*")),"AP 1 Early Benefit on and after 10/01/2014:",IF(COUNTIF(J9,"10.*"),"AP 1 Delayed Calc 1 13th Check:","")))) | C52: =IF(OR(COUNTIF(A34,"Select*"),COUNTIF(A34,"3.*")),"",IF(OR(COUNTIF(A34,"1.*"),COUNTIF(A34,"2.*"),COUNTIF(A34,"4.*")),IF(COUNTIF(J9,"10.*"),D44+D47,""))) | D52: =IF(OR(COUNTIF(A34,"1.*"),COUNTIF(A34,"2.*"),COUNTIF(A34,"4.*")),IF(OR(COUNTIF(J9,"1.*"),COUNTIF(J9,"3.*"),COUNTIF(J9,"4.*"),COUNTIF(J9,"6.*"),COUNTIF(J9,"7.*"),COUNTIF(J9,"8.*")),ROUND(D50*D51,2),""),"") | E52: =IF(COUNTIF(E34,"Select*"),"",IF(OR(COUNTIF(E34,"1.*"),COUNTIF(E34,"2.*"),COUNTIF(E34,"4.*")),IF(OR(COUNTIF(J9,"1.*"),COUNTIF(J9,"3.*"),COUNTIF(J9,"4.*"),COUNTIF(J9,"6.*"),COUNTIF(J9,"7.*"),COUNTIF(J9,"8.*")),"AP 2 Early Benefit on and after 10/01/2014:",""),"")) | H52: =IF(OR(COUNTIF(E34,"1.*"),COUNTIF(E34,"2.*"),COUNTIF(E34,"4.*")),IF(OR(COUNTIF(J9,"1.*"),COUNTIF(J9,"3.*"),COUNTIF(J9,"4.*"),COUNTIF(J9,"6.*"),COUNTIF(J9,"7.*"),COUNTIF(J9,"8.*")),H50*H51,""),"")
A53: =IF(OR(COUNTIF(A34,"Select*"),COUNTIF(A34,"3.*")),"",IF(COUNTIF(J9,"10.*"),"Pre-65 Pension Credits:","")) | B53: =IF(OR(COUNTIF(A34,"_"),COUNTIF(A34,"3.*")),"",IF(COUNTIF(J9,"10.*"),A27,"")) | C53: =IF(OR(COUNTIF(A34,"_"),COUNTIF(A34,"3.*")),"",IF(COUNTIF(J9,"10.*"),"Pre-65 Pension Credits EDM:","")) | D53: =IF(OR(COUNTIF(A34,"Select*"),COUNTIF(A34,"3.*")),"",IF(COUNTIF(J9,"10.*"),IF(COUNTIF(A34,"1.*"),B27,IF(OR(COUNTIF(A34,"2.*"),COUNTIF(A34,"4.*")),D38,"")),""))
A54: =IF(COUNTIF(J9,"10.*"),IF(OR(COUNTIF(A34,"2.*"),COUNTIF(A34,"4.*")),"Community Property Percentage:",""),"") | B54: =IF(COUNTIF(A34,"Select*"),"",IF(COUNTIF(J9,"10.*"),IF(OR(COUNTIF(A34,"2.*"),COUNTIF(A34,"4.*")),ROUNDDOWN(SUM(D38/B53),4),""),"")) | C54: =IF(COUNTIF(J9,"10.*"),C39,"") | D54: =IF(OR(COUNTIF(A34,"Select*"),COUNTIF(A34,"3.*")),"",IF(COUNTIF(J9,"10.*"),D39,""))
A55: =IF(OR(COUNTIF(A34,"Select*"),COUNTIF(A34,"3.*")),"",IF(COUNTIF(J9,"10.*"),"Final AP 1 Awarded Percentage:","")) | D55: =IF(COUNTIF(J9,"10.*"),IF(OR(COUNTIF(A34,"2.*"),COUNTIF(A34,"4.*")),ROUNDDOWN(B54*D54,4),IF(COUNTIF(A34,"1.*"),ROUNDDOWN((D53/B53)*D54,4),"")),"")
A56: =IF(COUNTIF(A34,"Select*"),"",IF(COUNTIF(J9,"10.*"),IF(COUNTIF(A34,"3.*"),"AP 1 Delayed Calc 2 Monthly Benefit:","AP 1 Awarded Monthly Amount:"),"AP 1 Awarded Monthly Amount:")) -> AP 1 Awarded Monthly Amount: | D56: =IF(COUNTIF(A34,"Select*"),"",IF(COUNTIF(A34,"3.*"),D40+D41+D42,IF(COUNTIF(J9,"10.*"),IF(COUNTIF(A34,"3.*"),SUM(D40:D42),IF(OR(COUNTIF(A34,"2.*"),COUNTIF(A34,"4.*")),IF(COUNTIF(E34,"1.*"),(M28+M34)*(D55),ROUND((M28+M29+M30+M34)*D55,2)),IF(COUNTIF(A34,"1.*"),(H17+H21+H26)+((H17+H21+H26)*M33),""))),IF(OR(COUNTIF(J9,"1.*"),COUNTIF(J9,"6.*")),D46+D49+D52,IF(COUNTIF(J9,"2.*"),D44,IF(OR(COUNTIF(J9,"3.*"),COUNTIF(J9,"4.*")),D44+D49+D52,IF(OR(COUNTIF(J9,"5.*"),COUNTIF(J9,"9.*")),D44+D47+D50,IF(OR(COUNTIF(J9,"7.*"),COUNTIF(J9,"8.*")),D44+D47+D52,"")))))))) -> 795.42 | E56: =IF(COUNTIF(E34,"Select*"),"",IF(COUNTIF(J9,"10.*"),IF(COUNTIF(E34,"3.*"),"AP 1 Delayed Calc 2 Monthly Benefit:",""),"AP 1 Awarded Monthly Amount:"))
A57: =IF(COUNTIF(A34,"Select*"),"",IF(COUNTIF(J9,"10.*"),IF(COUNTIF(A34,"3.*"),"AP 1 Delayed Calc 2 13th Check Benefit:","AP 1 Awarded 13th Check Amount:"),"AP 1 Awarded 13th Check Amount:")) -> AP 1 Awarded 13th Check Amount: | D57: =IF(COUNTIF(A34,"Select*"),"",IF(COUNTIF(A34,"3.*"),D40+D41+D42,IF(COUNTIF(J9,"10.*"),IF(COUNTIF(A34,"3.*"),SUM(D40:D41),IF(OR(COUNTIF(A34,"2.*"),COUNTIF(A34,"4.*")),IF(COUNTIF(E34,"1.*"),(M29+(M29*M33))*(D55),(M29+M28+((M28+M29)*M33))*D55),IF(COUNTIF(A34,"1.*"),(H17+H21)+((H17+H21)*M33),""))),IF(OR(COUNTIF(J9,"1.*"),COUNTIF(J9,"6.*")),D46+D49,IF(COUNTIF(J9,"2.*"),D44,IF(OR(COUNTIF(J9,"3.*"),COUNTIF(J9,"4.*")),D44+D49,IF(OR(COUNTIF(J9,"5.*"),COUNTIF(J9,"9.*")),D44+D47+D50,IF(OR(COUNTIF(J9,"7.*"),COUNTIF(J9,"8.*")),D44+D47+D50,"")))))))) -> 795.42 | E57: =IF(COUNTIF(E34,"Select*"),"",IF(COUNTIF(J9,"10.*"),IF(COUNTIF(E34,"3.*"),"AP 1 Delayed Calc 2 13th Check Benefit:",""),"AP 1 Awarded 13th Check Amount:"))
A58: =IF(COUNTIF(J9,"10.*"),"Delayed Calculation 2 Increase:","") | D58: =IF(COUNTIF(J9,"10.*"),M33,"")
A59: =IF(COUNTIF(A34,"_"),"",IF(COUNTIF(J9,"10.*"),"AP 1 Delayed Calc 2 Monthly Benefit:",IF(OR(COUNTIF(A34,"1.*"),COUNTIF(A34,"2.*"),COUNTIF(A34,"4.*")),"AP 1 Total Monthly Benefit:",""))) | D59: =IF(COUNTIF(A34,"_"),"",IF(OR(COUNTIF(A34,"1.*"),COUNTIF(A34,"2.*"),COUNTIF(A34,"4.*")),IF(OR(COUNTIF(J9,"1.*"),COUNTIF(J9,"6.*")),SUM(D46,D49,D52),IF(OR(COUNTIF(J9,"3.*"),COUNTIF(J9,"4.*"),COUNTIF(J9,"6.*")),SUM(D44,D49,D52),IF(OR(COUNTIF(J9,"7.*"),COUNTIF(J9,"8.*")),SUM(D44,D47,D52),IF(COUNTIF(J9,"10.*"),D56+(D56*D58),SUM(D44,D47,D50))))))) -> FALSE
A60: =IF(COUNTIF(A34,"_"),"",IF(COUNTIF(J9,"10.*"),"AP 1 Delayed Calc 2 13th Check Benefit:",IF(OR(COUNTIF(A34,"1.*"),COUNTIF(A34,"2.*"),COUNTIF(A34,"4.*")),"AP 1 13th Check:",""))) | D60: =IF(OR(COUNTIF(A34,"_"),COUNTIF(A34,"3.*")),"",IF(OR(COUNTIF(A34,"1.*"),COUNTIF(A34,"2.*"),COUNTIF(A34,"4.*")),IF(OR(COUNTIF(J9,"1.*"),COUNTIF(J9,"6.*")),SUM(D46,D49),IF(OR(COUNTIF(J9,"3.*"),COUNTIF(J9,"4.*"),COUNTIF(J9,"6.*")),SUM(D44,D49),IF(OR(COUNTIF(J9,"7.*"),COUNTIF(J9,"8.*")),SUM(D44,D47),IF(COUNTIF(J9,"10.*"),D57+(D57*D58),SUM(D44,D47))))))) | E60: =IF(COUNTIF(E34,"_"),"",IF(OR(COUNTIF(E34,"1.*"),COUNTIF(E34,"2.*"),COUNTIF(E34,"4.*")),"AP 2 Total Monthly Benefit:","")) | H60: =IF(COUNTIF(E34,"_"),"",IF(OR(COUNTIF(E34,"1.*"),COUNTIF(E34,"2.*"),COUNTIF(E34,"4.*")),IF(OR(COUNTIF(J9,"1.*"),COUNTIF(J9,"6.*")),SUM(H46,H49,H52),IF(OR(COUNTIF(J9,"3.*"),COUNTIF(J9,"4.*"),COUNTIF(J9,"6.*")),SUM(H44,H49,H52),IF(OR(COUNTIF(J9,"7.*"),COUNTIF(J9,"8.*")),SUM(H44,H47,H52),SUM(H44,H47,H50)))),""))
A61: =IF(COUNTIF(J9,"10.*"),"Greater of Calc 1 and 2:","") | C61: =IF(COUNTIF(J9,"10.*"),IF(C51>=D59,"Calculation 1",IF(D59>C51,"Calculation 2",""))) -> FALSE | D61: =IF(COUNTIF(J9,"10.*"),IF(C51>=D56,C51,IF(D56>C51,D56,""))) -> FALSE | E61: =IF(COUNTIF(E34,"_"),"",IF(OR(COUNTIF(E34,"1.*"),COUNTIF(E34,"2.*"),COUNTIF(E34,"4.*")),"AP 2 13th Check:","")) | H61: =IF(OR(COUNTIF(E34,"_"),COUNTIF(E34,"3.*")),"",IF(OR(COUNTIF(E34,"1.*"),COUNTIF(E34,"2.*"),COUNTIF(E34,"4.*")),IF(OR(COUNTIF(J9,"1.*"),COUNTIF(J9,"6.*")),SUM(H46,H49),IF(OR(COUNTIF(J9,"3.*"),COUNTIF(J9,"4.*"),COUNTIF(J9,"6.*")),SUM(H44,H49),IF(OR(COUNTIF(J9,"7.*"),COUNTIF(J9,"8.*")),SUM(H44,H47),SUM(H44,H47)))))) -> FALSE

Sheet QDRO Month Calc
A1: AP 1 QDRO Calculation Using Months | G1: AP 2 QDRO Calculation Using Months
A2: Totals: | B2: =SUM(B4:B69) -> 2 | C2: =SUM(C4:C69) -> 1 | E2: MEMBER ID: | G2: Totals: | H2: =SUM(H4:H69) -> 48 | I2: =SUM(I4:I69) -> 0 | K2: MEMBER ID: | L2: =F2 -> 0
A3: PLAN YEAR | B3: MONTHS WORKED | C3: MONTHS MARRIED | E3: MEMBER NAME: | G3: PLAN YEAR | H3: MONTHS WORKED | I3: MONTHS MARRIED | K3: MEMBER NAME: | L3: =F3 -> 0
A4: 2035 | B4: 0 | C4: 0 | E4: AP 1 NAME: | G4: 2035 | H4: 0 | I4: 0 | K4: AP 2 NAME:
A5: 2034 | B5: 0 | C5: 0 | E5: MARRIAGE DATES: | G5: 2034 | H5: 0 | I5: 0 | K5: MARRIAGE DATES:
A6: 2033 | B6: 0 | C6: 0 | E6: DATE OF MARRIAGE: | G6: 2033 | H6: 0 | I6: 0 | K6: DATE OF MARRIAGE:
A7: 2032 | B7: 0 | C7: 0 | E7: DATE OF SEPARATION: | G7: 2032 | H7: 0 | I7: 0 | K7: DATE OF SEPARATION:
A8: 2031 | B8: 0 | C8: 0 | G8: 2031 | H8: 0 | I8: 0
A9: 2030 | B9: 0 | C9: 0 | G9: 2030 | H9: 0 | I9: 0
A10: 2029 | B10: 0 | C10: 0 | G10: 2029 | H10: 0 | I10: 0
A11: 2028 | B11: 0 | C11: 0 | G11: 2028 | H11: 0 | I11: 0
A12: 2027 | B12: 0 | C12: 0 | G12: 2027 | H12: 0 | I12: 0
A13: 2026 | B13: 0 | C13: 0 | G13: 2026 | H13: 0 | I13: 0
A14: 2025 | B14: 0 | C14: 0 | G14: 2025 | H14: 0 | I14: 0
A15: 2024 | B15: 0 | C15: 0 | G15: 2024 | H15: 0 | I15: 0
A16: 2023 | B16: 0 | C16: 0 | G16: 2023 | H16: 0 | I16: 0
A17: 2022 | B17: 0 | C17: 0 | G17: 2022 | H17: 0 | I17: 0
A18: 2021 | B18: 0 | C18: 0 | G18: 2021 | H18: 0 | I18: 0
A19: 2020 | B19: 0 | C19: 0 | G19: 2020 | H19: 0 | I19: 0
... A69: 1970 | B69: 0 | C69: 0 | G69: 1970 | H69: 0 | I69: 0

Sheet Pro-Rata
A1: California Ironworkers Field Pension Trust Pro Rata Pension Calculation
A2: Member Name: | D2: Russell W. Nelson Jr. | I2: Member ID: | J2: 217296X00
A3: Member Date of Birth: | D3: 21088
A4: Member Age at Retirement: | D4: =DATEDIF(D3,D5,"y")&"/"&(DATEDIF(D3,D5, "m") - (DATEDIF(D3,D5, "y") * 12)) -> 66/4
A5: Member Retirement Date: | D5: 45323
A6: Spouse Name: | D6: Susan K. Nelson | H6: Spouse Age Difference from Member: | K6: =IF(D7=0,0,IF(AND(D3-D7<0,(DATEDIF(D3,D5,"m")-(DATEDIF(D3,D5,"y")*12))-(DATEDIF(D7,D5,"m")-(DATEDIF(D7,D5,"y")*12))=0),DATEDIF(D3,D5,"y")-DATEDIF(D7,D5,"y"),IF(AND(D3-D7>0,(DATEDIF(D7,D5,"m")-(DATEDIF(D7,D5,"y")*12))-(DATEDIF(D3,D5,"m")-(DATEDIF(D3,D5,"y")*12))=0),DATEDIF(D7,D5,"y")-DATEDIF(D3,D5,"y"),IF(D3-D7<0,ROUNDDOWN(YEARFRAC(D3,D7),0),IF(D3-D7>0,ROUNDDOWN(YEARFRAC(D7,D3),0),0))))) -> 3 | L6: =IF(D7=0,"N/A",IF(K6=0,"No Difference.",IF(D3-D7<0,"Year(s) Younger.", IF(D3-D7>0, "Year(s) Older.","No Difference.")))) -> Year(s) Older.
A7: Spouse Date of Birth: | D7: 19954
A8: Spouse Age at Retirement: | D8: =DATEDIF(D7,D5,"y")&"/"&(DATEDIF(D7,D5, "m") - (DATEDIF(D7,D5, "y") * 12)) -> 69/5
A9: Credits Earned Prior to 09/01/2011 | E9: Benefit Calculation | J9: Early H&W Pension Options
A10: PR Credits | B10: CA Credits | C10: Rate | D10: Value | E10: Total CIFPT Pension Credits: | I10: =B40 -> 44.38 | J10: Option | K10: Factor | L10: Member Benefit | M10: Spouse Benefit
D11: =(A11+B11)*C11 -> 0 | E11: Total Pro-Rata Credits: | I11: =SUM('Pro-Rata Worksheet'!J5) -> 11.65 | J11: 0.5 | K11: =IF(COUNTIF(L6,"*Younger*"),100%-8%-(K6*0.4%),IF(100%-8%+(K6*0.4%)>100%,100%,100%-8%+(K6*0.4%))) -> 0.932 | L11: =(I15+I18+I21)*K11 -> 19588.015 | M11: =L11*J11 -> 9794.0076
D12: =(A12+B12)*C12 -> 0 | E12: Pro-Rata Factor: | I12: =ROUNDDOWN(I10/I11,4) -> 3.8094 | J12: 13th Check | K12: =IF(COUNTIF(L6,"*Younger*"),100%-8%-(K6*0.4%),IF(100%-8%+(K6*0.4%)>100%,100%,100%-8%+(K6*0.4%))) -> 0.932 | L12: =(I15+I18)*K12 -> 13313.995 | M12: =L12*J11 -> 6656.9975
D13: =(A13+B13)*C13 -> 0 | E13: Pro-Rata Member Benefit Prior to 09/01/2011 | I13: =D18*I12 -> 12223.565 | J13: 0.75 | K13: =IF(COUNTIF(L6,"*Younger*"),100%-12%-(K6*0.4%),IF(100%-12%+(K6*0.4%)>100%,100%,100%-12%+(K6*0.4%))) -> 0.892 | L13: =(I15+I18+I21)*K13 -> 18747.328 | M13: =L13*J13 -> 14060.496
B14: =SUM('Pro-Rata Worksheet'!B65:B69) -> 0 | C14: 50 | D14: =(A14+B14)*C14 -> 0 | E14: ER Factor | I14: =IF(DATEDIF(D3,D5,"m")<=600,(DATEDIF(D3,D5,"m")-540)*0.1%+40%,IF(DATEDIF(D3,D5,"m")<=660,(DATEDIF(D3,D5,"m")-600)*0.2%+46%,IF((DATEDIF(D3,D5,"m")-660)*0.5%+58%>=100%,100%,(DATEDIF(D3,D5,"m")-660)*0.5%+58%))) -> 1 | J14: 13th Check | K14: =IF(COUNTIF(L6,"*Younger*"),100%-12%-(K6*0.4%),IF(100%-12%+(K6*0.4%)>100%,100%,100%-12%+(K6*0.4%))) -> 0.892 | L14: =(I15+I18)*K14 -> 12742.579 | M14: =L14*J13 -> 9556.9342
A15: {=SUM('Pro-Rata Worksheet'!I35:I64-'Pro-Rata Worksheet'!B35:B64)} -> 0 | B15: 23.03 | C15: 118 | D15: =(A15+B15)*C15 -> 2717.54 | E15: Pro-Rata ER Benefit Prior to 09/01/2011 | I15: =(I13*I14) -> 12223.565 | J15: 1 | K15: =IF(COUNTIF(L6,"*Younger*"),100%-15%-(K6*0.5%),IF(100%-15%+(K6*0.5%)>100%,100%,100%-15%+(K6*0.5%))) -> 0.865 | L15: =(I15+I18+I21)*K15 -> 18179.864 | M15: =L15*J15 -> 18179.864
C16: 105 | D16: =(A16+B16)*C16 -> 0 | E16: Pro-Rata Member Benefit on or After 09/01/2011 | I16: =D22*I12 -> 2061.8378 | J16: 13th Check | K16: =IF(COUNTIF(L6,"*Younger*"),100%-15%-(K6*0.5%),IF(100%-15%+(K6*0.5%)>100%,100%,100%-15%+(K6*0.5%))) -> 0.865 | L16: =(I15+I18)*K16 -> 12356.873 | M16: =L16*J15 -> 12356.873
A17: {=SUM('Pro-Rata Worksheet'!I31:I34-'Pro-Rata Worksheet'!B31:B34)} -> 0 | B17: 3.93 | C17: 125 | D17: =(A17+B17)*C17 -> 491.25 | E17: ER Factor | I17: =IF(DATEDIF(D3,D5,"m")<=600,(DATEDIF(D3,D5,"m")-540)*0.1%+22%,IF(DATEDIF(D3,D5,"m")<=660,(DATEDIF(D3,D5,"m")-600)*0.2%+28%,IF((DATEDIF(D3,D5,"m")-660)*0.5%+40%>=100%,100%,(DATEDIF(D3,D5,"m")-660)*0.5%+40%))) -> 1
A18: =SUM(A11:A17) -> 0 | B18: =SUM(B11:B17) -> 26.96 | C18: Subtotal | D18: =SUM(D11:D17) -> 3208.79 | E18: Pro-Rata ER Benefit on or After 09/01/2011 | I18: =I16*I17 -> 2061.8378 | J18: Disability H&W Pension Options
A19: Credits Earned On or After 09/01/2011 | E19: Pro-Rata Member Benefit on or After 10/01/2014 | I19: =SUM(D30+D39)*I12 -> 6731.7812 | J19: Option | K19: Factor | L19: Member Benefit | M19: Spouse Benefit
C20: 90 | D20: =(A20+B20)*C20 -> 0 | E20: ER Factor | I20: =IF(DATEDIF(D3,D5,"m")<=600,(DATEDIF(D3,D5,"m")-540)*0.1%+22%,IF(DATEDIF(D3,D5,"m")<=660,(DATEDIF(D3,D5,"m")-600)*0.2%+28%,IF((DATEDIF(D3,D5,"m")-660)*0.5%+40%>=100%,100%,(DATEDIF(D3,D5,"m")-660)*0.5%+40%))) -> 1 | J20: 0.5 | K20: =IF(COUNTIF(L6,"*Younger*"),100%-18%-(K6*0.4%),IF(100%-18%+(K6*0.4%)>100%,100%,100%-18%+(K6*0.4%))) -> 0.832 | L20: =(I13+I16+I19)*K20 -> 17486.297 | M20: =L20*J20 -> 8743.1484
B21: 4.33 | C21: 125 | D21: =(A21+B21)*C21 -> 541.25 | E21: Pro-Rata ER Benefit on or After 10/01/2014 | I21: =I19*I20 -> 6731.7812 | J21: 13th Check | K21: =IF(COUNTIF(L6,"*Younger*"),100%-18%-(K6*0.4%),IF(100%-18%+(K6*0.4%)>100%,100%,100%-18%+(K6*0.4%))) -> 0.832 | L21: =(I13+I16)*K21 -> 11885.455 | M21: =L21*J20 -> 5942.7274
A22: =SUM(A20:A21) -> 0 | B22: =SUM(B20:B21) -> 4.33 | C22: Subtotal | D22: =SUM(D20:D21) -> 541.25 | J22: 0.75 | K22: =IF(COUNTIF(L6,"*Younger*"),100%-24%-(K6*0.4%),IF(100%-24%+(K6*0.4%)>100%,100%,100%-24%+(K6*0.4%))) -> 0.772 | L22: =(I13+I16+I19)*K22 -> 16225.266 | M22: =L22*J22 -> 12168.949
A23: Credits Earned On or After 10/01/2014 | E23: Pro-Rata Regular, Service, Disability or Delayed Calc 1 Amount | I23: =SUM(I13,I16,I19) -> 21017.184 | J23: 13th Check | K23: =IF(COUNTIF(L6,"*Younger*"),100%-24%-(K6*0.4%),IF(100%-24%+(K6*0.4%)>100%,100%,100%-24%+(K6*0.4%))) -> 0.772 | L23: =(I13+I16)*K23 -> 11028.331 | M23: =L23*J22 -> 8271.248
A24: {=SUM('Pro-Rata Worksheet'!I6:I26-'Pro-Rata Worksheet'!B6:B26)} -> 0 | C24: 105 | D24: =(A24+B24)*C24 -> 0 | E24: Pro-Rata 13th Check | I24: =SUM(I13,I16) -> 14285.402 | J24: 1 | K24: =IF(COUNTIF(L6,"*Younger*"),100%-30%-(K6*0.5%),IF(100%-30%+(K6*0.5%)>100%,100%,100%-30%+(K6*0.5%))) -> 0.715 | L24: =(I13+I16+I19)*K24 -> 15027.286 | M24: =L24*J24 -> 15027.286
C25: 125 | D25: =(A25+B25)*C25 -> 0 | J25: 13th Check | K25: =IF(COUNTIF(L6,"*Younger*"),100%-30%-(K6*0.5%),IF(100%-30%+(K6*0.5%)>100%,100%,100%-30%+(K6*0.5%))) -> 0.715 | L25: =(I13+I16)*K24 -> 10214.063 | M25: =L25*J24 -> 10214.063
B26: 13.09 | C26: 135 | D26: =(A26+B26)*C26 -> 1767.15 | E26: Pro-Rata Early Retirement Pension Amount | I26: =SUM(I15,I18,I21) -> 21017.184
D27: =(A27+B27)*C27 -> 0 | E27: Pro-Rata Early 13th Check | I27: =SUM(I15,I18) -> 14285.402 | J27: Regular/Service/Delayed 1 H&W Pension Options
D28: =(A28+B28)*C28 -> 0 | J28: Option | K28: Factor | L28: Member Benefit | M28: Spouse Benefit
D29: =(A29+B29)*C29 -> 0 | J29: 0.5 | K29: =IF(COUNTIF(L6,"*Younger*"),100%-8%-(K6*0.4%),IF(100%-8%+(K6*0.4%)>100%,100%,100%-8%+(K6*0.4%))) -> 0.932 | L29: =(I13+I16+I19)*K29 -> 19588.015 | M29: =L29*J29 -> 9794.0076
A30: =SUM(A24:A29) -> 0 | B30: =SUM(B24:B29) -> 13.09 | C30: Subtotal | D30: =SUM(D24:D29) -> 1767.15 | J30: 13th Check | K30: =IF(COUNTIF(L6,"*Younger*"),100%-8%-(K6*0.4%),IF(100%-8%+(K6*0.4%)>100%,100%,100%-8%+(K6*0.4%))) -> 0.932 | L30: =(I13+I16)*K30 -> 13313.995 | M30: =L30*J29 -> 6656.9975
A31: =SUM(A18,A22,A30) -> 0 | B31: =SUM(B18,B22,B30) -> 44.38 | C31: Pre-65 Total | D31: =SUM(D18,D22,D30) -> 5517.19 | E31: First 60 months with 40 hours or less (1.00%): | I31: 16 | J31: 0.75 | K31: =IF(COUNTIF(L6,"*Younger*"),100%-12%-(K6*0.4%),IF(100%-12%+(K6*0.4%)>100%,100%,100%-12%+(K6*0.4%))) -> 0.892 | L31: =(I13+I16+I19)*K31 -> 18747.328 | M31: =L31*J31 -> 14060.496 | P31: .
A32: Credits Earned After Age 65 | E32: 61 + months with with 40 hours or less (1.50%): | I32: 0 | J32: 13th Check | K32: =IF(COUNTIF(L6,"*Younger*"),100%-12%-(K6*0.4%),IF(100%-12%+(K6*0.4%)>100%,100%,100%-12%+(K6*0.4%))) -> 0.892 | L32: =(I13+I16)*K32 -> 12742.579 | M32: =L32*J31 -> 9556.9342
C33: 105 | D33: =(A33+B33)*C33 -> 0 | E33: Delayed Calc 2 Retirement Increase: | I33: =SUM(I31*1%)+(I32*1.5%) -> 0.16 | J33: 1 | K33: =IF(COUNTIF(L6,"*Younger*"),100%-15%-(K6*0.5%),IF(100%-15%+(K6*0.5%)>100%,100%,100%-15%+(K6*0.5%))) -> 0.865 | L33: =(I13+I16+I19)*K33 -> 18179.864 | M33: =L33*J33 -> 18179.864
C34: 125 | D34: =(A34+B34)*C34 -> 0 | E34: Pro-Rata Delayed Benefit Increase | I34: =SUM(D31*I12)*I33 -> 3362.7494 | J34: 13th Check | K34: =IF(COUNTIF(L6,"*Younger*"),100%-15%-(K6*0.5%),IF(100%-15%+(K6*0.5%)>100%,100%,100%-15%+(K6*0.5%))) -> 0.865 | L34: =(I13+I16)*K34 -> 12356.873 | M34: =L34*J33 -> 12356.873
C35: 135 | D35: =(A35+B35)*C35 -> 0 | E35: Pro-Rata Delayed 13th Check Increase | I35: =SUM((D18+D22)*I12)*I33 -> 2285.6644
D36: =(A36+B36)*C36 -> 0 | E36: Pro-Rata Delayed Calc 2 Member Benefit: | I36: =SUM((D31*I12)+I34) -> 24379.933 | J36: Delayed 2 H&W Pension Options
D37: =(A37+B37)*C37 -> 0 | E37: Pro-Rata Delayed Calc 2 Member 13th Check: | I37: =SUM((D18+D22)*I12+I35) -> 16571.067 | J37: Option | K37: Factor | L37: Member Benefit | M37: Spouse Benefit
D38: =(A38+B38)*C38 -> 0 | J38: 0.5 | K38: =IF(COUNTIF(L6,"*Younger*"),100%-8%-(K6*0.4%),IF(100%-8%+(K6*0.4%)>100%,100%,100%-8%+(K6*0.4%))) -> 0.932 | L38: =I36*K38 -> 22722.098 | M38: =L38*J38 -> 11361.049
A39: =SUM(A33:A38) -> 0 | B39: =SUM(B33:B38) -> 0 | C39: Subtotal | D39: =SUM(D33:D38) -> 0 | E39: Delayed Calculation 1 Benefit Amount: | I39: =I23 -> 21017.184 | J39: 13th Check | K39: =IF(COUNTIF(L6,"*Younger*"),100%-8%-(K6*0.4%),IF(100%-8%+(K6*0.4%)>100%,100%,100%-8%+(K6*0.4%))) -> 0.932 | L39: =I37*K39 -> 15444.234 | M39: =L39*J38 -> 7722.1171
A40: =SUM(A18,A22,A30,A39) -> 0 | B40: =SUM(B18,B22,B30,B39) -> 44.38 | C40: Total | D40: =SUM(D18,D22,D30,D39) -> 5517.19 | E40: Delayed Calculation 2 Benefit Amount: | I40: =I36 -> 24379.933 | J40: 0.75 | K40: =IF(COUNTIF(L6,"*Younger*"),100%-12%-(K6*0.4%),IF(100%-12%+(K6*0.4%)>100%,100%,100%-12%+(K6*0.4%))) -> 0.892 | L40: =I36*K40 -> 21746.9 | M40: =L40*J40 -> 16310.175
E41: Greater of Calculation 1 and 2: | H41: =IF(I39=I40,"No Difference",IF(I39<I40,"Calculation 2","Calculation 1")) -> Calculation 2 | I41: =IF(I39=I40,I39,IF(I39<I40,I40,I39)) -> 24379.933 | J41: 13th Check | K41: =IF(COUNTIF(L6,"*Younger*"),100%-12%-(K6*0.4%),IF(100%-12%+(K6*0.4%)>100%,100%,100%-12%+(K6*0.4%))) -> 0.892 | L41: =I37*K41 -> 14781.392 | M41: =L41*J40 -> 11086.044
J42: 1 | K42: =IF(COUNTIF(L6,"*Younger*"),100%-15%-(K6*0.5%),IF(100%-15%+(K6*0.5%)>100%,100%,100%-15%+(K6*0.5%))) -> 0.865 | L42: =I36*K42 -> 21088.642 | M42: =L42*J42 -> 21088.642
A43: Processed By: | E43: Checked By: | J43: 13th Check | K43: =IF(COUNTIF(L6,"*Younger*"),100%-15%-(K6*0.5%),IF(100%-15%+(K6*0.5%)>100%,100%,100%-15%+(K6*0.5%))) -> 0.865 | L43: =I37*K43 -> 14333.973 | M43: =L43*J42 -> 14333.973

Sheet 4% Interest Calculator
A1: 4% Interest Calculator
A3: Pension 4% Interest run: | C3: =TODAY() -> 46164 | D3: =NOW() -> 46164.659
A4: Member Name: | B4: James Davis
A5: Member ID: | B5: 341317X00
A6: Payment Effective Date: | B6: 45809
A7: Begin Date: | B7: 45809
A8: End Date: | B8: 46143
A9: Payout Date: | B9: 46147
A10: Date | B10: Payment | C10: Months | D10: Interest | E10: Running Total
A11: =B7 -> 45809 | B11: 53.64 | C11: =DATEDIF(A11,B8,"m")+1 -> 12 | D11: =((0.04/12)*C11+1) -> 1.04 | E11: =(B11*(ROUND((0.04/12)*C11+1,8))) -> 55.7856
A12: =IF(OR(A11=B8,A11=""),"",EDATE(A11,1)) -> 45839 | B12: 53.64 | C12: =DATEDIF(A12,B8,"m")+1 -> 11 | D12: =((0.04/12)*C12+1) -> 1.0366667 | E12: =(B12*(ROUND((0.04/12)*C12+1,8))) -> 55.6068
A13: =IF(OR(A12=B8,A12=""),"",EDATE(A12,1)) -> 45870 | B13: 53.64 | C13: =DATEDIF(A13,B8,"m")+1 -> 10 | D13: =((0.04/12)*C13+1) -> 1.0333333 | E13: =(B13*(ROUND((0.04/12)*C13+1,8))) -> 55.428
A14: =IF(OR(A13=B8,A13=""),"",EDATE(A13,1)) -> 45901 | B14: 53.64 | C14: =DATEDIF(A14,B8,"m")+1 -> 9 | D14: =((0.04/12)*C14+1) -> 1.03 | E14: =(B14*(ROUND((0.04/12)*C14+1,8))) -> 55.2492
A15: =IF(OR(A14=B8,A14=""),"",EDATE(A14,1)) -> 45931 | B15: 53.64 | C15: =DATEDIF(A15,B8,"m")+1 -> 8 | D15: =((0.04/12)*C15+1) -> 1.0266667 | E15: =(B15*(ROUND((0.04/12)*C15+1,8))) -> 55.0704
A16: =IF(OR(A15=B8,A15=""),"",EDATE(A15,1)) -> 45962 | B16: 53.64 | C16: =DATEDIF(A16,B8,"m")+1 -> 7 | D16: =((0.04/12)*C16+1) -> 1.0233333 | E16: =(B16*(ROUND((0.04/12)*C16+1,8))) -> 54.8916
A17: =IF(OR(A16=B8,A16=""),"",EDATE(A16,1)) -> 45992 | B17: 53.64 | C17: =DATEDIF(A17,B8,"m")+1 -> 6 | D17: =((0.04/12)*C17+1) -> 1.02 | E17: =(B17*(ROUND((0.04/12)*C17+1,8))) -> 54.7128
A18: =IF(OR(A17=B8,A17=""),"",EDATE(A17,1)) -> 46023 | B18: 53.64 | C18: =DATEDIF(A18,B8,"m")+1 -> 5 | D18: =((0.04/12)*C18+1) -> 1.0166667 | E18: =(B18*(ROUND((0.04/12)*C18+1,8))) -> 54.534
A19: =IF(OR(A18=B8,A18=""),"",EDATE(A18,1)) -> 46054 | B19: 53.64 | C19: =DATEDIF(A19,B8,"m")+1 -> 4 | D19: =((0.04/12)*C19+1) -> 1.0133333 | E19: =(B19*(ROUND((0.04/12)*C19+1,8))) -> 54.3552
A20: =IF(OR(A19=B8,A19=""),"",EDATE(A19,1)) -> 46082 | B20: 53.64 | C20: =DATEDIF(A20,B8,"m")+1 -> 3 | D20: =((0.04/12)*C20+1) -> 1.01 | E20: =(B20*(ROUND((0.04/12)*C20+1,8))) -> 54.1764
A21: =IF(OR(A20=B8,A20=""),"",EDATE(A20,1)) -> 46113 | B21: 53.64 | C21: =DATEDIF(A21,B8,"m")+1 -> 2 | D21: =((0.04/12)*C21+1) -> 1.0066667 | E21: =(B21*(ROUND((0.04/12)*C21+1,8))) -> 53.9976
A22: =IF(OR(A21=B18,A21=""),"",EDATE(A21,1)) -> 46143 | B22: 53.64 | C22: =IF(A22="","",DATEDIF(A22,B8,"m")+1) -> 1 | D22: =((0.04/12)*C22+1) -> 1.0033333 | E22: =(B22*(ROUND((0.04/12)*C22+1,8))) -> 53.8188
A23: =IF(OR(A22=B8,A22=""),"",EDATE(A22,1)) | B23: 53.64 | C23: =IF(A23="","",DATEDIF(A23,B8,"m")+1) | D23: =((0.04/12)*C23+1) -> #VALUE! | E23: =(B23*(ROUND((0.04/12)*C23+1,8))) -> #VALUE!
A26: Total Payments: | B26: =SUM(B11:B23) -> 697.32
A27: Total w/Interest: | B27: =SUM(E11:E23) -> #VALUE!
A28: Interest: | B28: =B27-B26 -> #VALUE!

Sheet DCP Tax Calculator
B1: What member wants | C1: Early Withdraw | E1: What member should request | F1: ="What member will receive if they ask for $"&B4 -> What member will receive if they ask for $20000 | G1: ="What member will receive if they ask for $"&ROUND(E4,2) -> What member will receive if they ask for $25000
C2: =B4*0.1 -> 2000 | D2: Without
C3: Fed Taxes | D3: State Tax
B4: 20000 | C4: =B4*0.2 -> 4000 | E4: =SUM(B4+(B4*0.25)) -> 25000 | F4: =SUM(B4-(C4+D4)) -> 16000 | G4: =SUM(E4-(E4*0.2)) -> 20000
B6: What member wants | C6: Early Withdraw | E6: What member should request | F6: ="What member will receive if they ask for $"&B9 -> What member will receive if they ask for $20000 | G6: ="What member will receive if they ask for $"&ROUND(E9,2) -> What member will receive if they ask for $25642
C7: =B9*0.1 -> 2000 | D7: With
C8: Fed Taxes | D8: State Taxes
B9: =B4 -> 20000 | C9: =B9*0.2 -> 4000 | D9: =0.02*B9 -> 400 | E9: =SUM(B9+(B9*0.25)+(B9*0.0321)) -> 25642 | F9: =SUM(B9-(C9+D9)) -> 15600 | G9: =SUM(E9-((E9*0.2)+(E9*0.02))) -> 20000.76

Sheet DCP QDRO Calculation Sheet
A1: CALIFORNIA IRONWORKERS FIELD DEFINED CONTRIBUTION PENSION PLAN
A2: QDRO CALCULATION SHEET
A5: Member's Name: | C5: Steven Samler | G5: SSN: | H5: 568-77-0976
A7: QDRO REVIEWED BY LEGAL COUNSEL AND ACCEPTED ON: | H7: N/A
A14: Date of Marriage: | C14: 27378 | F14: Effective Date of QDRO:
F15: If date of separation occurs on or before 9/30/98, eff.
A16: Date of Separation: | C16: 30834 | F16: date of qdro must be 9/30/98, if separation occurs after
F17: this date, use separation date unless qdro advises
F18: otherwise.
A20: Balance on DOS: | E20: 2409.72
A21: Less funds earned prior to DOM: | E21: 422.5
A23: Total funds earned during marriage: | E23: =E20-E21 -> 1987.22
A24: AP Percentage Interest: | C24: 0.5 | E24: =SUM(E23*C24) -> 993.61
A26: YEAR: | B26: =IF(C16>36053,"",IF(AND(MONTH(C16)<"6",YEAR(C16)=1998),YEAR(C16),IF(MONTH(C16)<"5",YEAR(C16)+1,""))) -> 1985 | D26: %: | E26: =IF(B26=1981,0.055,IF(B26=1982,0.0845,IF(B26=1983,0.1017,IF(B26=1984,0.093807,IF(B26=1985,0.12604006,IF(B26=1986,0.08076508,IF(B26=1987,0.06066944,IF(B26=1988,0.06668109,IF(B26=1989,0.08438409,IF(B26=1990,0.08780206,IF(B26=1991,0.10655716,IF(B26=1992,0.1269022,IF(B26=1993,0.13044565,IF(B26=1994,0.0952,IF(B26=1995,0.07845,IF(B26=1996,0.04089,IF(B26=1997,0.06913,IF(B26=1998,0.0873744,"")))))))))))))))))) -> 0.12604006
E27: =SUM(E24*E26) -> 125.23466 | G27: FIGURES CALCULATED BY:
C28: New Total: | E28: =SUM(E24+E27) -> 1118.8447
A30: YEAR: | B30: =IF(B26>1997,"",B26+1) -> 1986 | D30: %: | E30: =IF(B30=1981,0.055,IF(B30=1982,0.0845,IF(B30=1983,0.1017,IF(B30=1984,0.093807,IF(B30=1985,0.12604006,IF(B30=1986,0.08076508,IF(B30=1987,0.06066944,IF(B30=1988,0.06668109,IF(B30=1989,0.08438409,IF(B30=1990,0.08780206,IF(B30=1991,0.10655716,IF(B30=1992,0.1269022,IF(B30=1993,0.13044565,IF(B30=1994,0.0952,IF(B30=1995,0.07845,IF(B30=1996,0.04089,IF(B30=1997,0.06913,IF(B30=1998,0.0873744,"")))))))))))))))))) -> 0.08076508
E31: =SUM(E28*E30) -> 90.363579 | G31: DATE: | H31: =TODAY() -> 46164
C32: New Total: | E32: =SUM(E28+E31) -> 1209.2082
G33: FIGURES CHECKED BY:
A34: YEAR: | B34: =IF(B30>1997,"",B30+1) -> 1987 | D34: %: | E34: =IF(B34=1981,0.055,IF(B34=1982,0.0845,IF(B34=1983,0.1017,IF(B34=1984,0.093807,IF(B34=1985,0.12604006,IF(B34=1986,0.08076508,IF(B34=1987,0.06066944,IF(B34=1988,0.06668109,IF(B34=1989,0.08438409,IF(B34=1990,0.08780206,IF(B34=1991,0.10655716,IF(B34=1992,0.1269022,IF(B34=1993,0.13044565,IF(B34=1994,0.0952,IF(B34=1995,0.07845,IF(B34=1996,0.04089,IF(B34=1997,0.06913,IF(B34=1998,0.0873744,"")))))))))))))))))) -> 0.06066944
E35: =SUM(E32*E34) -> 73.361987
C36: New Total: | E36: =SUM(E32+E35) -> 1282.5702
G37: DATE:
A38: YEAR: | B38: =IF(B34>1997,"",B34+1) -> 1988 | D38: %: | E38: =IF(B38=1981,0.055,IF(B38=1982,0.0845,IF(B38=1983,0.1017,IF(B38=1984,0.093807,IF(B38=1985,0.12604006,IF(B38=1986,0.08076508,IF(B38=1987,0.06066944,IF(B38=1988,0.06668109,IF(B38=1989,0.08438409,IF(B38=1990,0.08780206,IF(B38=1991,0.10655716,IF(B38=1992,0.1269022,IF(B38=1993,0.13044565,IF(B38=1994,0.0952,IF(B38=1995,0.07845,IF(B38=1996,0.04089,IF(B38=1997,0.06913,IF(B38=1998,0.0873744,"")))))))))))))))))) -> 0.06668109
E39: =SUM(E36*E38) -> 85.523181
C40: New Total: | E40: =SUM(E36+E39) -> 1368.0934
A42: YEAR: | B42: =IF(B38>1997,"",B38+1) -> 1989 | D42: %: | E42: =IF(B42=1981,0.055,IF(B42=1982,0.0845,IF(B42=1983,0.1017,IF(B42=1984,0.093807,IF(B42=1985,0.12604006,IF(B42=1986,0.08076508,IF(B42=1987,0.06066944,IF(B42=1988,0.06668109,IF(B42=1989,0.08438409,IF(B42=1990,0.08780206,IF(B42=1991,0.10655716,IF(B42=1992,0.1269022,IF(B42=1993,0.13044565,IF(B42=1994,0.0952,IF(B42=1995,0.07845,IF(B42=1996,0.04089,IF(B42=1997,0.06913,IF(B42=1998,0.0873744,"")))))))))))))))))) -> 0.08438409
E43: =SUM(E40*E42) -> 115.44532
C44: New Total: | E44: =SUM(E40+E43) -> 1483.5387
A46: YEAR: | B46: =IF(B42>1997,"",B42+1) -> 1990 | D46: %: | E46: =IF(B46=1981,0.055,IF(B46=1982,0.0845,IF(B46=1983,0.1017,IF(B46=1984,0.093807,IF(B46=1985,0.12604006,IF(B46=1986,0.08076508,IF(B46=1987,0.06066944,IF(B46=1988,0.06668109,IF(B46=1989,0.08438409,IF(B46=1990,0.08780206,IF(B46=1991,0.10655716,IF(B46=1992,0.1269022,IF(B46=1993,0.13044565,IF(B46=1994,0.0952,IF(B46=1995,0.07845,IF(B46=1996,0.04089,IF(B46=1997,0.06913,IF(B46=1998,0.0873744,"")))))))))))))))))) -> 0.08780206
E47: =SUM(E44*E46) -> 130.25776
C48: New Total: | E48: =SUM(E44+E47) -> 1613.7965
A50: YEAR: | B50: =IF(B46>1997,"",B46+1) -> 1991 | D50: %: | E50: =IF(B50=1981,0.055,IF(B50=1982,0.0845,IF(B50=1983,0.1017,IF(B50=1984,0.093807,IF(B50=1985,0.12604006,IF(B50=1986,0.08076508,IF(B50=1987,0.06066944,IF(B50=1988,0.06668109,IF(B50=1989,0.08438409,IF(B50=1990,0.08780206,IF(B50=1991,0.10655716,IF(B50=1992,0.1269022,IF(B50=1993,0.13044565,IF(B50=1994,0.0952,IF(B50=1995,0.07845,IF(B50=1996,0.04089,IF(B50=1997,0.06913,IF(B50=1998,0.0873744,"")))))))))))))))))) -> 0.10655716
E51: =SUM(E48*E50) -> 171.96157
C52: New Total: | E52: =SUM(E48+E51) -> 1785.7581
A54: YEAR: | B54: =IF(B50>1997,"",B50+1) -> 1992 | D54: %: | E54: =IF(B54=1981,0.055,IF(B54=1982,0.0845,IF(B54=1983,0.1017,IF(B54=1984,0.093807,IF(B54=1985,0.12604006,IF(B54=1986,0.08076508,IF(B54=1987,0.06066944,IF(B54=1988,0.06668109,IF(B54=1989,0.08438409,IF(B54=1990,0.08780206,IF(B54=1991,0.10655716,IF(B54=1992,0.1269022,IF(B54=1993,0.13044565,IF(B54=1994,0.0952,IF(B54=1995,0.07845,IF(B54=1996,0.04089,IF(B54=1997,0.06913,IF(B54=1998,0.0873744,"")))))))))))))))))) -> 0.1269022
E55: =SUM(E52*E54) -> 226.61663
C56: New Total: | E56: =SUM(E52+E55) -> 2012.3747
A58: YEAR: | B58: =IF(B54>1997,"",B54+1) -> 1993 | D58: %: | E58: =IF(B58=1981,0.055,IF(B58=1982,0.0845,IF(B58=1983,0.1017,IF(B58=1984,0.093807,IF(B58=1985,0.12604006,IF(B58=1986,0.08076508,IF(B58=1987,0.06066944,IF(B58=1988,0.06668109,IF(B58=1989,0.08438409,IF(B58=1990,0.08780206,IF(B58=1991,0.10655716,IF(B58=1992,0.1269022,IF(B58=1993,0.13044565,IF(B58=1994,0.0952,IF(B58=1995,0.07845,IF(B58=1996,0.04089,IF(B58=1997,0.06913,IF(B58=1998,0.0873744,"")))))))))))))))))) -> 0.13044565
E59: =SUM(E56*E58) -> 262.50552
C60: New Total: | E60: =SUM(E56+E59) -> 2274.8802
A62: YEAR: | B62: =IF(B58>1997,"",B58+1) -> 1994 | D62: %: | E62: =IF(B62=1981,0.055,IF(B62=1982,0.0845,IF(B62=1983,0.1017,IF(B62=1984,0.093807,IF(B62=1985,0.12604006,IF(B62=1986,0.08076508,IF(B62=1987,0.06066944,IF(B62=1988,0.06668109,IF(B62=1989,0.08438409,IF(B62=1990,0.08780206,IF(B62=1991,0.10655716,IF(B62=1992,0.1269022,IF(B62=1993,0.13044565,IF(B62=1994,0.0952,IF(B62=1995,0.07845,IF(B62=1996,0.04089,IF(B62=1997,0.06913,IF(B62=1998,0.0873744,"")))))))))))))))))) -> 0.0952
E63: =SUM(E60*E62) -> 216.5686
C64: New Total: | E64: =SUM(E60+E63) -> 2491.4488
A66: YEAR: | B66: =IF(B62>1997,"",B62+1) -> 1995 | D66: %: | E66: =IF(B66=1981,0.055,IF(B66=1982,0.0845,IF(B66=1983,0.1017,IF(B66=1984,0.093807,IF(B66=1985,0.12604006,IF(B66=1986,0.08076508,IF(B66=1987,0.06066944,IF(B66=1988,0.06668109,IF(B66=1989,0.08438409,IF(B66=1990,0.08780206,IF(B66=1991,0.10655716,IF(B66=1992,0.1269022,IF(B66=1993,0.13044565,IF(B66=1994,0.0952,IF(B66=1995,0.07845,IF(B66=1996,0.04089,IF(B66=1997,0.06913,IF(B66=1998,0.0873744,"")))))))))))))))))) -> 0.07845
E67: =SUM(E64*E66) -> 195.45416
C68: New Total: | E68: =SUM(E64+E67) -> 2686.903
A70: YEAR: | B70: =IF(B66>1997,"",B66+1) -> 1996 | D70: %: | E70: =IF(B70=1981,0.055,IF(B70=1982,0.0845,IF(B70=1983,0.1017,IF(B70=1984,0.093807,IF(B70=1985,0.12604006,IF(B70=1986,0.08076508,IF(B70=1987,0.06066944,IF(B70=1988,0.06668109,IF(B70=1989,0.08438409,IF(B70=1990,0.08780206,IF(B70=1991,0.10655716,IF(B70=1992,0.1269022,IF(B70=1993,0.13044565,IF(B70=1994,0.0952,IF(B70=1995,0.07845,IF(B70=1996,0.04089,IF(B70=1997,0.06913,IF(B70=1998,0.0873744,"")))))))))))))))))) -> 0.04089
E71: =SUM(E68*E70) -> 109.86746
C72: New Total: | E72: =SUM(E68+E71) -> 2796.7704
A74: YEAR: | B74: =IF(B70>1997,"",B70+1) -> 1997 | D74: %: | E74: =IF(B74=1981,0.055,IF(B74=1982,0.0845,IF(B74=1983,0.1017,IF(B74=1984,0.093807,IF(B74=1985,0.12604006,IF(B74=1986,0.08076508,IF(B74=1987,0.06066944,IF(B74=1988,0.06668109,IF(B74=1989,0.08438409,IF(B74=1990,0.08780206,IF(B74=1991,0.10655716,IF(B74=1992,0.1269022,IF(B74=1993,0.13044565,IF(B74=1994,0.0952,IF(B74=1995,0.07845,IF(B74=1996,0.04089,IF(B74=1997,0.06913,IF(B74=1998,0.0873744,"")))))))))))))))))) -> 0.06913
E75: =SUM(E72*E74) -> 193.34074
C76: New Total: | E76: =SUM(E72+E75) -> 2990.1112
A78: YEAR: | B78: =IF(B74>1997,"",B74+1) -> 1998 | D78: %: | E78: =IF(B78=1981,0.055,IF(B78=1982,0.0845,IF(B78=1983,0.1017,IF(B78=1984,0.093807,IF(B78=1985,0.12604006,IF(B78=1986,0.08076508,IF(B78=1987,0.06066944,IF(B78=1988,0.06668109,IF(B78=1989,0.08438409,IF(B78=1990,0.08780206,IF(B78=1991,0.10655716,IF(B78=1992,0.1269022,IF(B78=1993,0.13044565,IF(B78=1994,0.0952,IF(B78=1995,0.07845,IF(B78=1996,0.04089,IF(B78=1997,0.06913,IF(B78=1998,0.0873744,"")))))))))))))))))) -> 0.0873744
E79: =SUM(E76*E78) -> 261.25917
C80: New Total: | E80: =SUM(E76+E79) -> 3251.3703
A82: YEAR: | B82: =IF(B78>1997,"",B78+1) | D82: %: | E82: =IF(B82=1981,0.055,IF(B82=1982,0.0845,IF(B82=1983,0.1017,IF(B82=1984,0.093807,IF(B82=1985,0.12604006,IF(B82=1986,0.08076508,IF(B82=1987,0.06066944,IF(B82=1988,0.06668109,IF(B82=1989,0.08438409,IF(B82=1990,0.08780206,IF(B82=1991,0.10655716,IF(B82=1992,0.1269022,IF(B82=1993,0.13044565,IF(B82=1994,0.0952,IF(B82=1995,0.07845,IF(B82=1996,0.04089,IF(B82=1997,0.06913,IF(B82=1998,0.0873744,""))))))))))))))))))
E83: =SUM(E80*E82) -> #VALUE!
C84: New Total: | E84: =SUM(E80+E83) -> #VALUE!
A86: YEAR: | B86: =IF(B82>1997,"",B82+1) | D86: %: | E86: =IF(B86=1981,0.055,IF(B86=1982,0.0845,IF(B86=1983,0.1017,IF(B86=1984,0.093807,IF(B86=1985,0.12604006,IF(B86=1986,0.08076508,IF(B86=1987,0.06066944,IF(B86=1988,0.06668109,IF(B86=1989,0.08438409,IF(B86=1990,0.08780206,IF(B86=1991,0.10655716,IF(B86=1992,0.1269022,IF(B86=1993,0.13044565,IF(B86=1994,0.0952,IF(B86=1995,0.07845,IF(B86=1996,0.04089,IF(B86=1997,0.06913,IF(B86=1998,0.0873744,""))))))))))))))))))
E87: =SUM(E84*E86) -> #VALUE!
C88: New Total: | E88: =SUM(E84+E87) -> #VALUE!
A90: YEAR: | B90: =IF(B86>1997,"",B86+1) | D90: %: | E90: =IF(B90=1981,0.055,IF(B90=1982,0.0845,IF(B90=1983,0.1017,IF(B90=1984,0.093807,IF(B90=1985,0.12604006,IF(B90=1986,0.08076508,IF(B90=1987,0.06066944,IF(B90=1988,0.06668109,IF(B90=1989,0.08438409,IF(B90=1990,0.08780206,IF(B90=1991,0.10655716,IF(B90=1992,0.1269022,IF(B90=1993,0.13044565,IF(B90=1994,0.0952,IF(B90=1995,0.07845,IF(B90=1996,0.04089,IF(B90=1997,0.06913,IF(B90=1998,0.0873744,""))))))))))))))))))
E91: =SUM(E88*E90) -> #VALUE!
C92: New Total: | E92: =SUM(E88+E91) -> #VALUE!
A94: YEAR: | B94: =IF(B90>1997,"",B90+1) | D94: %: | E94: =IF(B94=1981,0.055,IF(B94=1982,0.0845,IF(B94=1983,0.1017,IF(B94=1984,0.093807,IF(B94=1985,0.12604006,IF(B94=1986,0.08076508,IF(B94=1987,0.06066944,IF(B94=1988,0.06668109,IF(B94=1989,0.08438409,IF(B94=1990,0.08780206,IF(B94=1991,0.10655716,IF(B94=1992,0.1269022,IF(B94=1993,0.13044565,IF(B94=1994,0.0952,IF(B94=1995,0.07845,IF(B94=1996,0.04089,IF(B94=1997,0.06913,IF(B94=1998,0.0873744,""))))))))))))))))))
E95: =SUM(E92*E94) -> #VALUE!
C96: New Total: | E96: =SUM(E92+E95) -> #VALUE!

Sheet Tabs to the right do not work
B1: What member Wants | E1: What member should request | F1: ="What member will receive if they ask for $"&B4 -> What member will receive if they ask for $18660.37 | G1: ="What member will receive if they ask for $"&E4 -> What member will receive if they ask for $23325.4625
C3: Fed Taxes
B4: 18660.37 | C4: =B4*0.2 -> 3732.074 | E4: =SUM(B4+(B4*0.25)) -> 23325.462 | F4: =SUM(B4-(C4+D4)) -> 14928.296 | G4: =SUM(E4-(E4*0.2)) -> 18660.37
B6: What member wants | E6: What member should request | F6: ="What member will receive if they ask for $"&B9 -> What member will receive if they ask for $1000 | G6: ="What member will receive if they ask for $"&E9 -> What member will receive if they ask for $1282.1
C8: Fed Taxes | D8: State Taxes
B9: 1000 | C9: =B9*0.2 -> 200 | D9: =0.02*B9 -> 20 | E9: =SUM(B9+(B9*0.25)+(B9*0.0321)) -> 1282.1 | F9: =SUM(B9-(C9+D9)) -> 780 | G9: =SUM(E9-((E9*0.2)+(E9*0.02))) -> 1000.038
E10: =SUM(E9-((E9*0.2)+(E9*0.02))) -> 1000.038

Sheet Mail Dashboard
A4: Form Dashboard
A5: Member Name: | F5: Member ID:
A6: Member Address: | F6: Member SSN:
A7: Member Age:
A8: Spouse Name:
A9: Spouse Age:
A10: AP or Ex Spouse Name(s):
A11: AP or Ex Spouse Age:
A12: Date: | B12: =TODAY() -> 46164
A13: Forms to complete
A14: DCP Checklist
A15: Pension elected at Retirement:
A16: Retirement or Eligibility Date: | B16: 46174

Sheet Overpayment
A1: ="OVERPAYMENT REDUCTION CALCULATION SHEET - "&B5*100&"% MAXIMUM DISTRIBUTION REDUCTION" -> OVERPAYMENT REDUCTION CALCULATION SHEET - 10% MAXIMUM DISTRIBUTION REDUCTION | I1: OVERPAYMENT REDUCTION CALCULATION SHEET - MONTHLY BREAKDOWN
J2: Monthly Reduction | K2: Months of Payments in Year | L2: =IF(G4="","","13th Check Reduction") -> 13th Check Reduction | M2: Total payment for year | N2: Total payments to date | O2: Total Months left
A3: Retiree: | B3: Louie Anaya | D3: Member ID: | E3: 301966X65 | F3: Monthly Benefit: | G3: 3108.91 | I3: Year
A4: Pension Eff. Date: | B4: 45931 | C4: Date Reductions Start: | E4: 46174 | F4: 13th Check: | G4: 3108.91 | I4: =""&YEAR(E4) -> 2026 | J4: =G22 -> 53.74 | K4: =""&13-MONTH(E4) -> 7 | L4: =IF(G4="","",G23) -> 53.74 | M4: =IF(G4="",J4*K4,(J4*K4)+G23) -> 429.92 | N4: =M4 -> 429.92 | O4: =IF(G4="",G26-K4,IF(K4>4,G28-K4-1)) -> 111
A5: % of Reduction: | B5: 0.1 | I5: =IF(O4>0,""&YEAR(E4)+1,"") -> 2027 | J5: =G22 -> 53.74 | K5: =IF(O4>11,12,O4) -> 12 | L5: =IF(G4="","",G23) -> 53.74 | M5: =IF(M4+(J5*K5)>G6,(J5*K5)-((M4+(J5*K5))-G6),IF(G4="",J5*K5,(J5*K5)+G23)) -> 698.62 | N5: =SUM(M4:M5) -> 1128.54 | O5: =IF(G4="",G26-K4-K5,IF(K5>11,G28-K4-K5-1)) -> 99
A6: 1) | B6: Determine the amount of the total overpayment; | E6: Total Overpayment Amount (TOA): | G6: 6986.5 | I6: =IF(O5>0,""&YEAR(E4)+2,"") -> 2028 | J6: =G22 -> 53.74 | K6: =IF(O5>11,12,O5) -> 12 | L6: =IF(G4="","",G23) -> 53.74 | M6: =IF(SUM(M4:M5)+(J6*K6)>G6,(J6*K6)-((SUM(M4:M5)+(J6*K6))-G6),IF(G4="",J6*K6,(J6*K6)+G23)) -> 698.62 | N6: =SUM(M4:M6) -> 1827.16 | O6: =G28-K4-K5-K6-1 -> 87
I7: =IF(O6>0,""&YEAR(E4)+3,"") -> 2029 | J7: =G22 -> 53.74 | K7: =IF(O6>11,12,O6) -> 12 | L7: =IF(G4="","",G23) -> 53.74 | M7: =IF(SUM(M4:M6)+(J7*K7)>G6,(J7*K7)-((SUM(M4:M6)+(J7*K7))-G6),IF(G4="",J7*K7,(J7*K7)+G23)) -> 698.62 | N7: =SUM(M4:M7) -> 2525.78 | O7: =G28-K4-K5-K6-K7-1 -> 75
A8: 2) | B8: ="The amount recouped each year cannot exceed "&B5*100&"% of the total overpayment amount." -> The amount recouped each year cannot exceed 10% of the total overpayment amount. | I8: =IF(O7>0,""&YEAR(E4)+4,"") -> 2030 | J8: =G22 -> 53.74 | K8: =IF(O7>11,12,O7) -> 12 | L8: =IF(G4="","",G23) -> 53.74 | M8: =IF(SUM(M4:M7)+(J8*K8)>G6,(J8*K8)-((SUM(M4:M7)+(J8*K8))-G6),IF(G4="",J8*K8,(J8*K8)+G23)) -> 698.62 | N8: =SUM(M4:M8) -> 3224.4 | O8: =G26-K4-K5-K6-K7-K8-1 -> 64
B9: ="Multiply the total overpayment by "&B5*100&"%, then divide that amount by the number of" -> Multiply the total overpayment by 10%, then divide that amount by the number of | I9: =IF(O8>0,""&YEAR(E4)+5,"") -> 2031 | J9: =G22 -> 53.74 | K9: =IF(O8>11,12,O8) -> 12 | L9: =IF(G4="","",G23) -> 53.74 | M9: =IF(SUM(M4:M8)+(J9*K9)>G6,(J9*K9)-((SUM(M4:M8)+(J9*K9))-G6),IF(G4="",J9*K9,(J9*K9)+G23)) -> 698.62 | N9: =SUM(M4:M9) -> 3923.02 | O9: =G26-K4-K5-K6-K7-K8-K9 -> 53
B10: benefit payment the participants or beneficiary receives each calendar year; | I10: =IF(O9>0,""&YEAR(E4)+6,"") -> 2032 | J10: =G22 -> 53.74 | K10: =IF(O9>11,12,O9) -> 12 | L10: =IF(G4="","",G23) -> 53.74 | M10: =IF(SUM(M4:M9)+(J10*K10)>G6,(J10*K10)-((SUM(M4:M9)+(J10*K10))-G6),IF(G4="",J10*K10,(J10*K10)+G23)) -> 698.62 | N10: =SUM(M4:M10) -> 4621.64 | O10: =G26-K4-K5-K6-K7-K8-K9-K10 -> 41
E11: =IF(G4="","TOA x "&B5*100&"% / 12 =","TOA x "&B5*100&"% / 13 =") -> TOA x 10% / 13 = | F11: Monthly Reduction: | G11: =IF(G4="",ROUND((G6*B5)/12,2),ROUND((G6*B5)/13,2)) -> 53.74 | I11: =IF(O10>0,""&YEAR(E4)+7,"") -> 2033 | J11: =G22 -> 53.74 | K11: =IF(O10>11,12,O10) -> 12 | L11: =IF(G4="","",G23) -> 53.74 | M11: =IF(SUM(M4:M10)+(J11*K11)>G6,(J11*K11)-((SUM(M4:M10)+(J11*K11))-G6),IF(G4="",J11*K11,(J11*K11)+G23)) -> 698.62 | N11: =SUM(M4:M11) -> 5320.26 | O11: =G26-K4-K5-K6-K7-K8-K9-K10-K11 -> 29
A12: 3) | B12: ="Future benefit payments cannot be reduced to below "&100-B5*100&"% of the correct monthly benefit" -> Future benefit payments cannot be reduced to below 90% of the correct monthly benefit | F12: =IF(G4="","","13th Check Reduction:") -> 13th Check Reduction: | G12: =IF(G4="","",ROUND((G6*B5)/13,2)) -> 53.74 | I12: =IF(O11>0,""&YEAR(E4)+8,"") -> 2034 | J12: =G22 -> 53.74 | K12: =IF(O11>11,12,O11) -> 12 | L12: =IF(G4="","",G23) -> 53.74 | M12: =IF(SUM(M4:M11)+(J12*K12)>G6,(J12*K12)-((SUM(M4:M11)+(J12*K12))-G6),IF(G4="",J12*K12,(J12*K12)+G23)) -> 698.62 | N12: =SUM(M4:M12) -> 6018.88 | O12: =G26-K4-K5-K6-K7-K8-K9-K10-K11-K12 -> 17
B13: amount. Multiply the participant or beneficiary's correct monthly benefit payment by | I13: =IF(O12>0,""&YEAR(E4)+9,"") -> 2035 | J13: =G22 -> 53.74 | K13: =IF(O12>11,12,O12) -> 12 | L13: =IF(G4="","",G23) -> 53.74 | M13: =IF(SUM(M4:M12)+(J13*K13)>G6,(J13*K13)-((SUM(M4:M12)+(J13*K13))-G6),IF(G4="",J13*K13,(J13*K13)+G23)) -> 698.62 | N13: =SUM(M4:M13) -> 6717.5 | O13: =G26-K4-K5-K6-K7-K8-K9-K10-K11-K12-K13 -> 5
B14: =B5*100&"%;" -> 10%; | D14: ="Correct Monthly Benefit Amount x "&B5*100&"% =" -> Correct Monthly Benefit Amount x 10% = | F14: Monthly Reduction: | G14: =ROUND(G3*B5,2) -> 310.89 | I14: =IF(O13>0,""&YEAR(E4)+10,"") -> 2036 | J14: =G22 -> 53.74 | K14: =IF(O13>11,12,O13) -> 5 | L14: =IF(G4="","",G23) -> 53.74 | M14: =IF(SUM(M4:M13)+(J14*K14)>G6,(J14*K14)-((SUM(M4:M13)+(J14*K14))-G6),IF(G4="",J14*K14,(J14*K14)+G23)) -> 322.44 | N14: =SUM(M4:M14) -> 7039.94 | O14: =G26-K4-K5-K6-K7-K8-K9-K10-K11-K12-K13-K14 -> 0
A15: 4) | B15: If the monthly amount in 2) is less than 3), deduct the amount in 2) from the participant | F15: =IF(G4="","","13th Check Reduction:") -> 13th Check Reduction: | G15: =IF(G4="","",ROUND(G4*B5,2)) -> 310.89 | I15: =IF(O14>0,""&YEAR(E4)+11,"") | J15: =G22 -> 53.74 | K15: =IF(O14>11,12,O14) -> 0 | L15: =IF(G4="","",G23) -> 53.74 | M15: =IF(SUM(M4:M14)+(J15*K15)>G6,(J15*K15)-((SUM(M4:M14)+(J15*K15))-G6),IF(G4="",J15*K15,(J15*K15)+G23)) -> -53.44 | N15: =SUM(M4:M15) -> 6986.5 | O15: =G26-K4-K5-K6-K7-K8-K9-K10-K11-K12-K13-K14-K15 -> 0
B16: or beneficiary's corrected monthly benefit amount; OR | E16: =G11 -> 53.74 | F16: Monthly Benefit: | G16: =IF(G11<G14,G3-G11,"-") -> 3055.17 | I16: =IF(O15>0,""&YEAR(E4)+12,"") | J16: =G22 -> 53.74 | K16: =IF(O15>11,12,O15) -> 0 | L16: =IF(G4="","",G23) -> 53.74 | M16: =IF(SUM(M4:M15)+(J16*K16)>G6,(J16*K16)-((SUM(M4:M15)+(J16*K16))-G6),IF(G4="",J16*K16,(J16*K16)+G23)) -> 53.74 | N16: =SUM(M4:M16) -> 7040.24 | O16: =G26-K4-K5-K6-K7-K8-K9-K10-K11-K12-K13-K14-K15-K16 -> 0
E17: Amount in 2) above | F17: =IF(G4="","","13th Check:") -> 13th Check: | G17: =IF(G4="","",IF(G11<G14,G4-G11,"-")) -> 3055.17 | I17: =IF(O16>0,""&YEAR(E4)+13,"") | J17: =G22 -> 53.74 | K17: =IF(O16>11,12,O16) -> 0 | L17: =IF(G4="","",G23) -> 53.74 | M17: =IF(SUM(M4:M16)+(J17*K17)>G6,(J17*K17)-((SUM(M4:M16)+(J17*K17))-G6),IF(G4="",J17*K17,(J17*K17)+G23)) -> -53.74 | N17: =SUM(M4:M17) -> 6986.5 | O17: =G26-K4-K5-K6-K7-K8-K9-K10-K11-K12-K13-K14-K15-K16-K17 -> 0
A18: 5) | B18: If the monthly amount in 2) is greater than 3), deduct the amount in 3) from participant | I18: =IF(O17>0,""&YEAR(E4)+14,"") | J18: =G22 -> 53.74 | K18: =IF(O17>11,12,O17-1) -> -1 | M18: =IF(SUM(M4:M17)+(J18*K18)>G6,(J18*K18)-((SUM(M4:M17)+(J18*K18))-G6),IF(G4="",J18*K18,(J18*K18)+L18)) -> -53.74 | N18: =SUM(M4:M18) -> 6932.76 | O18: =G26-K4-K5-K6-K7-K8-K9-K10-K11-K12-K13-K14-K15-K16-K17-K18-1 -> 0
B19: or beneficiary's corrected monthly benefit amount | E19: =G14 -> 310.89 | F19: Monthly Benefit: | G19: =IF(G11>G14,G3-G14,"-") -> - | I19: =IF(O18>0,""&YEAR(E4)+15,"") | J19: =G22 -> 53.74 | K19: =IF(O18>11,12,O18) -> 0 | M19: =IF(SUM(M4:M18)+(J19*K19)>G6,(J19*K19)-((SUM(M4:M18)+(J19*K19))-G6),J19*K19) -> 0 | N19: =SUM(M4:M19) -> 6932.76 | O19: =G26-K4-K5-K6-K7-K8-K9-K10-K11-K12-K13-K14-K15-K16-K17-K18-K19-2 -> -1
E20: =G15 -> 310.89 | F20: =IF(G4="","","13th Check:") -> 13th Check: | G20: =IF(G4="","",IF(G12>G15,G4-G15,"-")) -> - | I20: =IF(O19>0,""&YEAR(E4)+16,"") | J20: =G22 -> 53.74 | K20: =IF(O19>11,12,O19) -> -1 | M20: =IF(SUM(M4:M19)+(J20*K20)>G6,(J20*K20)-((SUM(M4:M19)+(J20*K20))-G6),J20*K20) -> -53.74 | N20: =SUM(M4:M20) -> 6879.02 | O20: =G26-K4-K5-K6-K7-K8-K9-K10-K11-K12-K13-K14-K15-K16-K17-K18-K19-K20-3 -> -1
A21: 6) | B21: Schedule the deduction amount until the overpayment is repaid. | E21: Amount in 3) above | I21: =IF(O20>0,""&YEAR(E4)+17,"") | J21: =G22 -> 53.74 | K21: =IF(O20>11,12,O20) -> -1 | M21: =IF(SUM(M4:M20)+(J21*K21)>G6,(J21*K21)-((SUM(M4:M20)+(J21*K21))-G6),J21*K21) -> -53.74 | N21: =SUM(M4:M21) -> 6825.28 | O21: =G26-K4-K5-K6-K7-K8-K9-K10-K11-K12-K13-K14-K15-K16-K17-K18-K19-K20-K21-4 -> -1
D22: Monthly Benefit Reduction (E16 or E19): | F22: =IF(E16>E19,"E19","E16") -> E16 | G22: =IF(E16>E19,E19,E16) -> 53.74 | I22: =IF(O21>0,""&YEAR(E4)+18,"") | J22: =G22 -> 53.74 | K22: =IF(O21>11,12,O21) -> -1 | M22: =IF(SUM(M4:M21)+(J22*K22)>G6,(J22*K22)-((SUM(M4:M21)+(J22*K22))-G6),J22*K22) -> -53.74 | N22: =SUM(M4:M22) -> 6771.54 | O22: =G26-K4-K5-K6-K7-K8-K9-K10-K11-K12-K13-K14-K15-K16-K17-K18-K19-K20-K21-K22-5 -> -1
D23: =IF(G4="","","13th Check Benefit Reduction (E16 or E19):") -> 13th Check Benefit Reduction (E16 or E19): | F23: =IF(G4="","",IF(E16>E19,"E19","E16")) -> E16 | G23: =IF(G4="","",IF(E16>E20,E20,E16)) -> 53.74 | I23: =IF(O22>0,""&YEAR(E4)+19,"") | J23: =IF(O22=0,"",G22) -> 53.74 | K23: =IF(O22>11,12,O22) -> -1 | N23: =SUM(M4:M23) -> 6771.54 | O23: =G26-K4-K5-K6-K7-K8-K9-K10-K11-K12-K13-K14-K15-K16-K17-K18-K19-K20-K21-K22-K23-6 -> -1
D24: Reduced Monthly Benefit Amount: | G24: =IF(E16<=E19,G16,G19) -> 3055.17 | I24: =IF(O23>0,""&YEAR(E4)+20,"") | J24: =IF(O23=0,"",G22) -> 53.74 | K24: =IF(O23>11,12,O23) -> -1 | N24: =SUM(M4:M24) -> 6771.54 | O24: =G26-K4-K5-K6-K7-K8-K9-K10-K11-K12-K13-K14-K15-K16-K17-K18-K19-K20-K21-K22-K23-K24-7 -> -1
D25: =IF(G4="","","Reduced 13th Check:") -> Reduced 13th Check: | G25: =IF(G4="","",IF(E16<=E19,G17,G20)) -> 3055.17
C26: Total Number of Months to Receive Reduced Monthly Benefit: | G26: =IF(G4="",ROUNDUP(G6/G22,0),IF(OR(MONTH(B4)<9,YEAR(B4)<YEAR(E4)),ROUNDUP((G6-(ROUNDDOWN((G6/G22)/13,0)*G23))/G22,0)-1,ROUNDUP((G6-((ROUNDDOWN((G6/G22)/13,0)-1)*G23))/G22,0))) -> 120
C28: Number of Months to Receive Full Benefit Reduction: | G28: =IF(G4="",ROUNDDOWN(G6/G22,0),IF(OR(MONTH(B4)<9,YEAR(B4)<YEAR(E4)),ROUNDDOWN(G6/G22,0)-ROUNDDOWN((ROUNDDOWN((G6/G22)/13,0)*G23)/G22,0)-1,ROUNDDOWN(G6/G22,0)-ROUNDDOWN(((ROUNDDOWN((G6/G22)/13,0)-1)*G23)/G22,0))) -> 119 | M28: =IF(G4="",EDATE(E4,G28-1),IF(OR(MONTH(B4)<9,YEAR(B4)<YEAR(E4)),EDATE(E4,(G28-1)-(ROUNDDOWN((G6/G22)/13,0))),EDATE(E4,(G28-1)-(ROUNDDOWN((G6/G22)/13,0)-1)))) -> 49461
C29: Number of months x Monthly Benefit Reduction: | G29: =IF(G4="",(G28*G22),IF(AND(MONTH(B4)<9,YEAR(B4)<=YEAR(E4)),(ROUNDDOWN((G6/G22)/13,0))*G23+(G28*G22)+G22,(((ROUNDDOWN((G6/G22)/13,0)))*G23)+(G28*G22)+G22)) -> 6986.2
B31: If the Final Month Remaining Overpayment is $0, the | E31: Final Mth Overpayment Reduction (G6-G29) | G31: =IF(G28=G26,G22,G6-G29) -> 0.3 | I31: Original Overpayment Amount: | L31: 6076
B32: overpayment is satisifed and no further reduction is | E32: If Final Month Remaining Overpayment is $0, the overpayment is satisfied and the | I32: Unreduced Pension Benefit: | L32: 108.5
B33: necessary; if not, pay the Next Months Benefit Amount | E33: monthly pension payment should be returned to the corrected, full monthly benefit amount | I33: Number of Retro Payments: | L33: 2
B34: one-time and then change the gross distribution amount to | E34: Date of Final Month | G34: =EDATE(E4,G28) -> 49796 | I34: Total Retro Pension Payments: | L34: =L32*L33 -> 217
B35: the Corrected Monthly Benefit Amount going forward. | E35: Final Reduction Month Benefit Amount : | G35: =IF(G28=G26,G22,SUM(G3-G31)) -> 3108.61 | I35: Overpayment Amount minus Retro: | L35: =L31-L34 -> 5859
E36: (show reduced benefit amount if necessary)
B38: Processed By: | F38: Date: | G38: =TODAY() -> 46164
B40: 1st Approval: | F40: Date:
B42: Final Approval: | F42: Date:

Sheet Re-Retirement
A1: CALIFORNIA IRONWORKERS FIELD PENSION TRUST CALCULATION WORKSHEET
A2: Member Name: | B2: Ricky G. Peters | G2: Member ID: | H2: 237895X00
A3: Retiree DOB: | B3: 21470 | C3: Age at Retirement: | D3: 66/11
A4: New Retirement Effective Date: | C4: 45931
A5: Spouse Name: | B5: Phyllis A. Peters
A6: Prev. Spouse DOB: | B6: 22191 | C6: Age at Retirement: | D6: 53/6 | F6: =IF(B6=0,"","Prev. Spouse Age Difference from Member:") -> Prev. Spouse Age Difference from Member: | I6: =IF(B6=0,"",IF(AND(B3-B6<0,(DATEDIF(B3,C4,"m")-(DATEDIF(B3,C4,"y")*12))-(DATEDIF(B6,C4,"m")-(DATEDIF(B6,C4,"y")*12))=0),DATEDIF(B3,C4,"y")-DATEDIF(B6,C4,"y"),IF(AND(B3-B6>0,(DATEDIF(B6,C4,"m")-(DATEDIF(B6,C4,"y")*12))-(DATEDIF(B3,C4,"m")-(DATEDIF(B3,C4,"y")*12))=0),DATEDIF(B6,C4,"y")-DATEDIF(B3,C4,"y"),IF(B3-B6<0,ROUNDDOWN(YEARFRAC(B3,B6),0),IF(B3-B6>0,ROUNDDOWN(YEARFRAC(B6,B3),0),0))))) -> 2 | J6: =IF(B6=0,"",IF(I6=0,"No Difference.",IF(B3-B6<0,"Year(s) Younger.", IF(B3-B6>0, "Year(s) Older.","No Difference.")))) -> Year(s) Younger.
B7: Phyllis A. Peters
A8: Currn.Spouse DOB: | B8: 22191 | C8: Age at Retirement: | D8: 64/11 | F8: =IF(B8=0,"","Currn. Spouse Age Difference from Member:") -> Currn. Spouse Age Difference from Member: | I8: =IF(B8=0,"",IF(AND(B3-B8<0,(DATEDIF(B3,C4,"m")-(DATEDIF(B3,C4,"y")*12))-(DATEDIF(B8,C4,"m")-(DATEDIF(B8,C4,"y")*12))=0),DATEDIF(B3,C4,"y")-DATEDIF(B8,C4,"y"),IF(AND(B3-B8>0,(DATEDIF(B8,C4,"m")-(DATEDIF(B8,C4,"y")*12))-(DATEDIF(B3,C4,"m")-(DATEDIF(B3,C4,"y")*12))=0),DATEDIF(B8,C4,"y")-DATEDIF(B3,C4,"y"),IF(B3-B8<0,ROUNDDOWN(YEARFRAC(B3,B8),0),IF(B3-B8>0,ROUNDDOWN(YEARFRAC(B8,B3),0),0))))) -> 2 | J8: =IF(B8=0,"",IF(I8=0,"No Difference.",IF(B3-B8<0,"Year(s) Younger.", IF(B3-B8>0, "Year(s) Older.","No Difference.")))) -> Year(s) Younger.
A9: Credits Earned Prior to 09/01/2011 | F9: Member Benefit Calculation | L9: Previous Retirement Reduction Calculation
A10: Old Credits | B10: New Credits | C10: Rate | D10: Value | I10: CIFPT Credits: | J10: 1.5 | L10: Gross Pens $ | M10: Months | N10: $ Received
D11: =SUM((A11+B11)*C11) -> 0 | I11: Pro-Rata Credits: | J11: 38.022 | L11: 77 | M11: 36 | N11: =SUM(L11*M11) -> 2772
D12: =SUM((A12+B12)*C12) -> 0 | F12: New Credits Prior to 09/01/2011 Prior to ER Reduction | I12: Pro-Rata Factor: | J12: =J10/J11 -> 0.039450844 | N12: =SUM(L12*M12) -> 0
D13: =SUM((A13+B13)*C13) -> 0 | F13: ER Factor based on current age | I13: xERF | J13: =IF(DATEDIF(B3,C4,"m")<=600,(DATEDIF(B3,C4,"m")-540)*0.1%+40%,IF(DATEDIF(B3,C4,"m")<=660,(DATEDIF(B3,C4,"m")-600)*0.2%+46%,IF((DATEDIF(B3,C4,"m")-660)*0.5%+58%>=100%,100%,(DATEDIF(B3,C4,"m")-660)*0.5%+58%))) -> 1 | N13: =SUM(L13*M13) -> 0
D14: =SUM((A14+B14)*C14) -> 0 | J14: =SUM(B11*C11,B12*C12,B13*C13,B14*C14,B15*C15,B16*C16,B17*C17,B18*C18,B19*C19,B20*C20,B21*C21,B22*C22,B23*C23,B24*C24,B25*C25) -> 0 | N14: =SUM(L14*M14) -> 0
A15: 0.5 | C15: 50 | D15: =SUM((A15+B15)*C15) -> 25 | F15: New Credits Only On or After 09/01/2011 Prior to ER Reduction | J15: =SUM(D34) -> 0 | N15: =SUM(L15*M15) -> 0
C16: 70 | D16: =SUM((A16+B16)*C16) -> 0 | F16: ER Factor based on current age | I16: xERF | J16: =IF(DATEDIF(B3,C4,"m")<=600,(DATEDIF(B3,C4,"m")-540)*0.1%+22%,IF(DATEDIF(B3,C4,"m")<=660,(DATEDIF(B3,C4,"m")-600)*0.2%+28%,IF((DATEDIF(B3,C4,"m")-660)*0.5%+40%>=100%,100%,(DATEDIF(B3,C4,"m")-660)*0.5%+40%))) -> 1 | N16: =SUM(L16*M16) -> 0
C17: 80 | D17: =SUM((A17+B17)*C17) -> 0 | J17: =SUM(J15*J16) -> 0 | L17: Gross Total of Pymts Recvd | N17: =SUM(N11:N16) -> 2772
C18: 82 | D18: =SUM((A18+B18)*C18) -> 0 | F18: New Credits Only on or After 10/01/2014 Prior to Reduction | J18: =SUM(D41) -> 0 | L18: Husband and Wife Pension Options
C19: 85 | D19: =SUM((A19+B19)*C19) -> 0 | F19: ER Factor based on current age | I19: xERF | J19: =IF(DATEDIF(B3,C4,"m")<=600,(DATEDIF(B3,C4,"m")-540)*0.1%+22%,IF(DATEDIF(B3,C4,"m")<=660,(DATEDIF(B3,C4,"m")-600)*0.2%+28%,IF((DATEDIF(B3,C4,"m")-660)*0.5%+40%>=100%,100%,(DATEDIF(B3,C4,"m")-660)*0.5%+40%))) -> 1 | L19: (use only % applicable to previous ER election )
C20: 90 | D20: =SUM((A20+B20)*C20) -> 0 | J20: =SUM(J18*J19) -> 0 | L20: Option | M20: Factor | N20: Benefit Amt
C21: 100 | D21: =SUM((A21+B21)*C21) -> 0 | F21: Prev Retirement Benefit Amount | H21: Pre 09/01/2011 unreduced | J21: =SUM(A11*C11,A12*C12,A13*C13,A14*C14,A15*C15,A16*C16,A17*C17,A18*C18,A19*C19,A20*C20,A21*C21,A22*C22,A23*C23,A24*C24,A25*C25)*J12 -> 146.07085 | L21: 1 | M21: 0.84 | N21: =J35*M21 -> 106.33242
A22: 3.33 | C22: 105 | D22: =SUM((A22+B22)*C22) -> 349.65 | F22: ER calcculation based on current | H22: Post 09/01/2011 unreduced | J22: =SUM(A31*C31,A32*C32)*J12 -> 8.2353637 | L22: Member 13th Ck | N22: =((J24+J25)-J32)*M21 -> 106.33242
C23: 115 | D23: =SUM((A23+B23)*C23) -> 0 | F23: age and date period original credits | H23: Post 10/01/2014 unreduced | J23: =SUM(A38*C38,A39*C39)*J12 -> 0 | L23: Spouse | M23: * | N23: =SUM(N21*L21) -> 106.33242
C24: 125 | D24: =SUM((A24+B24)*C24) -> 0 | F24: earned and paid on original ER | H24: xERF Pre 09/01/2011 | J24: =SUM(J21*J13) -> 146.07085 | L24: Spouse 13th Ck | M24: * | N24: =SUM(N22*L21) -> 106.33242
A25: 28.203 | C25: 118 | D25: =SUM((A25+B25)*C25) -> 3327.954 | I25: xERF Post 09/01/2011 | J25: =SUM(J22*J16) -> 8.2353637 | L25: Husband and Wife Pension Options
A26: Old Credits | B26: New Credits | D26: Total Value | I26: xERF Post 10/01/2014 | J26: =SUM(J23*J19) -> 0 | L26: (H&W Options on only new credits)
A27: =SUM(A12:A25) -> 32.033 | B27: =SUM(B12:B25) -> 0 | D27: =SUM(D12:D25) -> 3702.604 | F27: Re-calc of first retirement ONLY (no new credits & before 1% red or H&W) | J27: =SUM(J24+J25+J26) -> 154.30622 | L27: Option | M27: Factor | N27: Benefit Amt
F28: Previous Retirement Information | L28: 0.5 | M28: 0.912 | N28: =SUM(J38*M28) -> 0
A29: Credits Earned On or After 09/01/2011 | F29: Previous Pension Type | H29: ER PR 100% | L29: Member 13th Ck | N29: =SUM((J14+J17)*M28) -> 0
A30: Old Credits | B30: New Credits | C30: Rate | D30: Value | F30: Previous Pension Eff Date | H30: 41760 | L30: Spouse | M30: * | N30: =SUM(N28*50%) -> 0
A31: 1.67 | C31: 125 | D31: =SUM((A31+B31)*C31) -> 208.75 | F31: Total Gross Amt of Prev ER Pens Payments Paid to Member | J31: =SUM(N17) -> 2772 | L31: Spouse 13th Ck | M31: * | N31: =SUM(N29*0.5) -> 0
C32: 90 | D32: =SUM((A32+B32)*C32) -> 0 | F32: Amount Above x 1% Previous Early Retirement Penalty | J32: =SUM(J31*1%) -> 27.72 | L32: 0.75 | M32: 0.872 | N32: =SUM(J38*M32) -> 0
A33: Old Credits | B33: New Credits | D33: Total Value | F33: When Separating the old & new benefits; the 1% penalty reduction | L33: Member 13th Ck | N33: =SUM((J14+J17)*M32) -> 0
A34: =SUM(A31+A32) -> 1.67 | B34: =SUM(B31+B32) -> 0 | D34: =SUM(D32) -> 0 | F34: should always be taken from the total of the new benefit | L34: Spouse | M34: * | N34: =SUM(N32*75%) -> 0
F35: Recalculated Previous ER Benefit After 1% Penalty Reduction | J35: =SUM(J27-J32) -> 126.58622 | L35: Spouse 13th Ck | M35: * | N35: =SUM(N33*0.75) -> 0
A36: Credits Earned On or After 10/01/2014 | F36: Previous ER Benefit Amount (for reference only; amount of new | J36: 91.65 | L36: 1 | M36: 0.84 | N36: =SUM(J38*M36) -> 0
A37: Old Credits | B37: New Credits | C37: Rate | D37: Value | F37: benefit cannot be less than the original ER benefit received)** | J37: 91.65 | L37: Member 13th Ck | N37: =SUM((J14+J17)*M36) -> 0
C38: 135 | D38: =SUM((A38+B38)*C38) -> 0 | F38: New Benefit (Single Life new credits only; reference only) | J38: =SUM(J14+J17+J20) -> 0 | L38: Spouse | M38: * | N38: =SUM(N36) -> 0
C39: 105 | D39: =SUM((A39+B39)*C39) -> 0 | H39: 13th Ck Benefit to Member | J39: =SUM(J14+J17) -> 0 | L39: Spouse 13th Ck | M39: * | N39: =SUM(N37) -> 0
A40: Old Credits | B40: New Credits | D40: Total Value | F40: H&W Benefit (old credits) & 50% H&W (new credts) | J40: =SUM(J35+N28) -> 126.58622 | L40: * payable to the spouse if husband and wife
A41: =SUM(A38+A39) -> 0 | B41: =SUM(B38+B39) -> 0 | D41: =SUM(D38:D39) -> 0 | H41: 13th Ck Benefit to Member | J41: =SUM(((N22-J32)+N29)) -> 78.612423 | L41: benefit was elected on that benefit piece
F42: H&W Benefit (old credits) & 75% H&W (new credts) | J42: =SUM(J35+N32) -> 126.58622 | L42: This election cannot be changed or revoked.
H43: 13th Ck Benefit to Member | J43: =SUM((N22-J32)+N33) -> 78.612423 | L43: **benefit payable IF all new benefit amounts
F44: H&W Benefit (old credits) & 100% H&W (new credts) | J44: =SUM(J35+N36) -> 126.58622 | L44: are less than this previous retirement amount
H45: 13th Ck Benefit to Member | J45: =SUM((N22-J32)+N37) -> 78.612423
B47: CALIFORNIA IRONWORKERS FIELD PENSION TRUST CALCULATION WORKSHEET
B48: PREVIOUSLY ER RETIRED_ANY NEW PENSION TYPE_H&W ONLY ON OLD CREDITS
B50: Name: | J50: ID: | L50: Spouse Age
L51: Yrs Older
D52: RETIREE | G52: SPOUSE | I52: Spouse Age
C53: DOB: | F53: DOB: | I53: Yrs Younger | J53: or
C54: Age: | F54: Age: | L54: Previous Retirement Reduction Calculation
L55: Gross Pens $ | M55: Months | N55: $ Received
B56: Credits Earned Prior to 09/01/2011 | F56: Member Benefit Calculation | N56: =SUM(L56*M56) -> 0
B57: Credits | C57: Rate | D57: Value | F57: New Credits Only Prior to 09/01/2011 Prior to ER Reduction | J57: =SUM(D74) -> 0 | N57: =SUM(L57*M57) -> 0
F58: ER Factor based on current age | I58: xERF | N58: =SUM(L58*M58) -> 0
D59: =SUM(B59*C59) -> 0 | J59: =SUM(J57*J58) -> 0 | N59: =SUM(L59*M59) -> 0
D60: =SUM(B60*C60) -> 0 | F60: New Credits Only On or After 09/01/2011 Prior to ER Reduction | J60: =SUM(D81) -> 0 | N60: =SUM(L60*M60) -> 0
D61: =SUM(B61*C61) -> 0 | F61: ER Factor based on current age | I61: xERF | N61: =SUM(L61*M61) -> 0
D62: =SUM(B62*C62) -> 0 | J62: =SUM(J60*J61) -> 0 | L62: Gross Total of Pymts Recvd | N62: =SUM(N56:N61) -> 0
D63: =SUM(B63*C63) -> 0 | F63: New Credits Only on or After 10/01/2014 Prior to Reduction | J63: =SUM(D88) -> 0
C64: 70 | D64: =SUM(B64*C64) -> 0 | F64: ER Factor based on current age | I64: xERF | J64: =SUM(J61) -> 0 | L64: Husband and Wife Pension Options
C65: 80 | D65: =SUM(B65*C65) -> 0 | J65: =SUM(J63*J64) -> 0 | L65: ( H&W % option elected at previous retirement )
C66: 82 | D66: =SUM(B66*C66) -> 0 | F66: Prev Retirement Benefit Amt | H66: Pre 09/01/2011 unreduced | L66: Option | M66: Factor | N66: Benefit Amt
C67: 85 | D67: =SUM(B67*C67) -> 0 | F67: ER Factor based on current age | H67: Post 09/01/2011 unreduced | N67: =SUM(J72*M67) -> 0
C68: 90 | D68: =SUM(B68*C68) -> 0 | F68: and date period original credits | H68: Post 10/01/2014 unreduced | J68: 0 | L68: 13th Check Payable to Member | N68: =SUM((J69+J70)*M67) -> 0
C69: 100 | D69: =SUM(B69*C69) -> 0 | F69: earned (before / after 09/2011 | H69: xERF Pre 09/01/2011 | J69: =SUM(J66*J58) -> 0 | L69: *Spouse | N69: =SUM(N67*L67) -> 0
C70: 105 | D70: =SUM(B70*C70) -> 0 | I70: xERF Post 09/01/2011 | J70: =SUM(J67*J61) -> 0 | L70: *Spouse 13th Check | N70: =SUM(N68*L67) -> 0
C71: 115 | D71: =SUM(B71*C71) -> 0 | I71: xERF Post 10/01/2014 | J71: =SUM(J68*J64) -> 0
C72: 118 | D72: =SUM(B72*C72) -> 0 | F72: Re-calc of first retirement ONLY (no new credits & before 1% red or H&W) | J72: =SUM(J69+J70+J71) -> 0 | L72: * payable to the spouse if husband and wife
B73: Total Credits | D73: Total Value | L73: benefit was elected on that benefit piece
B74: =SUM(B59:B72) -> 0 | D74: =SUM(D59:D72) -> 0 | F74: Previous Retirement Information | L74: This election cannot be changed or revoked.
F75: Previous Pension Type | L75: **benefit payable IF all new benefit amounts
B76: Credits Earned On or After 09/01/2011 | F76: Previous Pension Eff Date | L76: are less than this previous retirement amount
B77: Credits | C77: Rate | D77: Value | F77: Total Gross Amt of Prev ER Pens Payments Paid to Member | J77: =SUM(N62) -> 0
F78: Amount Above x 1% Previous Early Retirement Penalty | J78: =SUM(J77*1%) -> 0
C79: 90 | D79: =SUM(B79*C79) -> 0 | F79: When Separating the old & new benefits; the 1% penalty reduction
B80: Total Credits | D80: Total Value | F80: should always be taken from the total of the new benefit
B81: =SUM(B78+B79) -> 0 | D81: =SUM(D79) -> 0 | F81: Recalculated Previous ER H&W Benefit After 1% Penalty Reduction | J81: =SUM(N67-J78) -> 0
F82: Previous ER Benefit Amount (for reference only; amount of new
B83: Credits Earned On or After 10/01/2014 | F83: benefit cannot be less than the original ER benefit received)
B84: Credits | C84: Rate | D84: Value
C85: 70 | D85: =SUM(B85*C85) -> 0 | F85: New Benefit Amount (Single Life; new credits only for reference) | J85: =SUM(J59+J62+J65) -> 0
C86: 105 | D86: =SUM(B86*C86) -> 0 | F86: New SL Benefit + | G86: =SUM(L67) -> 0 | H86: husband and wife (old credits only) | J86: =SUM(J85+(N67-J78)) -> 0
B87: Total Credits | D87: Total Value | F87: 13th Check Benefit Payable to Member | J87: =SUM(N68-J78)+(J59+J62) -> 0
B88: =SUM(B85+B86) -> 0 | D88: =SUM(D86+D85) -> 0
B92: CALIFORNIA IRONWORKERS FIELD PENSION TRUST CALCULATION WORKSHEET
B93: PREVIOUSLY ER RETIRED_REGULAR, SERVICE OR DISABILITY RETIREMENT_H&W ON ONLY NEW CREDITS | L93: 306498X00
B95: Name: | C95: Timothy M Jimenez | J95: ID: | M95: Spouse Age
B96: PENSION EFFECTIVE: | L96: OR | M96: Yrs Older
D97: RETIREE | G97: SPOUSE | J97: Spouse Age
C98: DOB: | D98: 24038 | F98: DOB: | G98: 24857 | J98: Yrs Younger
C99: Age: | D99: 59/1 | F99: Age: | G99: 56/10 | J99: 2.4 | L99: Previous Retirement Reduction Calculation
L100: Gross Pens $ | M100: Months | N100: $ Received
B101: Credits Earned Prior to 09/01/2011 | F101: Member Benefit Calculation | L101: 973 | M101: 23 | N101: =SUM(L101*M101) -> 22379
B102: Credits | C102: Rate | D102: Value | F102: New Credits Only Prior to 09/01/2011 Prior to ER Reduction | J102: =SUM(D119) -> 0 | N102: =SUM(L102*M102) -> 0
F103: ER Factor based on current age | I103: xERF | N103: =SUM(L103*M103) -> 0
D104: =SUM(B104*C104) -> 0 | J104: =SUM(J102*J103) -> 0 | N104: =SUM(L104*M104) -> 0
D105: =SUM(B105*C105) -> 0 | F105: New Credits Only On or After 09/01/2011 Prior to ER Reduction | J105: =SUM(D126) -> 150.3 | N105: =SUM(L105*M105) -> 0
D106: =SUM(B106*C106) -> 0 | F106: ER Factor based on current age | I106: xERF | J106: 0.645 | N106: =SUM(L106*M106) -> 0
...

Sheet Overpayments & Adjustments
J1: Member Name: | K1: Mario R. Ruelas | N1: Member ID: | O1: 320288X00
A2: Member/Payee Name: | B2: Aquilino C. Basa | C2: Member ID: | E2: 351870X00
A3: Difference Calculation between adjusted and corrected amounts | H3: Member's 13th Check | I3: 477.9
A4: Gross Payments | B4: Number of Months | C4: Adjusted Amount | D4: Difference | E4: Total difference | H4: # of 13th check years while suspended: | I4: 7 | J4: Suspended 2/1/2018 | K4: Member passed 7/24/2025
A5: 3425.32 | B5: 11 | C5: 3615.77 | D5: =C5-A5 -> 190.45 | E5: =(C5-A5)*B5 -> 2094.95 | F5: July 2025 to May 2026
A6: 2444.42 | B6: 1 | C6: 2634.86 | D6: =C6-A6 -> 190.44 | E6: =(C6-A6)*B6 -> 190.44 | F6: 2025 13th Check | H6: # of payments of previous benefit:
D7: =C7-A7 -> 0 | E7: =(C7-A7)*B7 -> 0 | H7: Total Amount owed to member: | I7: =I3*I4 -> 3345.3
E8: =SUM(E5:E7) -> 2285.39 | F8: Total Difference
A11: Monthly Federal Tax Withholding | B11: 145.93 | C11: =B11/A5 -> 0.042603319 | D11: =D5*C11 -> 8.1138021
A12: Monthly State Tax Withholding | B12: 30.53
A13: Gross Total Adjustment Owed | B13: =E8 -> 2285.39
A14: Total Federal Tax Withholding | B14: =B11*(SUM(B5:B8)) -> 1751.16
A15: Total State Tax Withholding | B15: =B12*SUM(B5:B8) -> 366.36
A16: Net Total Adjustment Owed | B16: =B13-B14-B15 -> 167.87
I17: Beatrice Ruelas
A18: Amount we should adjust to | B18: 794.5
A19: Difference between Adjustment and Monthly | B19: =B18-B7 -> 794.5
A20: Number of current payments received | B20: 5 | C20: October 2025 to January 2026
A21: Total Difference between Adjustment and Monthly | B21: =B19*B20 -> 3972.5
A22: Feburary 2026 payment | B22: 400.46
A23: Difference between Adjustment and October 2025 | B23: =B18-B22 -> 394.04
A24: Total Gross Difference | B24: =(B19*B20)+B23 -> 4366.54
A25: Federal Tax Monthly Withholding | B25: 30
A26: State Tax Monthly Withholding | B26: 5
A27: Total Net Difference | B27: =B24-((B25+B26)*(B20+1)) -> 4156.54

Sheet OldServiceEarlyDisability
A1: California Pension Calculation
A2: Member Name: | C2: Frank Rodriguez | H2: Member ID: | I2: 307213X00
A3: Member Date of Birth: | C3: 23531
A4: Member Age at Retirement: | C4: =DATEDIF(C3,C5,"y")&"/"&(DATEDIF(C3,C5, "m") - (DATEDIF(C3,C5, "y") * 12)) -> 61/7
A5: Member Retirement Date: | C5: 46054
A6: Spouse Name: | C6: Imelda Alvizo | G6: Spouse Age Difference from Member: | J6: =IF(C7=0,0,IF(AND(C3-C7<0,(DATEDIF(C3,C5,"m")-(DATEDIF(C3,C5,"y")*12))-(DATEDIF(C7,C5,"m")-(DATEDIF(C7,C5,"y")*12))=0),DATEDIF(C3,C5,"y")-DATEDIF(C7,C5,"y"),IF(AND(C3-C7>0,(DATEDIF(C7,C5,"m")-(DATEDIF(C7,C5,"y")*12))-(DATEDIF(C3,C5,"m")-(DATEDIF(C3,C5,"y")*12))=0),DATEDIF(C7,C5,"y")-DATEDIF(C3,C5,"y"),IF(C3-C7<0,ROUNDDOWN(YEARFRAC(C3,C7),0),IF(C3-C7>0,ROUNDDOWN(YEARFRAC(C7,C3),0),0))))) -> 9 | K6: =IF(C7=0,"N/A",IF(J6=0,"No Difference.",IF(C3-C7<0,"Year(s) Younger.", IF(C3-C7>0, "Year(s) Older.","No Difference.")))) -> Year(s) Younger.
A7: Spouse Date of Birth: | C7: 27099
A8: Spouse Age at Retirement: | C8: =DATEDIF(C7,C5,"y")&"/"&(DATEDIF(C7,C5, "m") - (DATEDIF(C7,C5, "y") * 12)) -> 51/10
A9: Credits Earned Prior to 09/01/2011 | D9: Benefit Calculation | I9: Early H&W Pension Options
A10: CA Credits | B10: Rate | C10: Value | D10: Total Pension Credits | H10: =SUM(A11:A17,A20:A21,A24:A29,A33:A38) -> 25.48 | I10: Option | J10: Factor | K10: Member Benefit | L10: Spouse Benefit
C11: =A11*B11 -> 0 | D11: Member Benefit Prior to 09/01/2011 | G11: =SUM(A11:A17) -> 14.4 | H11: =C18 -> 1663.58 | I11: 0.5 | J11: =IF(COUNTIF(K6,"*Younger*"),100%-8%-(J6*0.4%),IF(100%-8%+(J6*0.4%)>100%,100%,100%-8%+(J6*0.4%))) -> 0.884 | K11: =(H13+H16+H19)*J11 -> 2219.8288 | L11: =K11*I11 -> 1109.9144
C12: =A12*B12 -> 0 | D12: ER Factor | H12: =IF(DATEDIF(C3,C5,"m")<=600,(DATEDIF(C3,C5,"m")-540)*0.1%+40%,IF(DATEDIF(C3,C5,"m")<=660,(DATEDIF(C3,C5,"m")-600)*0.2%+46%,IF((DATEDIF(C3,C5,"m")-660)*0.5%+58%>=100%,100%,(DATEDIF(C3,C5,"m")-660)*0.5%+58%))) -> 0.975 | I12: 13th Check | J12: =IF(COUNTIF(K6,"*Younger*"),100%-8%-(J6*0.4%),IF(100%-8%+(J6*0.4%)>100%,100%,100%-8%+(J6*0.4%))) -> 0.884 | K12: =(H13+H16)*J12 -> 1623.5902 | L12: =K12*I11 -> 811.7951
C13: =A13*B13 -> 0 | D13: ER Benefit Prior to 09/01/2011 | H13: =(H11*H12) -> 1621.9905 | I13: 0.75 | J13: =IF(COUNTIF(K6,"*Younger*"),100%-12%-(J6*0.4%),IF(100%-12%+(J6*0.4%)>100%,100%,100%-12%+(J6*0.4%))) -> 0.844 | K13: =(H13+H16+H19)*J13 -> 2119.384 | L13: =K13*I13 -> 1589.538
B14: 50 | C14: =A14*B14 -> 0 | D14: Member Benefit on or After 09/01/2011 | G14: =SUM(A20:A21) -> 3 | H14: =C22 -> 270 | I14: 13th Check | J14: =IF(COUNTIF(K6,"*Younger*"),100%-12%-(J6*0.4%),IF(100%-12%+(J6*0.4%)>100%,100%,100%-12%+(J6*0.4%))) -> 0.844 | K14: =(H13+H16)*J14 -> 1550.1246 | L14: =K14*I13 -> 1162.5934
A15: 11.66 | B15: 118 | C15: =A15*B15 -> 1375.88 | D15: ER Factor | H15: =IF(DATEDIF(C3,C5,"m")<=600,(DATEDIF(C3,C5,"m")-540)*0.1%+22%,IF(DATEDIF(C3,C5,"m")<=660,(DATEDIF(C3,C5,"m")-600)*0.2%+28%,IF((DATEDIF(C3,C5,"m")-660)*0.5%+40%>=100%,100%,(DATEDIF(C3,C5,"m")-660)*0.5%+40%))) -> 0.795 | I15: 1 | J15: =IF(COUNTIF(K6,"*Younger*"),100%-15%-(J6*0.5%),IF(100%-15%+(J6*0.5%)>100%,100%,100%-15%+(J6*0.4%))) -> 0.805 | K15: =(H13+H16+H19)*J15 -> 2021.4504 | L15: =K15*I15 -> 2021.4504
A16: 2.74 | B16: 105 | C16: =A16*B16 -> 287.7 | D16: ER Benefit on or After 09/01/2011 | H16: =H14*H15 -> 214.65 | I16: 13th Check | J16: =IF(COUNTIF(K6,"*Younger*"),100%-15%-(J6*0.5%),IF(100%-15%+(J6*0.5%)>100%,100%,100%-15%+(J6*0.4%))) -> 0.805 | K16: =(H13+H16)*J16 -> 1478.4956 | L16: =K16*I15 -> 1478.4956
B17: 125 | C17: =A17*B17 -> 0 | D17: Member Benefit on or After 10/01/2014 | G17: {=SUM(A24:A29+A33:A38)} -> 8.08 | H17: =C30+C39 -> 848.4
A18: =SUM(A11:A17) -> 14.4 | B18: Subtotal | C18: =SUM(C11:C17) -> 1663.58 | D18: ER Factor | H18: =IF(DATEDIF(C3,C5,"m")<=600,(DATEDIF(C3,C5,"m")-540)*0.1%+22%,IF(DATEDIF(C3,C5,"m")<=660,(DATEDIF(C3,C5,"m")-600)*0.2%+28%,IF((DATEDIF(C3,C5,"m")-660)*0.5%+40%>=100%,100%,(DATEDIF(C3,C5,"m")-660)*0.5%+40%))) -> 0.795 | I18: Disability H&W Pension Options
A19: Credits Earned On or After 09/01/2011 | D19: ER Benefit on or After 10/01/2014 | H19: =H17*H18 -> 674.478 | I19: Option | J19: Factor | K19: Member Benefit | L19: Spouse Benefit
A20: 3 | B20: 90 | C20: =A20*B20 -> 270 | I20: 0.5 | J20: =IF(COUNTIF(K6,"*Younger*"),100%-18%-(J6*0.4%),IF(100%-18%+(J6*0.4%)>100%,100%,100%-18%+(J6*0.4%))) -> 0.784 | K20: =(H11+H14+H17)*J20 -> 2181.0723 | L20: =K20*I20 -> 1090.5362
B21: 125 | C21: =A21*B21 -> 0 | D21: Regular, Service, Disability or Delayed Calc 1 Amount | H21: =SUM(H11,H14,H17) -> 2781.98 | I21: 13th Check | J21: =IF(COUNTIF(K6,"*Younger*"),100%-18%-(J6*0.4%),IF(100%-18%+(J6*0.4%)>100%,100%,100%-18%+(J6*0.4%))) -> 0.784 | K21: =(H11+H14)*J21 -> 1515.9267 | L21: =K21*I20 -> 757.96336
A22: =SUM(A20:A21) -> 3 | B22: Subtotal | C22: =SUM(C20:C21) -> 270 | D22: 13th Check | H22: =SUM(H11,H14) -> 1933.58 | I22: 0.75 | J22: =IF(COUNTIF(K6,"*Younger*"),100%-24%-(J6*0.4%),IF(100%-24%+(J6*0.4%)>100%,100%,100%-24%+(J6*0.4%))) -> 0.724 | K22: =(H11+H14+H17)*J22 -> 2014.1535 | L22: =K22*I22 -> 1510.6151
A23: Credits Earned On or After 10/01/2014 | I23: 13th Check | J23: =IF(COUNTIF(K6,"*Younger*"),100%-24%-(J6*0.4%),IF(100%-24%+(J6*0.4%)>100%,100%,100%-24%+(J6*0.4%))) -> 0.724 | K23: =(H11+H14)*J23 -> 1399.9119 | L23: =K23*I22 -> 1049.9339
A24: 8.08 | B24: 105 | C24: =A24*B24 -> 848.4 | D24: Early Retirement Pension Amount | H24: =SUM(H13,H16,H19) -> 2511.1185 | I24: 1 | J24: =IF(COUNTIF(K6,"*Younger*"),100%-30%-(J6*0.5%),IF(100%-30%+(J6*0.5%)>100%,100%,100%-30%+(J6*0.4%))) -> 0.655 | K24: =(H11+H14+H17)*J24 -> 1822.1969 | L24: =K24*I24 -> 1822.1969
B25: 125 | C25: =A25*B25 -> 0 | D25: 13th Check | H25: =SUM(H13,H16) -> 1836.6405 | I25: 13th Check | J25: =IF(COUNTIF(K6,"*Younger*"),100%-30%-(J6*0.5%),IF(100%-30%+(J6*0.5%)>100%,100%,100%-30%+(J6*0.4%))) -> 0.655 | K25: =(H11+H14)*J24 -> 1266.4949 | L25: =K25*I24 -> 1266.4949
B26: 135 | C26: =A26*B26 -> 0
C27: =A27*B27 -> 0 | D27: Pre-65 Pension Amount | H27: =C31 -> 2781.98 | I27: Regular/Service/Delayed 1 H&W Pension Options
C28: =A28*B28 -> 0 | D28: Months between age 65 & 70 with 40 hours or less (1.00%): | H28: 0 | I28: Option | J28: Factor | K28: Member Benefit | L28: Spouse Benefit
C29: =A29*B29 -> 0 | D29: Months after age 70 with with hours or less (1.50%): | H29: 0 | I29: 0.5 | J29: =IF(COUNTIF(K6,"*Younger*"),100%-8%-(J6*0.4%),IF(100%-8%+(J6*0.4%)>100%,100%,100%-8%+(J6*0.4%))) -> 0.884 | K29: =(H11+H14+H17)*J29 -> 2459.2703 | L29: =K29*I29 -> 1229.6352
A30: =SUM(A24:A29) -> 8.08 | B30: Subtotal | C30: =SUM(C24:C29) -> 848.4 | D30: Delayed Calc 2 Retirement Increase: | H30: =SUM(H28*1%)+(H29*1.5%) -> 0 | I30: 13th Check | J30: =IF(COUNTIF(K6,"*Younger*"),100%-8%-(J6*0.4%),IF(100%-8%+(J6*0.4%)>100%,100%,100%-8%+(J6*0.4%))) -> 0.884 | K30: =(H11+H14)*J30 -> 1709.2847 | L30: =K30*I29 -> 854.64236
A31: =SUM(A18,A22,A30) -> 25.48 | B31: Pre-65 Total | C31: =SUM(C18,C22,C30) -> 2781.98 | D31: Delayed Benefit Increase | H31: =SUM(H11+H14+H17)*H30 -> 0 | I31: 0.75 | J31: =IF(COUNTIF(K6,"*Younger*"),100%-12%-(J6*0.4%),IF(100%-12%+(J6*0.4%)>100%,100%,100%-12%+(J6*0.4%))) -> 0.844 | K31: =(H11+H14+H17)*J31 -> 2347.9911 | L31: =K31*I31 -> 1760.9933
A32: Credits Earned After Age 65 | D32: Delayed 13th Check Increase | H32: =SUM(H11+H14)*H30 -> 0 | I32: 13th Check | J32: =IF(COUNTIF(K6,"*Younger*"),100%-12%-(J6*0.4%),IF(100%-12%+(J6*0.4%)>100%,100%,100%-12%+(J6*0.4%))) -> 0.844 | K32: =(H11+H14)*J32 -> 1631.9415 | L32: =K32*I31 -> 1223.9561
B33: 105 | C33: =(A33*B33) -> 0 | D33: Delayed Calc 2 Member Benefit: | H33: =SUM(C31+H31) -> 2781.98 | I33: 1 | J33: =IF(COUNTIF(K6,"*Younger*"),100%-15%-(J6*0.5%),IF(100%-15%+(J6*0.5%)>100%,100%,100%-15%+(J6*0.4%))) -> 0.805 | K33: =(H11+H14+H17)*J33 -> 2239.4939 | L33: =K33*I33 -> 2239.4939
B34: 125 | C34: =(A34*B34) -> 0 | D34: Delayed Calc 2 Member 13th Check: | H34: =SUM(C18+C22+H32) -> 1933.58 | I34: 13th Check | J34: =IF(COUNTIF(K6,"*Younger*"),100%-15%-(J6*0.5%),IF(100%-15%+(J6*0.5%)>100%,100%,100%-15%+(J6*0.4%))) -> 0.805 | K34: =(H11+H14)*J34 -> 1556.5319 | L34: =K34*I33 -> 1556.5319
B35: 135 | C35: =(A35*B35) -> 0
C36: =(A36*B36) -> 0 | D36: Delayed Calculation 1 Benefit Amount: | H36: =H21 -> 2781.98 | I36: Delayed 2 H&W Pension Options
C37: =(A37*B37) -> 0 | D37: Delayed Calculation 2 Benefit Amount: | H37: =H33 -> 2781.98 | I37: Option | J37: Factor | K37: Member Benefit | L37: Spouse Benefit
C38: =(A38*B38) -> 0 | D38: Greater of Calculation 1 and 2: | G38: =IF(H36=H37,"No Difference",IF(H36<H37,"Calculation 2","Calculation 1")) -> No Difference | H38: =IF(H36=H37,H36,IF(H36<H37,H37,H36)) -> 2781.98 | I38: 0.5 | J38: =IF(COUNTIF(K6,"*Younger*"),100%-8%-(J6*0.4%),IF(100%-8%+(J6*0.4%)>100%,100%,100%-8%+(J6*0.4%))) -> 0.884 | K38: =H33*J38 -> 2459.2703 | L38: =K38*I38 -> 1229.6352
A39: =SUM(A33:A38) -> 0 | B39: Subtotal | C39: =SUM(C33:C38) -> 0 | I39: 13th Check | J39: =IF(COUNTIF(K6,"*Younger*"),100%-8%-(J6*0.4%),IF(100%-8%+(J6*0.4%)>100%,100%,100%-8%+(J6*0.4%))) -> 0.884 | K39: =H34*J39 -> 1709.2847 | L39: =K39*I38 -> 854.64236
A40: =SUM(A18,A22,A30,A39) -> 25.48 | B40: Total | C40: =SUM(C18,C22,C30,C39) -> 2781.98 | I40: 0.75 | J40: =IF(COUNTIF(K6,"*Younger*"),100%-12%-(J6*0.4%),IF(100%-12%+(J6*0.4%)>100%,100%,100%-12%+(J6*0.4%))) -> 0.844 | K40: =H33*J40 -> 2347.9911 | L40: =K40*I40 -> 1760.9933
I41: 13th Check | J41: =IF(COUNTIF(K6,"*Younger*"),100%-12%-(J6*0.4%),IF(100%-12%+(J6*0.4%)>100%,100%,100%-12%+(J6*0.4%))) -> 0.844 | K41: =H34*J41 -> 1631.9415 | L41: =K41*I40 -> 1223.9561
I42: 1 | J42: =IF(COUNTIF(K6,"*Younger*"),100%-15%-(J6*0.5%),IF(100%-15%+(J6*0.5%)>100%,100%,100%-15%+(J6*0.4%))) -> 0.805 | K42: =H33*J42 -> 2239.4939 | L42: =K42*I42 -> 2239.4939
A43: Processed By: | E43: Checked By: | I43: 13th Check | J43: =IF(COUNTIF(K6,"*Younger*"),100%-15%-(J6*0.5%),IF(100%-15%+(J6*0.5%)>100%,100%,100%-15%+(J6*0.4%))) -> 0.805 | K43: =H34*J43 -> 1556.5319 | L43: =K43*I42 -> 1556.5319

Sheet QDRO Pension Calculator 6.017
A1: California Ironworkers Field Pension Trust Pension Calculation
A2: Member Name: | C2: Michael Sherritt | E2: Member ID: | F2: 275810X81 | K2: Processed By: | M2: Alex Miles
A3: Member Date of Birth: | C3: 23214
A4: Member Age at Retirement: | C4: =DATEDIF(C3,C5,"y")&"/"&(DATEDIF(C3,C5, "m") - (DATEDIF(C3,C5, "y") * 12)) -> 60/7 | K4: Date: | M4: =TODAY() -> 46164
A5: Member Retirement Date: | C5: 45352
A6: Spouse Name: | C6: Leyna P. Tran Sherritt | K6: Checked By:
A7: Spouse Date of Birth: | C7: 27877
A8: Spouse Age at Retirement: | C8: =IF(COUNTIF(C7,""),"",DATEDIF(C7,C5,"y")&"/"&(DATEDIF(C7,C5,"m")-(DATEDIF(C7,C5,"y")*12))) -> 47/10 | E8: =IF(C7=0,"","Spouse Age Difference from Member:") -> Spouse Age Difference from Member: | H8: =IF(C7=0,"",IF(AND(C3-C7<0,(DATEDIF(C3,C5,"m")-(DATEDIF(C3,C5,"y")*12))-(DATEDIF(C7,C5,"m")-(DATEDIF(C7,C5,"y")*12))=0),DATEDIF(C3,C5,"y")-DATEDIF(C7,C5,"y"),IF(AND(C3-C7>0,(DATEDIF(C7,C5,"m")-(DATEDIF(C7,C5,"y")*12))-(DATEDIF(C3,C5,"m")-(DATEDIF(C3,C5,"y")*12))=0),DATEDIF(C7,C5,"y")-DATEDIF(C3,C5,"y"),IF(C3-C7<0,ROUNDDOWN(YEARFRAC(C3,C7),0),IF(C3-C7>0,ROUNDDOWN(YEARFRAC(C7,C3),0),0))))) -> 12 | I8: =IF(C7=0,"",IF(H8=0,"No Difference.",IF(C3-C7<0,"Year(s) Younger.", IF(C3-C7>0, "Year(s) Older.","No Difference.")))) -> Year(s) Younger. | K8: Date:
A9: Credits Earned Prior to 09/01/2011 | J9: 1. Early Retirement Pension
A10: Member Credits | B10: =IF(COUNTIF(A32,"1.*"),"During AP 1 Marriage","") | C10: =IF(COUNTIF(A32,"1.*"),"AP 1 Credits","") | D10: =IF(COUNTIF(E32,"1.*"),"During AP 2 Marriage","") | E10: =IF(COUNTIF(E32,"1.*"),"AP 2 Credits","") | F10: Rate | G10: Member Value | H10: =IF(COUNTIF(A32,"1.*"),"AP 1 Value","") | I10: =IF(COUNTIF(E32,"1.*"),"AP 2 Value","") | J10: Benefit Calculation
C11: =IF(COUNTIF(A32,"1.*"),B11*D37,"") | E11: =IF(COUNTIF(E32,"1.*"),D11*H37,"") | G11: =IF(AND(COUNTIF(A32,"1.*"),COUNTIF(E32,"1.*")),SUM(A11*F11)-((C11*F11)+(E11*F11)),IF(COUNTIF(A32,"1.*"),SUM(A11*F11)-(C11*F11),IF(COUNTIF(E32,"1.*"),SUM(A11*F11)-(E11*F11),A11*F11))) -> 0 | H11: =IF(COUNTIF(A32,"1.*"),SUM(C11*F11),"") | I11: =IF(COUNTIF(E32,"1.*"),SUM(E11*F11),"") | J11: Full Benefit Prior to 09/01/2011: | M11: =SUM(A11:A17) -> 7.07 | N11: =SUM(A11*F11,A12*F12,A13*F13,A14*F14,A15*F15,A16*F16,A17*F17) -> 811.64
C12: =IF(COUNTIF(A32,"1.*"),B12*D37,"") | E12: =IF(COUNTIF(E32,"1.*"),D12*H37,"") | G12: =IF(AND(COUNTIF(A32,"1.*"),COUNTIF(E32,"1.*")),SUM(A12*F12)-((C12*F12)+(E12*F12)),IF(COUNTIF(A32,"1.*"),SUM(A12*F12)-(C12*F12),IF(COUNTIF(E32,"1.*"),SUM(A12*F12)-(E12*F12),A12*F12))) -> 0 | H12: =IF(COUNTIF(A32,"1.*"),SUM(C12*F12),"") | I12: =IF(COUNTIF(E32,"1.*"),SUM(E12*F12),"") | J12: =IF(COUNTIF(J9,"2.*"),"","Full Benefit from 09/01/2011 to 09/30/2014:") -> Full Benefit from 09/01/2011 to 09/30/2014: | M12: =IF(COUNTIF(J9,"2.*"),"",SUM(A20:A21)) -> 0.08 | N12: =IF(COUNTIF(J9,"2.*"),"",SUM(A20*F20,A21*F21)) -> 7.2
C13: =IF(COUNTIF(A32,"1.*"),B13*D37,"") | E13: =IF(COUNTIF(E32,"1.*"),D13*H37,"") | G13: =IF(AND(COUNTIF(A32,"1.*"),COUNTIF(E32,"1.*")),SUM(A13*F13)-((C13*F13)+(E13*F13)),IF(COUNTIF(A32,"1.*"),SUM(A13*F13)-(C13*F13),IF(COUNTIF(E32,"1.*"),SUM(A13*F13)-(E13*F13),A13*F13))) -> 0 | H13: =IF(COUNTIF(A32,"1.*"),SUM(C13*F13),"") | I13: =IF(COUNTIF(E32,"1.*"),SUM(E13*F13),"") | J13: =IF(COUNTIF(J9,"2.*"),"","Full Benefit on and After 10/01/2014:") -> Full Benefit on and After 10/01/2014: | M13: =IF(COUNTIF(J9,"2.*"),"",SUM(A24:A29)) -> 3.5 | N13: =IF(COUNTIF(J9,"2.*"),"",SUM(A24*F24,A25*F25,A26*F26,A27*F27,A28*F28,A29*F29)) -> 367.5
C14: =IF(COUNTIF(A32,"1.*"),B14*D37,"") | E14: =IF(COUNTIF(E32,"1.*"),D14*H37,"") | F14: 50 | G14: =IF(AND(COUNTIF(A32,"1.*"),COUNTIF(E32,"1.*")),SUM(A14*F14)-((C14*F14)+(E14*F14)),IF(COUNTIF(A32,"1.*"),SUM(A14*F14)-(C14*F14),IF(COUNTIF(E32,"1.*"),SUM(A14*F14)-(E14*F14),A14*F14))) -> 0 | H14: =IF(COUNTIF(A32,"1.*"),SUM(C14*F14),"") | I14: =IF(COUNTIF(E32,"1.*"),SUM(E14*F14),"") | J14: Total Pension Credits & Amount: | M14: =SUM(A11:A17,A20:A21,A24:A29) -> 10.65 | N14: =SUM(N11:N13) -> 1186.34
A15: =SUM('Pro-Rata Worksheet'!B35:B64) -> 5.33 | C15: =IF(COUNTIF(A32,"1.*"),B15*D37,"") | D15: 2.17 | E15: =IF(COUNTIF(E32,"1.*"),D15*H37,"") | F15: 118 | G15: =IF(AND(COUNTIF(A32,"1.*"),COUNTIF(E32,"1.*")),SUM(A15*F15)-((C15*F15)+(E15*F15)),IF(COUNTIF(A32,"1.*"),SUM(A15*F15)-(C15*F15),IF(COUNTIF(E32,"1.*"),SUM(A15*F15)-(E15*F15),A15*F15))) -> 628.94 | H15: =IF(COUNTIF(A32,"1.*"),SUM(C15*F15),"") | I15: =IF(COUNTIF(E32,"1.*"),SUM(E15*F15),"")
A16: =SUM('Pro-Rata Worksheet'!B31:B34) -> 1.74 | C16: =IF(COUNTIF(A32,"1.*"),B16*D37,"") | E16: =IF(COUNTIF(E32,"1.*"),D16*H37,"") | F16: 105 | G16: =IF(AND(COUNTIF(A33,"1.*"),COUNTIF(E33,"1.*")),SUM(A16*F16)-((C16*F16)+(E16*F16)),IF(COUNTIF(A33,"1.*"),SUM(A16*F16)-(C16*F16),IF(COUNTIF(E33,"1.*"),SUM(A16*F16)-(E16*F16),A16*F16))) -> 182.7 | H16: =IF(COUNTIF(A32,"1.*"),SUM(C16*F16),"") | I16: =IF(COUNTIF(E32,"1.*"),SUM(E16*F16),"") | J16: =IF(COUNTIF(A32,"_"),"","Alternate Payee 1 Award:") | N16: =IF(COUNTIF(A32,"_"),"",IF(COUNTIF(A32,"1.*"),ROUND(H18+H22+H30,2),IF(COUNTIF(A32,"3.*"),D38,IF(OR(COUNTIF(A32,"2.*"),COUNTIF(A32,"4.*")),IF(COUNTIF(J9,"2.*"),D41,ROUND((D41+D44+D47),2))))))
C17: =IF(COUNTIF(A32,"1.*"),B17*D37,"") | E17: =IF(COUNTIF(E32,"1.*"),D17*H37,"") | F17: 125 | G17: =IF(AND(COUNTIF(A34,"1.*"),COUNTIF(E34,"1.*")),SUM(A17*F17)-((C17*F17)+(E17*F17)),IF(COUNTIF(A34,"1.*"),SUM(A17*F17)-(C17*F17),IF(COUNTIF(E34,"1.*"),SUM(A17*F17)-(E17*F17),A17*F17))) -> 0 | H17: =IF(COUNTIF(A32,"1.*"),SUM(C17*F17),"") | I17: =IF(COUNTIF(E32,"1.*"),SUM(E17*F17),"") | J17: =IF(COUNTIF(A32,"_"),"","Alternate Payee 1 13th Check:") | N17: =IF(COUNTIF(A32,"_"),"",IF(COUNTIF(A32,"1.*"),ROUND(H18+H22,2),IF(COUNTIF(A32,"3.*"),D39,IF(OR(COUNTIF(A32,"2.*"),COUNTIF(A32,"4.*")),IF(COUNTIF(J9,"2.*"),D41,ROUND((D41+D44),2))))))
A18: =SUM(A11:A17) -> 7.07 | B18: =IF(COUNTIF(A32,"1.*"),SUM(B11:B17),"") | C18: =IF(COUNTIF(A32,"1.*"),SUM(C11:C17),"") | D18: =IF(COUNTIF(E32,"1.*"),SUM(D11:D17),"") | E18: =IF(COUNTIF(E32,"1.*"),SUM(E11:E17),"") | F18: Subtotal | G18: =SUM(G11:G17) -> 811.64 | H18: =IF(COUNTIF(A32,"1.*"),SUM(H11:H17),"") | I18: =IF(COUNTIF(E32,"1.*"),SUM(I11:I17),"") | J18: =IF(COUNTIF(E32,"_"),"","Alternate Payee 2 Award:") | N18: =IF(COUNTIF(E32,"_"),"",IF(COUNTIF(E32,"1.*"),ROUND(I18+I22+I30,2),IF(COUNTIF(E32,"3.*"),H38,IF(OR(COUNTIF(E32,"2.*"),COUNTIF(E32,"4.*")),IF(COUNTIF(J9,"2.*"),H41,ROUND((H41+H44+H47),2))))))
A19: Credits Earned On or After 09/01/2011 | J19: =IF(COUNTIF(E32,"_"),"","Alternate Payee 2 13th Check:") | N19: =IF(COUNTIF(E32,"_"),"",IF(COUNTIF(E32,"1.*"),ROUND(I18+I22,2),IF(COUNTIF(E32,"3.*"),H39,IF(OR(COUNTIF(E32,"2.*"),COUNTIF(E32,"4.*")),ROUND((H41+H44),2)))))
A20: =SUM('Pro-Rata Worksheet'!B27:B30) -> 0.08 | C20: =IF(COUNTIF(A32,"1.*"),B20*D37,"") | E20: =IF(COUNTIF(E32,"1.*"),D20*H37,"") | F20: 90 | G20: =IF(AND(COUNTIF(A32,"1.*"),COUNTIF(E32,"1.*")),SUM(A20*F20)-((C20*F20)+(E20*F20)),IF(COUNTIF(A32,"1.*"),SUM(A20*F20)-(C20*F20),IF(COUNTIF(E32,"1.*"),SUM(A20*F20)-(E20*F20),A20*F20))) -> 7.2 | H20: =IF(COUNTIF(A32,"1.*"),SUM(C20*F20),"") | I20: =IF(COUNTIF(E32,"1.*"),SUM(E20*F20),"")
C21: =IF(COUNTIF(A32,"1.*"),B21*D37,"") | E21: =IF(COUNTIF(E32,"1.*"),D21*H37,"") | F21: 125 | G21: =IF(AND(COUNTIF(A32,"1.*"),COUNTIF(E32,"1.*")),SUM(A21*F21)-((C21*F21)+(E21*F21)),IF(COUNTIF(A32,"1.*"),SUM(A21*F21)-(C21*F21),IF(COUNTIF(E32,"1.*"),SUM(A21*F21)-(E21*F21),A21*F21))) -> 0 | H21: =IF(COUNTIF(A32,"1.*"),SUM(C21*F21),"") | I21: =IF(COUNTIF(E32,"1.*"),SUM(E21*F21),"") | J21: Member Benefit Prior to 09/01/2011: | M21: =SUM(A11:A17) -> 7.07 | N21: =IF(AND(COUNTIF(A32,"1.*"),COUNTIF(E32,"1.*")),N11-(H18+I18),IF(AND(COUNTIF(A32,"1.*"),COUNTIF(E32,"2.*")),N11-(H18+(N11*H40)),IF(AND(COUNTIF(A32,"1.*"),COUNTIF(E32,"3.*")),N11-H18,IF(AND(COUNTIF(A32,"1.*"),COUNTIF(E32,"4.*")),N11-(H18+(N11*H40)),IF(AND(COUNTIF(A32,"2.*"),COUNTIF(E32,"1.*")),N11-((N11*D40)+I18),IF(AND(COUNTIF(A32,"2.*"),COUNTIF(E32,"2.*")),N11-((N11*D40)+(N11*H40)),IF(AND(COUNTIF(A32,"2.*"),COUNTIF(E32,"3.*")),N11-(N11*D40),IF(AND(COUNTIF(A32,"2.*"),COUNTIF(E32,"4.*")),N11-((N11*D40)+(N11*H40)),IF(AND(COUNTIF(A32,"3.*"),COUNTIF(E32,"1.*")),N11-I18,IF(AND(COUNTIF(A32,"3.*"),COUNTIF(E32,"2.*")),N11-(N11*H40),IF(AND(COUNTIF(A32,"3.*"),COUNTIF(E32,"3.*")),N11,IF(AND(COUNTIF(A32,"3.*"),COUNTIF(E32,"4.*")),N11-(N11*H40),IF(AND(COUNTIF(A32,"4.*"),COUNTIF(E32,"1.*")),N11-((N11*D40)+I18),IF(AND(COUNTIF(A32,"4.*"),COUNTIF(E32,"2.*")),N11-((N11*D40)+(N11*H40)),IF(AND(COUNTIF(A32,"4.*"),COUNTIF(E32,"3.*")),N11-(N11*D40),IF(AND(COUNTIF(A32,"4.*"),COUNTIF(E32,"4.*")),N11-((N11*D40)+(N11*H40)),IF(COUNTIF(A32,"1.*"),N11-H18,IF(OR(COUNTIF(A32,"2.*"),COUNTIF(A32,"4.*")),N11-(N11*D40),IF(COUNTIF(E32,"1.*"),N11-I18,IF(OR(COUNTIF(E32,"2.*"),COUNTIF(E32,"4.*")),N11-(N11*H40),SUM(A11*F11,A12*F12,A13*F13,A14*F14,A15*F15,A16*F16,A17*F17))))))))))))))))))))) -> 811.64
A22: =SUM(A20:A21) -> 0.08 | B22: =IF(COUNTIF(A32,"1.*"),SUM(B20:B21),"") | C22: =IF(COUNTIF(A32,"1.*"),SUM(C20:C21),"") | D22: =IF(COUNTIF(E32,"1.*"),SUM(D20:D21),"") | E22: =IF(COUNTIF(E32,"1.*"),SUM(E20:E21),"") | F22: Subtotal | G22: =SUM(G20:G21) -> 7.2 | H22: =IF(COUNTIF(A32,"1.*"),SUM(H20:H21),"") | I22: =IF(COUNTIF(E32,"1.*"),SUM(I20:I21),"") | J22: =IF(COUNTIF(J9,"1.*"),"ER Factor","") -> ER Factor | N22: =IF(COUNTIF(J9,"1.*"),IF(DATEDIF(C3,C5,"m")<=600,(DATEDIF(C3,C5,"m")-540)*0.1%+40%,IF(DATEDIF(C3,C5,"m")<=660,(DATEDIF(C3,C5,"m")-600)*0.2%+46%,IF((DATEDIF(C3,C5,"m")-660)*0.5%+58%>=100%,100%,(DATEDIF(C3,C5,"m")-660)*0.5%+58%))),"") -> 0.915
A23: Credits Earned On or After 10/01/2014 | J23: =IF(COUNTIF(J9,"1.*"),"ER Benefit Prior to 09/01/2011","") -> ER Benefit Prior to 09/01/2011 | N23: =IF(COUNTIF(J9,"1.*"),(N21*N22),"") -> 742.6506
A24: =SUM('Pro-Rata Worksheet'!B6:B26) -> 3.5 | C24: =IF(COUNTIF(A32,"1.*"),B24*D37,"") | E24: =IF(COUNTIF(E32,"1.*"),D24*H37,"") | F24: 105 | G24: =IF(AND(COUNTIF(A32,"1.*"),COUNTIF(E32,"1.*")),SUM(A24*F24)-((C24*F24))+(E24*F24),IF(COUNTIF(A32,"1.*"),SUM(A24*F24)-(C24*F24),IF(COUNTIF(E32,"1.*"),SUM(A24*F24)-(E24*F24),A24*F24))) -> 367.5 | H24: =IF(COUNTIF(A32,"1.*"),SUM(C24*F24),"") | I24: =IF(COUNTIF(E32,"1.*"),SUM(D24*F24),"") | J24: =IF(COUNTIF(J9,"2.*"),"","Member Benefit from 09/01/2011 to 09/30/2014:") -> Member Benefit from 09/01/2011 to 09/30/2014: | M24: =IF(COUNTIF(J9,"2.*"),"",SUM(A20:A21)) -> 0.08 | N24: =IF(COUNTIF(J9,"2.*"),"",IF(AND(COUNTIF(A32,"1.*"),COUNTIF(E32,"1.*")),N12-(H22+I22),IF(AND(COUNTIF(A32,"1.*"),COUNTIF(E32,"2.*")),N12-(H22+(N12*H40)),IF(AND(COUNTIF(A32,"1.*"),COUNTIF(E32,"3.*")),N12-H22,IF(AND(COUNTIF(A32,"1.*"),COUNTIF(E32,"4.*")),N12-(H22+(N12*H40)),IF(AND(COUNTIF(A32,"2.*"),COUNTIF(E32,"1.*")),N12-((N12*D40)+I22),IF(AND(COUNTIF(A32,"2.*"),COUNTIF(E32,"2.*")),N12-((N12*D40)+(N12*H40)),IF(AND(COUNTIF(A32,"2.*"),COUNTIF(E32,"3.*")),N12-(N12*D40),IF(AND(COUNTIF(A32,"2.*"),COUNTIF(E32,"4.*")),N12-((N12*D40)+(N12*H40)),IF(AND(COUNTIF(A32,"3.*"),COUNTIF(E32,"1.*")),N12-I22,IF(AND(COUNTIF(A32,"3.*"),COUNTIF(E32,"2.*")),N12-(N12*H40),IF(AND(COUNTIF(A32,"3.*"),COUNTIF(E32,"3.*")),N12,IF(AND(COUNTIF(A32,"3.*"),COUNTIF(E32,"4.*")),N12-(N12*H40),IF(AND(COUNTIF(A32,"4.*"),COUNTIF(E32,"1.*")),N12-((N12*D40)+I22),IF(AND(COUNTIF(A32,"4.*"),COUNTIF(E32,"2.*")),N12-((N12*D40)+(N12*H40)),IF(AND(COUNTIF(A32,"4.*"),COUNTIF(E32,"3.*")),N12-(N12*D40),IF(AND(COUNTIF(A32,"4.*"),COUNTIF(E32,"4.*")),N12-((N12*D40)+(N12*H40)),IF(COUNTIF(A32,"1.*"),N12-H22,IF(OR(COUNTIF(A32,"2.*"),COUNTIF(A32,"4.*")),N12-(N12*D40),IF(COUNTIF(E32,"1.*"),N12-I22,IF(OR(COUNTIF(E32,"2.*"),COUNTIF(E32,"4.*")),N12-(N12*H40),SUM(A20*F20,A21*F21)))))))))))))))))))))) -> 7.2
C25: =IF(COUNTIF(A32,"1.*"),B25*D37,"") | E25: =IF(COUNTIF(E32,"1.*"),D25*H37,"") | F25: 125 | G25: =IF(AND(COUNTIF(A32,"1.*"),COUNTIF(E32,"1.*")),SUM(A25*F25)-((C25*F25)+(E25*F25)),IF(COUNTIF(A32,"1.*"),SUM(A25*F25)-(C25*F25),IF(COUNTIF(E32,"1.*"),SUM(A25*F25)-(E25*F25),A25*F25))) -> 0 | H25: =IF(COUNTIF(A32,"1.*"),SUM(C25*F25),"") | I25: =IF(COUNTIF(E32,"1.*"),SUM(D25*F25),"") | J25: =IF(OR(COUNTIF(J9,"1.*"),COUNTIF(J9,"3.*")),"ER Factor","") -> ER Factor | N25: =IF(OR(COUNTIF(J9,"1.*"),COUNTIF(J9,"3.*")),IF(DATEDIF(C3,C5,"m")<=600,(DATEDIF(C3,C5,"m")-540)*0.1%+22%,IF(DATEDIF(C3,C5,"m")<=660,(DATEDIF(C3,C5,"m")-600)*0.2%+28%,IF((DATEDIF(C3,C5,"m")-660)*0.5%+40%>=100%,100%,(DATEDIF(C3,C5,"m")-660)*0.5%+40%))),"") -> 0.735
C26: =IF(COUNTIF(A32,"1.*"),B26*D37,"") | E26: =IF(COUNTIF(E32,"1.*"),D26*H37,"") | F26: 135 | G26: =IF(AND(COUNTIF(A32,"1.*"),COUNTIF(E32,"1.*")),SUM(A26*F26)-((C26*F26)+(E26*F26)),IF(COUNTIF(A32,"1.*"),SUM(A26*F26)-(C26*F26),IF(COUNTIF(E32,"1.*"),SUM(A26*F26)-(E26*F26),A26*F26))) -> 0 | H26: =IF(COUNTIF(A32,"1.*"),SUM(C26*F26),"") | I26: =IF(COUNTIF(E32,"1.*"),SUM(D26*F26),"") | J26: =IF(OR(COUNTIF(J9,"1.*"),COUNTIF(J9,"3.*")),"ER Benefit from 09/01/2011 to 09/30/2014","") -> ER Benefit from 09/01/2011 to 09/30/2014 | N26: =IF(OR(COUNTIF(J9,"1.*"),COUNTIF(J9,"3.*")),N12*N25,"") -> 5.292
C27: =IF(COUNTIF(A32,"1.*"),B27*D37,"") | E27: =IF(COUNTIF(E32,"1.*"),D27*H37,"") | G27: =IF(AND(COUNTIF(A32,"1.*"),COUNTIF(E32,"1.*")),SUM(A27*F27)-((C27*F27)+(E27*F27)),IF(COUNTIF(A32,"1.*"),SUM(A27*F27)-(C27*F27),IF(COUNTIF(E32,"1.*"),SUM(A27*F27)-(E27*F27),A27*F27))) -> 0 | H27: =IF(COUNTIF(A32,"1.*"),SUM(C27*F27),"") | I27: =IF(COUNTIF(E32,"1.*"),SUM(D27*F27),"") | J27: =IF(COUNTIF(J9,"2.*"),"","Member Benefit on and After 10/01/2014:") -> Member Benefit on and After 10/01/2014: | M27: =IF(COUNTIF(J9,"2.*"),"",SUM(A24:A29)) -> 3.5 | N27: =IF(COUNTIF(J9,"2.*"),"",IF(AND(COUNTIF(A32,"1.*"),COUNTIF(E32,"1.*")),N13-(H30+I30),IF(AND(COUNTIF(A32,"1.*"),COUNTIF(E32,"2.*")),N13-(H30+(N13*H40)),IF(AND(COUNTIF(A32,"1.*"),COUNTIF(E32,"3.*")),N13-H30,IF(AND(COUNTIF(A32,"1.*"),COUNTIF(E32,"4.*")),N13-(H30+(N13*H40)),IF(AND(COUNTIF(A32,"2.*"),COUNTIF(E32,"1.*")),N13-((N13*D40)+I30),IF(AND(COUNTIF(A32,"2.*"),COUNTIF(E32,"2.*")),N13-((N13*D40)+(N13*H40)),IF(AND(COUNTIF(A32,"2.*"),COUNTIF(E32,"3.*")),N13-(N13*D40),IF(AND(COUNTIF(A32,"2.*"),COUNTIF(E32,"4.*")),N13-((N13*D40)+(N13*H40)),IF(AND(COUNTIF(A32,"3.*"),COUNTIF(E32,"1.*")),N13-I30,IF(AND(COUNTIF(A32,"3.*"),COUNTIF(E32,"2.*")),N13-(N13*H40),IF(AND(COUNTIF(A32,"3.*"),COUNTIF(E32,"3.*")),N13,IF(AND(COUNTIF(A32,"3.*"),COUNTIF(E32,"4.*")),N13-(N13*H40),IF(AND(COUNTIF(A32,"4.*"),COUNTIF(E32,"1.*")),N13-((N13*D40)+I18),IF(AND(COUNTIF(A32,"4.*"),COUNTIF(E32,"2.*")),N13-((N13*D40)+(N13*H40)),IF(AND(COUNTIF(A32,"4.*"),COUNTIF(E32,"3.*")),N13-(N13*D40),IF(AND(COUNTIF(A32,"4.*"),COUNTIF(E32,"4.*")),N13-((N13*D40)+(N13*H40)),IF(COUNTIF(A32,"1.*"),N13-H30,IF(OR(COUNTIF(A32,"2.*"),COUNTIF(A32,"4.*")),N13-(N13*D40),IF(COUNTIF(E32,"1.*"),N13-I30,IF(OR(COUNTIF(E32,"2.*"),COUNTIF(E32,"4.*")),N13-(N13*H40),SUM(A24*F24,A25*F25,A26*F26,A27*F27,A28*F28,A28*F28,A29*F29)))))))))))))))))))))) -> 367.5
C28: =IF(COUNTIF(A32,"1.*"),B28*D37,"") | E28: =IF(COUNTIF(E32,"1.*"),D28*H37,"") | G28: =IF(AND(COUNTIF(A32,"1.*"),COUNTIF(E32,"1.*")),SUM(A28*F28)-((C28*F28)+(E28*F28)),IF(COUNTIF(A32,"1.*"),SUM(A28*F28)-(C28*F28),IF(COUNTIF(E32,"1.*"),SUM(A28*F28)-(E28*F28),A28*F28))) -> 0 | H28: =IF(COUNTIF(A32,"1.*"),SUM(C28*F28),"") | I28: =IF(COUNTIF(E32,"1.*"),SUM(D28*F28),"") | J28: =IF(OR(COUNTIF(J9,"1.*"),COUNTIF(J9,"3.*"),COUNTIF(J9,"7.*")),"ER Factor","") -> ER Factor | N28: =IF(OR(COUNTIF(J9,"1.*"),COUNTIF(J9,"3.*"),COUNTIF(J9,"7.*")),IF(DATEDIF(C3,C5,"m")<=600,(DATEDIF(C3,C5,"m")-540)*0.1%+22%,IF(DATEDIF(C3,C5,"m")<=660,(DATEDIF(C3,C5,"m")-600)*0.2%+28%,IF((DATEDIF(C3,C5,"m")-660)*0.5%+40%>=100%,100%,(DATEDIF(C3,C5,"m")-660)*0.5%+40%))),"") -> 0.735
C29: =IF(COUNTIF(A32,"1.*"),B29*D37,"") | E29: =IF(COUNTIF(E32,"1.*"),D29*H37,"") | G29: =IF(AND(COUNTIF(A32,"1.*"),COUNTIF(E32,"1.*")),SUM(A29*F29)-((C29*F29)+(E29*F29)),IF(COUNTIF(A32,"1.*"),SUM(A29*F29)-(C29*F29),IF(COUNTIF(E32,"1.*"),SUM(A29*F29)-(E29*F29),A29*F29))) -> 0 | H29: =IF(COUNTIF(A32,"1.*"),SUM(C29*F29),"") | I29: =IF(COUNTIF(E32,"1.*"),SUM(D29*F29),"") | J29: =IF(OR(COUNTIF(J9,"1.*"),COUNTIF(J9,"3.*"),COUNTIF(J9,"7.*")),"ER Benefit on or After 10/01/2014","") -> ER Benefit on or After 10/01/2014 | N29: =IF(OR(COUNTIF(J9,"1.*"),COUNTIF(J9,"3.*"),COUNTIF(J9,"7.*")),N13*N28,"") -> 270.1125
A30: =SUM(A24:A29) -> 3.5 | B30: =IF(COUNTIF(A32,"1.*"),SUM(B24:B29),"") | C30: =IF(COUNTIF(A32,"1.*"),SUM(C24:C29),"") | D30: =IF(COUNTIF(E32,"1.*"),SUM(D24:D29),"") | E30: =IF(COUNTIF(E32,"1.*"),SUM(E24:E29),"") | F30: Subtotal | G30: =SUM(G24:G29) -> 367.5 | H30: =IF(COUNTIF(A32,"1.*"),SUM(H24:H29),"") | I30: =IF(COUNTIF(E32,"1.*"),SUM(I24:I29),"") | J30: =IF(COUNTIF(A32,"3.*"),"AP 1 Pay Status Reduction","") | N30: =IF(COUNTIF(A32,"3.*"),D38,"")
A31: =SUM(A18,A22,A30) -> 10.65 | B31: =IF(COUNTIF(A32,"1.*"),SUM(B18,B22,B30),"") | C31: =IF(COUNTIF(A32,"1.*"),SUM(C18,C22,C30),"") | D31: =IF(COUNTIF(E32,"1.*"),SUM(D18,D22,D30),"") | E31: =IF(COUNTIF(E32,"1.*"),SUM(E18,E22,E30),"") | F31: Total | G31: =SUM(G18,G22,G30) -> 1186.34 | H31: =IF(COUNTIF(A32,"1.*"),SUM(H18,H22,H30),"") | I31: =IF(COUNTIF(E32,"1.*"),SUM(I18,I22,I30),"") | J31: =IF(COUNTIF(E32,"3.*"),"AP 2 Pay Status Reduction","") | N31: =IF(COUNTIF(E32,"3.*"),H38,"")
A32: _ | E32: _ | J32: =IF(AND(COUNTIF(A32,"_"),COUNTIF(E32,"_")),"","Member Monthly Benefit After AP Reductions:") | N32: =IF(AND(COUNTIF(A32,"_"),COUNTIF(E32,"_")),"",IF(COUNTIF(J9,"1.*"),SUM(N23,N26,N29),IF(COUNTIF(J9,"3.*"),SUM(N21,N26,N29),IF(COUNTIF(J9,"7.*"),SUM(N21,N24,N29),SUM(N21,N24,N27)))))
A33: =IF(COUNTIF(A32,"_"),"","AP 1 QDRO Calculation") | E33: =IF(COUNTIF(E32,"_"),"","AP 2 QDRO Calculation") | J33: =IF(AND(COUNTIF(A32,"_"),COUNTIF(E32,"_")),"","Member 13th Check After AP Reductions:") | N33: =IF(AND(COUNTIF(A32,"_"),COUNTIF(E32,"_")),"",IF(COUNTIF(J9,"1.*"),SUM(N23,N26),IF(COUNTIF(J9,"3.*"),SUM(N21,N26),SUM(N21,N24))))
A34: =IF(COUNTIF(A32,"_"),"","AP 1 Name:") | B34: Heather M. Thogersen | C34: =IF(COUNTIF(A32,"_"),"","AP 1 DOB:") | D34: 31610 | E34: =IF(COUNTIF(E32,"_"),"","AP 2 Name:") | G34: =IF(COUNTIF(E32,"_"),"","AP 2 DOB:") | J34: =IF(AND(COUNTIF(A32,"_"),COUNTIF(E32,"_")),"",IF(OR(COUNTIF(J9,"1.*"),COUNTIF(J9,"3.*"),COUNTIF(J9,"7.*")),"Member Benefit Deferred at Age 65 After AP Reductions:","")) | N34: =IF(AND(COUNTIF(A32,"_"),COUNTIF(E32,"_")),"",IF(OR(COUNTIF(J9,"1.*"),COUNTIF(J9,"3.*"),COUNTIF(J9,"7.*")),SUM(N21,N24,N27),""))
A35: =IF(COUNTIF(A32,"_"),"","DOM:") | B35: 40733 | C35: =IF(COUNTIF(A32,"_"),"","DOS:") | D35: 44569 | E35: =IF(COUNTIF(E32,"_"),"","DOM:") | G35: =IF(COUNTIF(E32,"_"),"","DOS:") | J35: =IF(AND(COUNTIF(A32,"_"),COUNTIF(E32,"_")),"",IF(OR(COUNTIF(J9,"1.*"),COUNTIF(J9,"3.*"),COUNTIF(J9,"7.*")),"Member 13th Check After AP Reductions:","")) | N35: =IF(AND(COUNTIF(A32,"_"),COUNTIF(E32,"_")),"",IF(OR(COUNTIF(J9,"1.*"),COUNTIF(J9,"3.*"),COUNTIF(J9,"7.*")),SUM(N21,N24),""))
A36: =IF(COUNTIF(A32,"_"),"",IF(COUNTIF(A32,"2.*"),"Total Service Credits:",IF(COUNTIF(A32,"4.*"),"Total Months Worked",""))) | B36: =IF(COUNTIF(A32,"_"),"",IF(COUNTIF(A32,"2.*"),SUM(A11:A17,A20:A21,A24:A29),IF(COUNTIF(A32,"4.*"),SUM('QDRO Month Calc'!B4:B69),""))) | C36: =IF(COUNTIF(A32,"_"),"",IF(COUNTIF(A32,"2.*"),"Total Credits EDM:",IF(COUNTIF(A32,"3.*"),"",IF(COUNTIF(A32,"4.*"),"Total Months Worked During Marriage","")))) | D36: 8.17 | E36: =IF(COUNTIF(E32,"_"),"",IF(COUNTIF(E32,"2.*"),"Total Service Credits:",IF(COUNTIF(E32,"4.*"),"Total Months Worked",""))) | F36: =IF(COUNTIF(E32,"_"),"",IF(COUNTIF(E32,"2.*"),SUM(A11:A17,A20:A21,A24:A29),IF(COUNTIF(E32,"4.*"),SUM('QDRO Month Calc'!H4:H69),""))) | G36: =IF(COUNTIF(E32,"_"),"",IF(COUNTIF(E32,"2.*"),"Total Credits EDM:",IF(COUNTIF(E32,"3.*"),"",IF(COUNTIF(E32,"4.*"),"Total Months Worked During Marriage","")))) | H36: =IF(COUNTIF(E32,"4.*"),SUM('QDRO Month Calc'!I4:I69),IF(COUNTIF(E32,"2.*"),D31,"")) | J36: =IF(COUNTIF(C7,""),"",IF(COUNTIF(J9,"1.*"),"Early Retirement H&W Pension Options",IF(COUNTIF(J9,"2.*"),"Regular at 62 H&W Pension Options",IF(COUNTIF(J9,"3.*"),"Regular at 62 & Early H&W Pension Options",IF(COUNTIF(J9,"4.*"),"Regular at 62 & Disability H&W Pension Options",IF(COUNTIF(J9,"5.*"),"Regular at 65 H&W Pension Options",IF(COUNTIF(J9,"6.*"),"Disability H&W Pension Options",IF(COUNTIF(J9,"7.*"),"Service Pre-Age 55 & Early H&W Pension Options",IF(COUNTIF(J9,"8.*"),"Service Pre-Age 55 & Disability H&W Pension Options",IF(COUNTIF(J9,"9.*"),"Service H&W Pension Options","Additional H&W Options")))))))))) -> Early Retirement H&W Pension Options
A37: =IF(COUNTIF(A32,"_"),"",IF(OR(COUNTIF(A32,"2.*"),COUNTIF(A32,"4.*")),"Community Property Percentage:","")) | B37: =IF(COUNTIF(A32,"_"),"",IF(OR(COUNTIF(A32,"2.*"),COUNTIF(A32,"4.*")),ROUNDDOWN(SUM(D36/B36),4),"")) | C37: =IF(COUNTIF(A32,"_"),"",IF(OR(COUNTIF(A32,"1.*"),COUNTIF(A32,"2.*"),COUNTIF(A32,"4.*")),"Percentage Amount Awarded to AP 1:","")) | D37: 0.5 | E37: =IF(COUNTIF(E32,"_"),"",IF(OR(COUNTIF(E32,"2.*"),COUNTIF(E32,"4.*")),"Community Property Percentage:","")) | F37: =IF(COUNTIF(E32,"_"),"",IF(OR(COUNTIF(E32,"2.*"),COUNTIF(E32,"4.*")),ROUNDDOWN(SUM(H36/F36),4),"")) | G37: =IF(COUNTIF(E32,"_"),"",IF(OR(COUNTIF(E32,"1.*"),COUNTIF(E32,"2.*"),COUNTIF(E32,"4.*")),"Percentage Amount Awarded to AP 2:","")) | H37: 0.5 | J37: =IF(COUNTIF(C7,""),"","Option") -> Option | K37: =IF(COUNTIF(C7,""),"","Factor") -> Factor | L37: =IF(COUNTIF(C7,""),"","Member Benefit") -> Member Benefit | M37: =IF(COUNTIF(C7,""),"","Spouse Benefit") -> Spouse Benefit
A38: =IF(COUNTIF(A32,"_"),"",IF(COUNTIF(A32,"3.*"),"AP 1 Awarded Monthly Amount:","")) | E38: =IF(COUNTIF(E32,"_"),"",IF(COUNTIF(E32,"3.*"),"AP 2 Awarded Monthly Amount:","")) | J38: =IF(COUNTIF(C7,""),"","50%") -> 50% | K38: =IF(COUNTIF(C7,""),"",IF(COUNTIF(J9,"4.*"),IF(COUNTIF(I8,"*Younger*"),100%-8%-(H8*0.4%),IF(100%-8%+(H8*0.4%)>100%,100%,100%-8%+(H8*0.4%)))*100&"% / "&IF(COUNTIF(I8,"*Younger*"),100%-18%-(H8*0.4%),IF(100%-18%+(H8*0.4%)>100%,100%,100%-18%+(H8*0.4%)))*100&"%",IF(COUNTIF(J9,"6.*"),IF(COUNTIF(I8,"*Younger*"),100%-18%-(H8*0.4%),IF(100%-18%+(H8*0.4%)>100%,100%,100%-18%+(H8*0.4%))),IF(COUNTIF(J9,"8.*"),IF(COUNTIF(I8,"*Younger*"),100%-8%-(H8*0.4%),IF(100%-8%+(H8*0.4%)>100%,100%,100%-8%+(H8*0.4%)))*100&"% / "&IF(COUNTIF(I8,"*Younger*"),100%-18%-(H8*0.4%),IF(100%-18%+(H8*0.4%)>100%,100%,100%-18%+(H8*0.4%)))*100&"%",IF(COUNTIF(I8,"*Younger*"),100%-8%-(H8*0.4%),IF(100%-8%+(H8*0.4%)>100%,100%,100%-8%+(H8*0.4%))))))) -> 0.872 | L38: =IF(COUNTIF(C7,""),"",IF(COUNTIF(J9,"1.*"),(N32)*K38,IF(COUNTIF(J9,"2.*"),(N32)*K38,IF(COUNTIF(J9,"3.*"),(N32)*K38,IF(COUNTIF(J9,"5.*"),(N32)*K38,IF(COUNTIF(J9,"6.*"),(N32)*K38,IF(COUNTIF(J9,"7.*"),(N32)*K38,IF(COUNTIF(J9,"8.*"),(N11+N12)*IF(COUNTIF(I8,"*Younger*"),100%-8%-(H8*0.4%),IF(100%-8%+(H8*0.4%)>100%,100%,100%-8%+(H8*0.4%)))+(N13*IF(COUNTIF(I8,"*Younger*"),100%-18%-(H8*0.4%),IF(100%-18%+(H8*0.4%)>100%,100%,100%-18%+(H8*0.4%)))),IF(COUNTIF(J9,"4.*"),N11*IF(COUNTIF(I8,"*Younger*"),100%-8%-(H8*0.4%),IF(100%-8%+(H8*0.4%)>100%,100%,100%-8%+(H8*0.4%)))+(N12+N13)*IF(COUNTIF(I8,"*Younger*"),100%-18%-(H8*0.4%),IF(100%-18%+(H8*0.4%)>100%,100%,100%-18%+(H8*0.4%))),IF(COUNTIF(J9,"9.*"),(N32)*K38,"")))))))))) -> #VALUE! | M38: =IF(COUNTIF(C7,""),"",L38*J38) -> #VALUE!
A39: =IF(COUNTIF(A32,"_"),"",IF(COUNTIF(A32,"3.*"),"AP 1 Awarded 13th Check Amount:","")) | E39: =IF(COUNTIF(E32,"_"),"",IF(COUNTIF(E32,"3.*"),"AP 2 Awarded 13th Check Amount:","")) | J39: =IF(COUNTIF(C7,""),"","13th Check") -> 13th Check | K39: =IF(COUNTIF(C7,""),"",IF(COUNTIF(J9,"4.*"),IF(COUNTIF(I8,"*Younger*"),100%-8%-(H8*0.4%),IF(100%-8%+(H8*0.4%)>100%,100%,100%-8%+(H8*0.4%)))*100&"% / "&IF(COUNTIF(I8,"*Younger*"),100%-18%-(H8*0.4%),IF(100%-18%+(H8*0.4%)>100%,100%,100%-18%+(H8*0.4%)))*100&"%",IF(COUNTIF(J9,"6.*"),IF(COUNTIF(I8,"*Younger*"),100%-18%-(H8*0.4%),IF(100%-18%+(H8*0.4%)>100%,100%,100%-18%+(H8*0.4%))),IF(COUNTIF(J9,"8.*"),IF(COUNTIF(I8,"*Younger*"),100%-8%-(H8*0.4%),IF(100%-8%+(H8*0.4%)>100%,100%,100%-8%+(H8*0.4%)))*100&"% / "&IF(COUNTIF(I8,"*Younger*"),100%-18%-(H8*0.4%),IF(100%-18%+(H8*0.4%)>100%,100%,100%-18%+(H8*0.4%)))*100&"%",IF(COUNTIF(I8,"*Younger*"),100%-8%-(H8*0.4%),IF(100%-8%+(H8*0.4%)>100%,100%,100%-8%+(H8*0.4%))))))) -> 0.872 | L39: =IF(COUNTIF(C7,""),"",IF(COUNTIF(J9,"1.*"),(N33)*K39,IF(COUNTIF(J9,"2.*"),(N33)*K39,IF(COUNTIF(J9,"3.*"),(N33)*K39,IF(COUNTIF(J9,"5.*"),(N33)*K39,IF(COUNTIF(J9,"6.*"),(N33)*K39,IF(COUNTIF(J9,"7.*"),(N33)*K39,IF(COUNTIF(J9,"8.*"),(N11+N12)*IF(COUNTIF(I8,"*Younger*"),100%-8%-(H8*0.4%),IF(100%-8%+(H8*0.4%)>100%,100%,100%-8%+(H8*0.4%))),IF(COUNTIF(J9,"4.*"),N11*IF(COUNTIF(I8,"*Younger*"),100%-8%-(H8*0.4%),IF(100%-8%+(H8*0.4%)>100%,100%,100%-8%+(H8*0.4%)))+(N12)*IF(COUNTIF(I8,"*Younger*"),100%-18%-(H8*0.4%),IF(100%-18%+(H8*0.4%)>100%,100%,100%-18%+(H8*0.4%))),IF(COUNTIF(J9,"9.*"),(N33)*K39,"")))))))))) -> #VALUE! | M39: =IF(COUNTIF(C7,""),"",L39*J38) -> #VALUE!
